Workbook

Sheet 見積内訳書
L1: お客様名
L2: 浅野誠一郎
L3: 工事場所入力
L5: 見積有効期限
L7: 見積有効期限
L9: 担当者
L12: 横自由入力
K13: ←
L16: 変更禁止 ↓↓
L17: 会社 情報
L18: ラグズ建築
L19: 〒500-8388
L20: 岐阜県岐阜市今嶺４丁目５−２０
E33: 内 訳 明 細 書 | J33: 1 | K33: 日付 | L33: 担当者 | S33: / | U33: ※下記二十枠部分触るな！
A35: 名 称 | E35: 数量 | F35: 呼称 | G35: 単 価 | H35: 金 額 | I35: 定価 | J35: 備 考 | K35: 職人 | L35: 人工 | M35: 人当 | N35: 費用 | O35: 材料 | P35: 数量 | Q35: Net | R35: 費用 | S35: 原価 | T35: 粗利率 | U35: 材料
N36: =L36*M36 -> 0 | R36: =P36*Q36 -> 0 | S36: =N36+R36 -> 0 | T36: =IF(H36<>0,1-(S36/H36),0) -> 0 | U36: 養生 | V36: =BD368 -> 0 | W36: =BE368 -> 0
A37: 1 | B37: 仮設工事 | E37: 1 | F37: 式 | H37: =H82 -> 0 | O37: 粗利率３５％（税抜） | R37: =B37 -> 仮設工事 | S37: =S82 -> 0 | T37: =IF(H37<>0,1-(S37/H37),0) -> 0 | U37: 産廃 | V37: =BF368 -> 0 | W37: =BG368 -> 0
A38: 2 | E38: 1 | F38: 式 | H38: =H108 -> 0 | O38: =SUM(K41/0.65) -> 0 | R38: =B38 -> 0 | S38: =S108 -> 0 | T38: =IF(H38<>0,1-(S38/H38),0) -> 0 | U38: 材木 | V38: =BH368 -> 1 | W38: =BI368 -> 0
A39: 3 | E39: 1 | F39: 式 | H39: =H134 -> 0 | R39: =B39 -> 0 | S39: =S134 -> 0 | T39: =IF(H39<>0,1-(S39/H39),0) -> 0 | U39: 建材 | V39: =BJ368 -> 0 | W39: =BK368 -> 0
A40: 4 | E40: 1 | F40: 式 | H40: =H160 -> 0 | K40: 原価 | O40: 粗利率３５％（税込） | R40: =B40 -> 0 | S40: =S160 -> 0 | T40: =IF(H40<>0,1-(S40/H40),0) -> 0 | U40: 電材 | V40: =BL368 -> 0 | W40: =BM368 -> 0
A41: 5 | E41: 1 | F41: 式 | H41: =H186 -> 0 | K41: =SUM(S55,K38) -> 0 | O41: =SUM(O38*1.1) -> 0 | R41: =B41 -> 0 | S41: =S186 -> 0 | T41: =IF(H41<>0,1-(S41/H41),0) -> 0 | U41: 住設 | V41: =BN368 -> 0 | W41: =BO368 -> 0
A42: 6 | E42: 1 | F42: 式 | H42: =H212 -> 0 | R42: =B42 -> 0 | S42: =S212 -> 0 | T42: =IF(H42<>0,1-(S42/H42),0) -> 0 | U42: サッシ | V42: =BP368 -> 0 | W42: =BQ368 -> 0
A43: 7 | E43: 1 | F43: 式 | H43: =H238 -> 0 | K43: 諸経費別 合計 | O43: 見積時税抜き粗利高 | R43: =B43 -> 0 | S43: =S238 -> 0 | T43: =IF(H43<>0,1-(S43/H43),0) -> 0 | U43: 足場 | V43: =BR368 -> 0 | W43: =BS368 -> 0
A44: 8 | E44: 1 | F44: 式 | H44: =H264 -> 0 | K44: =SUM(H37:H49) -> 0 | O44: =H54-S55 -> 0 | R44: =B44 -> 0 | S44: =S264 -> 0 | T44: =IF(H44<>0,1-(S44/H44),0) -> 0 | U44: 外壁 | V44: =BT368 -> 0 | W44: =BU368 -> 0
A45: 9 | E45: 1 | F45: 式 | H45: =H290 -> 0 | R45: =B45 -> 0 | S45: =S290 -> 0 | T45: =IF(H45<>0,1-(S45/H45),0) -> 0 | U45: 外構 | V45: =BV368 -> 0 | W45: =BW368 -> 0
A46: 10 | E46: 1 | F46: 式 | H46: =H316 -> 0 | K46: 粗利率（％） | R46: =B46 -> 0 | S46: =S316 -> 0 | T46: =IF(H46<>0,1-(S46/H46),0) -> 0 | U46: 雑費 | V46: =BX368 -> 0 | W46: =BY368 -> 0
A47: 11 | E47: 1 | F47: 式 | H47: =H342 -> 0 | K47: =SUM(1-K41/H54) -> #DIV/0! | R47: =B47 -> 0 | S47: =S342 -> 0 | T47: =IF(H47<>0,1-(S47/H47),0) -> 0 | U47: ガス | V47: =BZ368 -> 0 | W47: =CA368 -> 0
H48: =H368 -> 0 | N48: ※下記二十枠部分触るな！ | R48: =B48 -> 0 | S48: =S368 -> 0 | T48: =IF(H48<>0,1-(S48/H48),0) -> 0 | U48: ラグズ | V48: =CB368 -> 0 | W48: =CC368 -> 0
K49: 解体 | L49: =V368 -> 0 | M49: =W368 -> 0 | N49: 仮設 | O49: =AN368 -> 0 | P49: =AO368 -> 0 | R49: =B49 -> 0 | T49: =IF(H49<>0,1-(S49/H49),0) -> 0 | U49: 解体 | V49: =CD368 -> 0 | W49: =CE368 -> 0
K50: 設備 | L50: =X368 -> 0 | M50: =Y368 -> 0 | N50: 養生 | O50: =AP368 -> 0 | P50: =AQ368 -> 0 | T50: =IF(H50<>0,1-(S50/H50),0) -> 0 | U50: 大工 | V50: =CF368 -> 0 | W50: =CG368 -> 0
K51: 電気 | L51: =Z368 -> 0 | M51: =AA368 -> 0 | N51: 足場 | O51: =AR368 -> 0 | P51: =AS368 -> 0 | R51: =B51 -> 0 | T51: =IF(H51<>0,1-(S51/H51),0) -> 0 | U51: 電気 | V51: =CH368 -> 0 | W51: =CI368 -> 0
B52: 諸 経 費 | H52: =K44*0.08 -> 0 | K52: ガス | L52: =AB368 -> 0 | M52: =AC368 -> 0 | N52: 板金 | O52: =AT368 -> 0 | P52: =AU368 -> 0 | R52: ヨビ | S52: =H54*0.03 -> 0 | U52: 設備 | V52: =CJ368 -> 0 | W52: =CK368 -> 0
B53: 端 数 値 引 | K53: 大工 | L53: =AD368 -> 0 | M53: =AE368 -> 0 | N53: 屋根 | O53: =AV368 -> 0 | P53: =AW368 -> 0 | R53: =B53 -> 端 数 値 引 | T53: =IF(H53<>0,1-(S53/H53),0) -> 0 | U53: クロス | V53: =CL368 -> 0 | W53: =CM368 -> 0
B54: 合 計 | G54: =SUM(G37:G53) -> 0 | H54: =SUM(H37:H53) -> 0 | K54: クロス | L54: =AF368 -> 0 | M54: =AG368 -> 0 | N54: 塗装 | O54: =AX368 -> 0 | P54: =AY368 -> 0 | T54: =IF(H54<>0,1-(S54/H54),0) -> 0 | U54: 左官 | V54: =CN368 -> 0 | W54: =CO368 -> 0
B55: 消 費 税 | D55: 0.1 | G55: =G54*0.05 -> 0 | H55: =H54*10% -> 0 | K55: 左官 | L55: =AH368 -> 0 | M55: =AI368 -> 0 | N55: 建具 | O55: =AZ368 -> 0 | P55: =BA368 -> 0 | Q55: ゴミ経費なし 原価 | R55: 小計 | S55: =SUM(S37:S54) -> 0 | U55: 清掃 | V55: =CP368 -> 0 | W55: =CQ368 -> 0
K56: 清掃 | L56: =AJ368 -> 0 | M56: =AK368 -> 0 | N56: サッシ | O56: =BB368 -> 0 | P56: =BC368 -> 0 | T56: =IF(H56<>0,1-(S56/H56),0) -> 0 | U56: 塗装 | V56: =CR368 -> 0 | W56: =CS368 -> 0
B57: 総 合 計 | G57: =SUM(G54:G56) -> 0 | H57: =SUM(H54:H56) -> 0 | K57: 床 | L57: =AL368 -> 0 | M57: =AM368 -> 0 | U57: 建具 | V57: =CT368 -> 0 | W57: =CU368 -> 0
I58: ラグズ建築 | U58: 畳 | V58: =CV368 -> 0 | W58: =CW368 -> 0
E59: 内 訳 明 細 書 | J59: 2 | K59: 日付 | S59: / | U59: 申請 | V59: =CX368 -> 0 | W59: =CY368 -> 0
A61: 名 称 | E61: 数量 | F61: 呼称 | G61: 単 価 | H61: 金 額 | I61: 定価 | J61: 備 考 | K61: 職人 | L61: 人工 | M61: 人当 | N61: 費用① | O61: 材料 | P61: 数量 | Q61: 単価 | R61: 費用② | S61: 原価 | T61: 粗利率 | U61: 枠より右は絶対触らない。 | V61: =K49 -> 解体 | X61: =K50 -> 設備 | Z61: =K51 -> 電気 | AB61: =K52 -> ガス | AD61: =K53 -> 大工 | AF61: =K54 -> クロス | AH61: =K55 -> 左官 | AJ61: =K56 -> 清掃 | AL61: =K57 -> 床 | AN61: =N49 -> 仮設 | AP61: =N50 -> 養生 | AR61: =N51 -> 足場 | AT61: =N52 -> 板金 | AV61: =N53 -> 屋根 | AX61: =N54 -> 塗装 | AZ61: =N55 -> 建具 | BB61: =N56 -> サッシ | BD61: =U36 -> 養生 | BF61: =U37 -> 産廃 | BH61: =U38 -> 材木 | BJ61: =U39 -> 建材 | BL61: =U40 -> 電材 | BN61: =U41 -> 住設 | BP61: =U42 -> サッシ | BR61: =U43 -> 足場 | BT61: =U44 -> 外壁 | BV61: =U45 -> 外構 | BX61: =U46 -> 雑費 | BZ61: =U47 -> ガス | CB61: =U48 -> ラグズ | CD61: =U49 -> 解体 | CF61: =U50 -> 大工 | CH61: =U51 -> 電気 | CJ61: =U52 -> 設備 | CL61: =U53 -> クロス | CN61: =U54 -> 左官 | CP61: =U55 -> 清掃 | CR61: =U56 -> 塗装 | CT61: =U57 -> 建具 | CV61: =U58 -> 畳 | CX61: =U59 -> 申請
A62: =A37 -> 1 | B62: =B37 -> 仮設工事 | N62: =L62*M62 -> 0 | R62: =Q62*P62 -> 0 | S62: =R62+N62 -> 0 | T62: =IF(H62<>0,1-(S62/H62),0) -> 0 | V62: =IF($K62=$V$61,$L62,0) -> 0 | W62: =IF($K62=$V$61,$N62,0) -> 0 | X62: =IF($K62=$X$61,$L62,0) -> 0 | Y62: =IF($K62=$X$61,$N62,0) -> 0 | Z62: =IF($K62=$Z$61,$L62,0) -> 0 | AA62: =IF($K62=$Z$61,$N62,0) -> 0 | AB62: =IF($K62=$AB$61,$L62,0) -> 0 | AC62: =IF($K62=$AB$61,$N62,0) -> 0 | AD62: =IF($K62=$AD$61,$L62,0) -> 0 | AE62: =IF($K62=$AD$61,$N62,0) -> 0 | AF62: =IF($K62=$AF$61,$L62,0) -> 0 | AG62: =IF($K62=$AF$61,$N62,0) -> 0 | AH62: =IF($K62=$AH$61,$L62,0) -> 0 | AI62: =IF($K62=$AH$61,$N62,0) -> 0 | AJ62: =IF($K62=$AJ$61,$L62,0) -> 0 | AK62: =IF($K62=$AJ$61,$N62,0) -> 0 | AL62: =IF($K62=$AL$61,$L62,0) -> 0 | AM62: =IF($K62=$AL$61,$N62,0) -> 0 | AN62: =IF($K62=$AN$61,$L62,0) -> 0 | AO62: =IF($K62=$AN$61,$N62,0) -> 0 | AP62: =IF($K62=$AP$61,$L62,0) -> 0 | AQ62: =IF($K62=$AP$61,$N62,0) -> 0 | AR62: =IF($K62=$AR$61,$L62,0) -> 0 | AS62: =IF($K62=$AR$61,$N62,0) -> 0 | AT62: =IF($K62=$AT$61,$L62,0) -> 0 | AU62: =IF($K62=$AT$61,$N62,0) -> 0 | AV62: =IF($K62=$AV$61,$L62,0) -> 0 | AW62: =IF($K62=$AV$61,$N62,0) -> 0 | AX62: =IF($K62=$AX$61,$L62,0) -> 0 | AY62: =IF($K62=$AX$61,$N62,0) -> 0 | AZ62: =IF($K62=$AZ$61,$L62,0) -> 0 | BA62: =IF($K62=$AZ$61,$N62,0) -> 0 | BB62: =IF($K62=$BB$61,$L62,0) -> 0 | BC62: =IF($K62=$BB$61,$N62,0) -> 0 | BD62: =IF($O62=$BD$61,$P62,0) -> 0 | BE62: =IF($O62=$BD$61,$R62,0) -> 0 | BF62: =IF($O62=$BF$61,$P62,0) -> 0 | BG62: =IF($O62=$BF$61,$R62,0) -> 0 | BH62: =IF($O62=$BH$61,$P62,0) -> 0 | BI62: =IF($O62=$BH$61,$R62,0) -> 0 | BJ62: =IF($O62=$BJ$61,$P62,0) -> 0 | BK62: =IF($O62=$BJ$61,$R62,0) -> 0 | BL62: =IF($O62=$BL$61,$P62,0) -> 0 | BM62: =IF($O62=$BL$61,$R62,0) -> 0 | BN62: =IF($O62=$BN$61,$P62,0) -> 0 | BO62: =IF($O62=$BN$61,$R62,0) -> 0 | BP62: =IF($O62=$BP$61,$P62,0) -> 0 | BQ62: =IF($O62=$BP$61,$R62,0) -> 0 | BR62: =IF($O62=$BR$61,$P62,0) -> 0 | BS62: =IF($O62=$BR$61,$R62,0) -> 0 | BT62: =IF($O62=$BT$61,$P62,0) -> 0 | BU62: =IF($O62=$BT$61,$R62,0) -> 0 | BV62: =IF($O62=$BV$61,$P62,0) -> 0 | BW62: =IF($O62=$BV$61,$R62,0) -> 0 | BX62: =IF($O62=$BX$61,$P62,0) -> 0 | BY62: =IF($O62=$BX$61,$R62,0) -> 0 | BZ62: =IF($O62=$BZ$61,$P62,0) -> 0 | CA62: =IF($O62=$BZ$61,$R62,0) -> 0 | CB62: =IF($O62=$CB$61,$P62,0) -> 0 | CC62: =IF($O62=$CB$61,$R62,0) -> 0 | CD62: =IF($O62=$CD$61,$P62,0) -> 0 | CE62: =IF($O62=$CD$61,$R62,0) -> 0 | CF62: =IF($O62=$CF$61,$P62,0) -> 0 | CG62: =IF($O62=$CF$61,$R62,0) -> 0 | CH62: =IF($O62=$CH$61,$P62,0) -> 0 | CI62: =IF($O62=$CH$61,$R62,0) -> 0 | CJ62: =IF($O62=$CJ$61,$P62,0) -> 0 | CK62: =IF($O62=$CJ$61,$R62,0) -> 0 | CL62: =IF($O62=$CL$61,$P62,0) -> 0 | CM62: =IF($O62=$CL$61,$R62,0) -> 0 | CN62: =IF($O62=$CN$61,$P62,0) -> 0 | CO62: =IF($O62=$CN$61,$R62,0) -> 0 | CP62: =IF($O62=$CP$61,$P62,0) -> 0 | CQ62: =IF($O62=$CP$61,$R62,0) -> 0 | CR62: =IF($O62=$CR$61,$P62,0) -> 0 | CS62: =IF($O62=$CR$61,$R62,0) -> 0 | CT62: =IF($O62=$CT$61,$P62,0) -> 0 | CU62: =IF($O62=$CT$61,$R62,0) -> 0 | CV62: =IF($O62=$CV$61,$P62,0) -> 0 | CW62: =IF($O62=$CV$61,$R62,0) -> 0 | CX62: =IF($O62=$CX$61,$P62,0) -> 0 | CY62: =IF($O62=$CX$61,$R62,0) -> 0
H63: =S63*1.45 -> 0 | N63: =L63*M63 -> 0 | R63: =Q63*P63 -> 0 | S63: =R63+N63 -> 0 | T63: =IF(H63<>0,1-(S63/H63),0) -> 0 | V63: =IF($K63=$V$61,$L63,0) -> 0 | W63: =IF($K63=$V$61,$N63,0) -> 0 | X63: =IF($K63=$X$61,$L63,0) -> 0 | Y63: =IF($K63=$X$61,$N63,0) -> 0 | Z63: =IF($K63=$Z$61,$L63,0) -> 0 | AA63: =IF($K63=$Z$61,$N63,0) -> 0 | AB63: =IF($K63=$AB$61,$L63,0) -> 0 | AC63: =IF($K63=$AB$61,$N63,0) -> 0 | AD63: =IF($K63=$AD$61,$L63,0) -> 0 | AE63: =IF($K63=$AD$61,$N63,0) -> 0 | AF63: =IF($K63=$AF$61,$L63,0) -> 0 | AG63: =IF($K63=$AF$61,$N63,0) -> 0 | AH63: =IF($K63=$AH$61,$L63,0) -> 0 | AI63: =IF($K63=$AH$61,$N63,0) -> 0 | AJ63: =IF($K63=$AJ$61,$L63,0) -> 0 | AK63: =IF($K63=$AJ$61,$N63,0) -> 0 | AL63: =IF($K63=$AL$61,$L63,0) -> 0 | AM63: =IF($K63=$AL$61,$N63,0) -> 0 | AN63: =IF($K63=$AN$61,$L63,0) -> 0 | AO63: =IF($K63=$AN$61,$N63,0) -> 0 | AP63: =IF($K63=$AP$61,$L63,0) -> 0 | AQ63: =IF($K63=$AP$61,$N63,0) -> 0 | AR63: =IF($K63=$AR$61,$L63,0) -> 0 | AS63: =IF($K63=$AR$61,$N63,0) -> 0 | AT63: =IF($K63=$AT$61,$L63,0) -> 0 | AU63: =IF($K63=$AT$61,$N63,0) -> 0 | AV63: =IF($K63=$AV$61,$L63,0) -> 0 | AW63: =IF($K63=$AV$61,$N63,0) -> 0 | AX63: =IF($K63=$AX$61,$L63,0) -> 0 | AY63: =IF($K63=$AX$61,$N63,0) -> 0 | AZ63: =IF($K63=$AZ$61,$L63,0) -> 0 | BA63: =IF($K63=$AZ$61,$N63,0) -> 0 | BB63: =IF($K63=$BB$61,$L63,0) -> 0 | BC63: =IF($K63=$BB$61,$N63,0) -> 0 | BD63: =IF($O63=$BD$61,$P63,0) -> 0 | BE63: =IF($O63=$BD$61,$R63,0) -> 0 | BF63: =IF($O63=$BF$61,$P63,0) -> 0 | BG63: =IF($O63=$BF$61,$R63,0) -> 0 | BH63: =IF($O63=$BH$61,$P63,0) -> 0 | BI63: =IF($O63=$BH$61,$R63,0) -> 0 | BJ63: =IF($O63=$BJ$61,$P63,0) -> 0 | BK63: =IF($O63=$BJ$61,$R63,0) -> 0 | BL63: =IF($O63=$BL$61,$P63,0) -> 0 | BM63: =IF($O63=$BL$61,$R63,0) -> 0 | BN63: =IF($O63=$BN$61,$P63,0) -> 0 | BO63: =IF($O63=$BN$61,$R63,0) -> 0 | BP63: =IF($O63=$BP$61,$P63,0) -> 0 | BQ63: =IF($O63=$BP$61,$R63,0) -> 0 | BR63: =IF($O63=$BR$61,$P63,0) -> 0 | BS63: =IF($O63=$BR$61,$R63,0) -> 0 | BT63: =IF($O63=$BT$61,$P63,0) -> 0 | BU63: =IF($O63=$BT$61,$R63,0) -> 0 | BV63: =IF($O63=$BV$61,$P63,0) -> 0 | BW63: =IF($O63=$BV$61,$R63,0) -> 0 | BX63: =IF($O63=$BX$61,$P63,0) -> 0 | BY63: =IF($O63=$BX$61,$R63,0) -> 0 | BZ63: =IF($O63=$BZ$61,$P63,0) -> 0 | CA63: =IF($O63=$BZ$61,$R63,0) -> 0 | CB63: =IF($O63=$CB$61,$P63,0) -> 0 | CC63: =IF($O63=$CB$61,$R63,0) -> 0 | CD63: =IF($O63=$CD$61,$P63,0) -> 0 | CE63: =IF($O63=$CD$61,$R63,0) -> 0 | CF63: =IF($O63=$CF$61,$P63,0) -> 0 | CG63: =IF($O63=$CF$61,$R63,0) -> 0 | CH63: =IF($O63=$CH$61,$P63,0) -> 0 | CI63: =IF($O63=$CH$61,$R63,0) -> 0 | CJ63: =IF($O63=$CJ$61,$P63,0) -> 0 | CK63: =IF($O63=$CJ$61,$R63,0) -> 0 | CL63: =IF($O63=$CL$61,$P63,0) -> 0 | CM63: =IF($O63=$CL$61,$R63,0) -> 0 | CN63: =IF($O63=$CN$61,$P63,0) -> 0 | CO63: =IF($O63=$CN$61,$R63,0) -> 0 | CP63: =IF($O63=$CP$61,$P63,0) -> 0 | CQ63: =IF($O63=$CP$61,$R63,0) -> 0 | CR63: =IF($O63=$CR$61,$P63,0) -> 0 | CS63: =IF($O63=$CR$61,$R63,0) -> 0 | CT63: =IF($O63=$CT$61,$P63,0) -> 0 | CU63: =IF($O63=$CT$61,$R63,0) -> 0 | CV63: =IF($O63=$CV$61,$P63,0) -> 0 | CW63: =IF($O63=$CV$61,$R63,0) -> 0 | CX63: =IF($O63=$CX$61,$P63,0) -> 0 | CY63: =IF($O63=$CX$61,$R63,0) -> 0
H64: =S64*1.45 -> 0 | N64: =L64*M64 -> 0 | R64: =Q64*P64 -> 0 | S64: =R64+N64 -> 0 | T64: =IF(H64<>0,1-(S64/H64),0) -> 0 | V64: =IF($K64=$V$61,$L64,0) -> 0 | W64: =IF($K64=$V$61,$N64,0) -> 0 | X64: =IF($K64=$X$61,$L64,0) -> 0 | Y64: =IF($K64=$X$61,$N64,0) -> 0 | Z64: =IF($K64=$Z$61,$L64,0) -> 0 | AA64: =IF($K64=$Z$61,$N64,0) -> 0 | AB64: =IF($K64=$AB$61,$L64,0) -> 0 | AC64: =IF($K64=$AB$61,$N64,0) -> 0 | AD64: =IF($K64=$AD$61,$L64,0) -> 0 | AE64: =IF($K64=$AD$61,$N64,0) -> 0 | AF64: =IF($K64=$AF$61,$L64,0) -> 0 | AG64: =IF($K64=$AF$61,$N64,0) -> 0 | AH64: =IF($K64=$AH$61,$L64,0) -> 0 | AI64: =IF($K64=$AH$61,$N64,0) -> 0 | AJ64: =IF($K64=$AJ$61,$L64,0) -> 0 | AK64: =IF($K64=$AJ$61,$N64,0) -> 0 | AL64: =IF($K64=$AL$61,$L64,0) -> 0 | AM64: =IF($K64=$AL$61,$N64,0) -> 0 | AN64: =IF($K64=$AN$61,$L64,0) -> 0 | AO64: =IF($K64=$AN$61,$N64,0) -> 0 | AP64: =IF($K64=$AP$61,$L64,0) -> 0 | AQ64: =IF($K64=$AP$61,$N64,0) -> 0 | AR64: =IF($K64=$AR$61,$L64,0) -> 0 | AS64: =IF($K64=$AR$61,$N64,0) -> 0 | AT64: =IF($K64=$AT$61,$L64,0) -> 0 | AU64: =IF($K64=$AT$61,$N64,0) -> 0 | AV64: =IF($K64=$AV$61,$L64,0) -> 0 | AW64: =IF($K64=$AV$61,$N64,0) -> 0 | AX64: =IF($K64=$AX$61,$L64,0) -> 0 | AY64: =IF($K64=$AX$61,$N64,0) -> 0 | AZ64: =IF($K64=$AZ$61,$L64,0) -> 0 | BA64: =IF($K64=$AZ$61,$N64,0) -> 0 | BB64: =IF($K64=$BB$61,$L64,0) -> 0 | BC64: =IF($K64=$BB$61,$N64,0) -> 0 | BD64: =IF($O64=$BD$61,$P64,0) -> 0 | BE64: =IF($O64=$BD$61,$R64,0) -> 0 | BF64: =IF($O64=$BF$61,$P64,0) -> 0 | BG64: =IF($O64=$BF$61,$R64,0) -> 0 | BH64: =IF($O64=$BH$61,$P64,0) -> 0 | BI64: =IF($O64=$BH$61,$R64,0) -> 0 | BJ64: =IF($O64=$BJ$61,$P64,0) -> 0 | BK64: =IF($O64=$BJ$61,$R64,0) -> 0 | BL64: =IF($O64=$BL$61,$P64,0) -> 0 | BM64: =IF($O64=$BL$61,$R64,0) -> 0 | BN64: =IF($O64=$BN$61,$P64,0) -> 0 | BO64: =IF($O64=$BN$61,$R64,0) -> 0 | BP64: =IF($O64=$BP$61,$P64,0) -> 0 | BQ64: =IF($O64=$BP$61,$R64,0) -> 0 | BR64: =IF($O64=$BR$61,$P64,0) -> 0 | BS64: =IF($O64=$BR$61,$R64,0) -> 0 | BT64: =IF($O64=$BT$61,$P64,0) -> 0 | BU64: =IF($O64=$BT$61,$R64,0) -> 0 | BV64: =IF($O64=$BV$61,$P64,0) -> 0 | BW64: =IF($O64=$BV$61,$R64,0) -> 0 | BX64: =IF($O64=$BX$61,$P64,0) -> 0 | BY64: =IF($O64=$BX$61,$R64,0) -> 0 | BZ64: =IF($O64=$BZ$61,$P64,0) -> 0 | CA64: =IF($O64=$BZ$61,$R64,0) -> 0 | CB64: =IF($O64=$CB$61,$P64,0) -> 0 | CC64: =IF($O64=$CB$61,$R64,0) -> 0 | CD64: =IF($O64=$CD$61,$P64,0) -> 0 | CE64: =IF($O64=$CD$61,$R64,0) -> 0 | CF64: =IF($O64=$CF$61,$P64,0) -> 0 | CG64: =IF($O64=$CF$61,$R64,0) -> 0 | CH64: =IF($O64=$CH$61,$P64,0) -> 0 | CI64: =IF($O64=$CH$61,$R64,0) -> 0 | CJ64: =IF($O64=$CJ$61,$P64,0) -> 0 | CK64: =IF($O64=$CJ$61,$R64,0) -> 0 | CL64: =IF($O64=$CL$61,$P64,0) -> 0 | CM64: =IF($O64=$CL$61,$R64,0) -> 0 | CN64: =IF($O64=$CN$61,$P64,0) -> 0 | CO64: =IF($O64=$CN$61,$R64,0) -> 0 | CP64: =IF($O64=$CP$61,$P64,0) -> 0 | CQ64: =IF($O64=$CP$61,$R64,0) -> 0 | CR64: =IF($O64=$CR$61,$P64,0) -> 0 | CS64: =IF($O64=$CR$61,$R64,0) -> 0 | CT64: =IF($O64=$CT$61,$P64,0) -> 0 | CU64: =IF($O64=$CT$61,$R64,0) -> 0 | CV64: =IF($O64=$CV$61,$P64,0) -> 0 | CW64: =IF($O64=$CV$61,$R64,0) -> 0 | CX64: =IF($O64=$CX$61,$P64,0) -> 0 | CY64: =IF($O64=$CX$61,$R64,0) -> 0
H65: =S65*1.45 -> 0 | N65: =L65*M65 -> 0 | R65: =Q65*P65 -> 0 | S65: =R65+N65 -> 0 | T65: =IF(H65<>0,1-(S65/H65),0) -> 0 | V65: =IF($K65=$V$61,$L65,0) -> 0 | W65: =IF($K65=$V$61,$N65,0) -> 0 | X65: =IF($K65=$X$61,$L65,0) -> 0 | Y65: =IF($K65=$X$61,$N65,0) -> 0 | Z65: =IF($K65=$Z$61,$L65,0) -> 0 | AA65: =IF($K65=$Z$61,$N65,0) -> 0 | AB65: =IF($K65=$AB$61,$L65,0) -> 0 | AC65: =IF($K65=$AB$61,$N65,0) -> 0 | AD65: =IF($K65=$AD$61,$L65,0) -> 0 | AE65: =IF($K65=$AD$61,$N65,0) -> 0 | AF65: =IF($K65=$AF$61,$L65,0) -> 0 | AG65: =IF($K65=$AF$61,$N65,0) -> 0 | AH65: =IF($K65=$AH$61,$L65,0) -> 0 | AI65: =IF($K65=$AH$61,$N65,0) -> 0 | AJ65: =IF($K65=$AJ$61,$L65,0) -> 0 | AK65: =IF($K65=$AJ$61,$N65,0) -> 0 | AL65: =IF($K65=$AL$61,$L65,0) -> 0 | AM65: =IF($K65=$AL$61,$N65,0) -> 0 | AN65: =IF($K65=$AN$61,$L65,0) -> 0 | AO65: =IF($K65=$AN$61,$N65,0) -> 0 | AP65: =IF($K65=$AP$61,$L65,0) -> 0 | AQ65: =IF($K65=$AP$61,$N65,0) -> 0 | AR65: =IF($K65=$AR$61,$L65,0) -> 0 | AS65: =IF($K65=$AR$61,$N65,0) -> 0 | AT65: =IF($K65=$AT$61,$L65,0) -> 0 | AU65: =IF($K65=$AT$61,$N65,0) -> 0 | AV65: =IF($K65=$AV$61,$L65,0) -> 0 | AW65: =IF($K65=$AV$61,$N65,0) -> 0 | AX65: =IF($K65=$AX$61,$L65,0) -> 0 | AY65: =IF($K65=$AX$61,$N65,0) -> 0 | AZ65: =IF($K65=$AZ$61,$L65,0) -> 0 | BA65: =IF($K65=$AZ$61,$N65,0) -> 0 | BB65: =IF($K65=$BB$61,$L65,0) -> 0 | BC65: =IF($K65=$BB$61,$N65,0) -> 0 | BD65: =IF($O65=$BD$61,$P65,0) -> 0 | BE65: =IF($O65=$BD$61,$R65,0) -> 0 | BF65: =IF($O65=$BF$61,$P65,0) -> 0 | BG65: =IF($O65=$BF$61,$R65,0) -> 0 | BH65: =IF($O65=$BH$61,$P65,0) -> 0 | BI65: =IF($O65=$BH$61,$R65,0) -> 0 | BJ65: =IF($O65=$BJ$61,$P65,0) -> 0 | BK65: =IF($O65=$BJ$61,$R65,0) -> 0 | BL65: =IF($O65=$BL$61,$P65,0) -> 0 | BM65: =IF($O65=$BL$61,$R65,0) -> 0 | BN65: =IF($O65=$BN$61,$P65,0) -> 0 | BO65: =IF($O65=$BN$61,$R65,0) -> 0 | BP65: =IF($O65=$BP$61,$P65,0) -> 0 | BQ65: =IF($O65=$BP$61,$R65,0) -> 0 | BR65: =IF($O65=$BR$61,$P65,0) -> 0 | BS65: =IF($O65=$BR$61,$R65,0) -> 0 | BT65: =IF($O65=$BT$61,$P65,0) -> 0 | BU65: =IF($O65=$BT$61,$R65,0) -> 0 | BV65: =IF($O65=$BV$61,$P65,0) -> 0 | BW65: =IF($O65=$BV$61,$R65,0) -> 0 | BX65: =IF($O65=$BX$61,$P65,0) -> 0 | BY65: =IF($O65=$BX$61,$R65,0) -> 0 | BZ65: =IF($O65=$BZ$61,$P65,0) -> 0 | CA65: =IF($O65=$BZ$61,$R65,0) -> 0 | CB65: =IF($O65=$CB$61,$P65,0) -> 0 | CC65: =IF($O65=$CB$61,$R65,0) -> 0 | CD65: =IF($O65=$CD$61,$P65,0) -> 0 | CE65: =IF($O65=$CD$61,$R65,0) -> 0 | CF65: =IF($O65=$CF$61,$P65,0) -> 0 | CG65: =IF($O65=$CF$61,$R65,0) -> 0 | CH65: =IF($O65=$CH$61,$P65,0) -> 0 | CI65: =IF($O65=$CH$61,$R65,0) -> 0 | CJ65: =IF($O65=$CJ$61,$P65,0) -> 0 | CK65: =IF($O65=$CJ$61,$R65,0) -> 0 | CL65: =IF($O65=$CL$61,$P65,0) -> 0 | CM65: =IF($O65=$CL$61,$R65,0) -> 0 | CN65: =IF($O65=$CN$61,$P65,0) -> 0 | CO65: =IF($O65=$CN$61,$R65,0) -> 0 | CP65: =IF($O65=$CP$61,$P65,0) -> 0 | CQ65: =IF($O65=$CP$61,$R65,0) -> 0 | CR65: =IF($O65=$CR$61,$P65,0) -> 0 | CS65: =IF($O65=$CR$61,$R65,0) -> 0 | CT65: =IF($O65=$CT$61,$P65,0) -> 0 | CU65: =IF($O65=$CT$61,$R65,0) -> 0 | CV65: =IF($O65=$CV$61,$P65,0) -> 0 | CW65: =IF($O65=$CV$61,$R65,0) -> 0 | CX65: =IF($O65=$CX$61,$P65,0) -> 0 | CY65: =IF($O65=$CX$61,$R65,0) -> 0
H66: =S66*1.45 -> 0 | N66: =L66*M66 -> 0 | R66: =Q66*P66 -> 0 | S66: =R66+N66 -> 0 | T66: =IF(H66<>0,1-(S66/H66),0) -> 0 | V66: =IF($K66=$V$61,$L66,0) -> 0 | W66: =IF($K66=$V$61,$N66,0) -> 0 | X66: =IF($K66=$X$61,$L66,0) -> 0 | Y66: =IF($K66=$X$61,$N66,0) -> 0 | Z66: =IF($K66=$Z$61,$L66,0) -> 0 | AA66: =IF($K66=$Z$61,$N66,0) -> 0 | AB66: =IF($K66=$AB$61,$L66,0) -> 0 | AC66: =IF($K66=$AB$61,$N66,0) -> 0 | AD66: =IF($K66=$AD$61,$L66,0) -> 0 | AE66: =IF($K66=$AD$61,$N66,0) -> 0 | AF66: =IF($K66=$AF$61,$L66,0) -> 0 | AG66: =IF($K66=$AF$61,$N66,0) -> 0 | AH66: =IF($K66=$AH$61,$L66,0) -> 0 | AI66: =IF($K66=$AH$61,$N66,0) -> 0 | AJ66: =IF($K66=$AJ$61,$L66,0) -> 0 | AK66: =IF($K66=$AJ$61,$N66,0) -> 0 | AL66: =IF($K66=$AL$61,$L66,0) -> 0 | AM66: =IF($K66=$AL$61,$N66,0) -> 0 | AN66: =IF($K66=$AN$61,$L66,0) -> 0 | AO66: =IF($K66=$AN$61,$N66,0) -> 0 | AP66: =IF($K66=$AP$61,$L66,0) -> 0 | AQ66: =IF($K66=$AP$61,$N66,0) -> 0 | AR66: =IF($K66=$AR$61,$L66,0) -> 0 | AS66: =IF($K66=$AR$61,$N66,0) -> 0 | AT66: =IF($K66=$AT$61,$L66,0) -> 0 | AU66: =IF($K66=$AT$61,$N66,0) -> 0 | AV66: =IF($K66=$AV$61,$L66,0) -> 0 | AW66: =IF($K66=$AV$61,$N66,0) -> 0 | AX66: =IF($K66=$AX$61,$L66,0) -> 0 | AY66: =IF($K66=$AX$61,$N66,0) -> 0 | AZ66: =IF($K66=$AZ$61,$L66,0) -> 0 | BA66: =IF($K66=$AZ$61,$N66,0) -> 0 | BB66: =IF($K66=$BB$61,$L66,0) -> 0 | BC66: =IF($K66=$BB$61,$N66,0) -> 0 | BD66: =IF($O66=$BD$61,$P66,0) -> 0 | BE66: =IF($O66=$BD$61,$R66,0) -> 0 | BF66: =IF($O66=$BF$61,$P66,0) -> 0 | BG66: =IF($O66=$BF$61,$R66,0) -> 0 | BH66: =IF($O66=$BH$61,$P66,0) -> 0 | BI66: =IF($O66=$BH$61,$R66,0) -> 0 | BJ66: =IF($O66=$BJ$61,$P66,0) -> 0 | BK66: =IF($O66=$BJ$61,$R66,0) -> 0 | BL66: =IF($O66=$BL$61,$P66,0) -> 0 | BM66: =IF($O66=$BL$61,$R66,0) -> 0 | BN66: =IF($O66=$BN$61,$P66,0) -> 0 | BO66: =IF($O66=$BN$61,$R66,0) -> 0 | BP66: =IF($O66=$BP$61,$P66,0) -> 0 | BQ66: =IF($O66=$BP$61,$R66,0) -> 0 | BR66: =IF($O66=$BR$61,$P66,0) -> 0 | BS66: =IF($O66=$BR$61,$R66,0) -> 0 | BT66: =IF($O66=$BT$61,$P66,0) -> 0 | BU66: =IF($O66=$BT$61,$R66,0) -> 0 | BV66: =IF($O66=$BV$61,$P66,0) -> 0 | BW66: =IF($O66=$BV$61,$R66,0) -> 0 | BX66: =IF($O66=$BX$61,$P66,0) -> 0 | BY66: =IF($O66=$BX$61,$R66,0) -> 0 | BZ66: =IF($O66=$BZ$61,$P66,0) -> 0 | CA66: =IF($O66=$BZ$61,$R66,0) -> 0 | CB66: =IF($O66=$CB$61,$P66,0) -> 0 | CC66: =IF($O66=$CB$61,$R66,0) -> 0 | CD66: =IF($O66=$CD$61,$P66,0) -> 0 | CE66: =IF($O66=$CD$61,$R66,0) -> 0 | CF66: =IF($O66=$CF$61,$P66,0) -> 0 | CG66: =IF($O66=$CF$61,$R66,0) -> 0 | CH66: =IF($O66=$CH$61,$P66,0) -> 0 | CI66: =IF($O66=$CH$61,$R66,0) -> 0 | CJ66: =IF($O66=$CJ$61,$P66,0) -> 0 | CK66: =IF($O66=$CJ$61,$R66,0) -> 0 | CL66: =IF($O66=$CL$61,$P66,0) -> 0 | CM66: =IF($O66=$CL$61,$R66,0) -> 0 | CN66: =IF($O66=$CN$61,$P66,0) -> 0 | CO66: =IF($O66=$CN$61,$R66,0) -> 0 | CP66: =IF($O66=$CP$61,$P66,0) -> 0 | CQ66: =IF($O66=$CP$61,$R66,0) -> 0 | CR66: =IF($O66=$CR$61,$P66,0) -> 0 | CS66: =IF($O66=$CR$61,$R66,0) -> 0 | CT66: =IF($O66=$CT$61,$P66,0) -> 0 | CU66: =IF($O66=$CT$61,$R66,0) -> 0 | CV66: =IF($O66=$CV$61,$P66,0) -> 0 | CW66: =IF($O66=$CV$61,$R66,0) -> 0 | CX66: =IF($O66=$CX$61,$P66,0) -> 0 | CY66: =IF($O66=$CX$61,$R66,0) -> 0
H67: =S67*1.45 -> 0 | N67: =L67*M67 -> 0 | R67: =Q67*P67 -> 0 | S67: =R67+N67 -> 0 | T67: =IF(H67<>0,1-(S67/H67),0) -> 0 | V67: =IF($K67=$V$61,$L67,0) -> 0 | W67: =IF($K67=$V$61,$N67,0) -> 0 | X67: =IF($K67=$X$61,$L67,0) -> 0 | Y67: =IF($K67=$X$61,$N67,0) -> 0 | Z67: =IF($K67=$Z$61,$L67,0) -> 0 | AA67: =IF($K67=$Z$61,$N67,0) -> 0 | AB67: =IF($K67=$AB$61,$L67,0) -> 0 | AC67: =IF($K67=$AB$61,$N67,0) -> 0 | AD67: =IF($K67=$AD$61,$L67,0) -> 0 | AE67: =IF($K67=$AD$61,$N67,0) -> 0 | AF67: =IF($K67=$AF$61,$L67,0) -> 0 | AG67: =IF($K67=$AF$61,$N67,0) -> 0 | AH67: =IF($K67=$AH$61,$L67,0) -> 0 | AI67: =IF($K67=$AH$61,$N67,0) -> 0 | AJ67: =IF($K67=$AJ$61,$L67,0) -> 0 | AK67: =IF($K67=$AJ$61,$N67,0) -> 0 | AL67: =IF($K67=$AL$61,$L67,0) -> 0 | AM67: =IF($K67=$AL$61,$N67,0) -> 0 | AN67: =IF($K67=$AN$61,$L67,0) -> 0 | AO67: =IF($K67=$AN$61,$N67,0) -> 0 | AP67: =IF($K67=$AP$61,$L67,0) -> 0 | AQ67: =IF($K67=$AP$61,$N67,0) -> 0 | AR67: =IF($K67=$AR$61,$L67,0) -> 0 | AS67: =IF($K67=$AR$61,$N67,0) -> 0 | AT67: =IF($K67=$AT$61,$L67,0) -> 0 | AU67: =IF($K67=$AT$61,$N67,0) -> 0 | AV67: =IF($K67=$AV$61,$L67,0) -> 0 | AW67: =IF($K67=$AV$61,$N67,0) -> 0 | AX67: =IF($K67=$AX$61,$L67,0) -> 0 | AY67: =IF($K67=$AX$61,$N67,0) -> 0 | AZ67: =IF($K67=$AZ$61,$L67,0) -> 0 | BA67: =IF($K67=$AZ$61,$N67,0) -> 0 | BB67: =IF($K67=$BB$61,$L67,0) -> 0 | BC67: =IF($K67=$BB$61,$N67,0) -> 0 | BD67: =IF($O67=$BD$61,$P67,0) -> 0 | BE67: =IF($O67=$BD$61,$R67,0) -> 0 | BF67: =IF($O67=$BF$61,$P67,0) -> 0 | BG67: =IF($O67=$BF$61,$R67,0) -> 0 | BH67: =IF($O67=$BH$61,$P67,0) -> 0 | BI67: =IF($O67=$BH$61,$R67,0) -> 0 | BJ67: =IF($O67=$BJ$61,$P67,0) -> 0 | BK67: =IF($O67=$BJ$61,$R67,0) -> 0 | BL67: =IF($O67=$BL$61,$P67,0) -> 0 | BM67: =IF($O67=$BL$61,$R67,0) -> 0 | BN67: =IF($O67=$BN$61,$P67,0) -> 0 | BO67: =IF($O67=$BN$61,$R67,0) -> 0 | BP67: =IF($O67=$BP$61,$P67,0) -> 0 | BQ67: =IF($O67=$BP$61,$R67,0) -> 0 | BR67: =IF($O67=$BR$61,$P67,0) -> 0 | BS67: =IF($O67=$BR$61,$R67,0) -> 0 | BT67: =IF($O67=$BT$61,$P67,0) -> 0 | BU67: =IF($O67=$BT$61,$R67,0) -> 0 | BV67: =IF($O67=$BV$61,$P67,0) -> 0 | BW67: =IF($O67=$BV$61,$R67,0) -> 0 | BX67: =IF($O67=$BX$61,$P67,0) -> 0 | BY67: =IF($O67=$BX$61,$R67,0) -> 0 | BZ67: =IF($O67=$BZ$61,$P67,0) -> 0 | CA67: =IF($O67=$BZ$61,$R67,0) -> 0 | CB67: =IF($O67=$CB$61,$P67,0) -> 0 | CC67: =IF($O67=$CB$61,$R67,0) -> 0 | CD67: =IF($O67=$CD$61,$P67,0) -> 0 | CE67: =IF($O67=$CD$61,$R67,0) -> 0 | CF67: =IF($O67=$CF$61,$P67,0) -> 0 | CG67: =IF($O67=$CF$61,$R67,0) -> 0 | CH67: =IF($O67=$CH$61,$P67,0) -> 0 | CI67: =IF($O67=$CH$61,$R67,0) -> 0 | CJ67: =IF($O67=$CJ$61,$P67,0) -> 0 | CK67: =IF($O67=$CJ$61,$R67,0) -> 0 | CL67: =IF($O67=$CL$61,$P67,0) -> 0 | CM67: =IF($O67=$CL$61,$R67,0) -> 0 | CN67: =IF($O67=$CN$61,$P67,0) -> 0 | CO67: =IF($O67=$CN$61,$R67,0) -> 0 | CP67: =IF($O67=$CP$61,$P67,0) -> 0 | CQ67: =IF($O67=$CP$61,$R67,0) -> 0 | CR67: =IF($O67=$CR$61,$P67,0) -> 0 | CS67: =IF($O67=$CR$61,$R67,0) -> 0 | CT67: =IF($O67=$CT$61,$P67,0) -> 0 | CU67: =IF($O67=$CT$61,$R67,0) -> 0 | CV67: =IF($O67=$CV$61,$P67,0) -> 0 | CW67: =IF($O67=$CV$61,$R67,0) -> 0 | CX67: =IF($O67=$CX$61,$P67,0) -> 0 | CY67: =IF($O67=$CX$61,$R67,0) -> 0
H68: =S68*1.45 -> 0 | N68: =L68*M68 -> 0 | R68: =Q68*P68 -> 0 | S68: =R68+N68 -> 0 | T68: =IF(H68<>0,1-(S68/H68),0) -> 0 | V68: =IF($K68=$V$61,$L68,0) -> 0 | W68: =IF($K68=$V$61,$N68,0) -> 0 | X68: =IF($K68=$X$61,$L68,0) -> 0 | Y68: =IF($K68=$X$61,$N68,0) -> 0 | Z68: =IF($K68=$Z$61,$L68,0) -> 0 | AA68: =IF($K68=$Z$61,$N68,0) -> 0 | AB68: =IF($K68=$AB$61,$L68,0) -> 0 | AC68: =IF($K68=$AB$61,$N68,0) -> 0 | AD68: =IF($K68=$AD$61,$L68,0) -> 0 | AE68: =IF($K68=$AD$61,$N68,0) -> 0 | AF68: =IF($K68=$AF$61,$L68,0) -> 0 | AG68: =IF($K68=$AF$61,$N68,0) -> 0 | AH68: =IF($K68=$AH$61,$L68,0) -> 0 | AI68: =IF($K68=$AH$61,$N68,0) -> 0 | AJ68: =IF($K68=$AJ$61,$L68,0) -> 0 | AK68: =IF($K68=$AJ$61,$N68,0) -> 0 | AL68: =IF($K68=$AL$61,$L68,0) -> 0 | AM68: =IF($K68=$AL$61,$N68,0) -> 0 | AN68: =IF($K68=$AN$61,$L68,0) -> 0 | AO68: =IF($K68=$AN$61,$N68,0) -> 0 | AP68: =IF($K68=$AP$61,$L68,0) -> 0 | AQ68: =IF($K68=$AP$61,$N68,0) -> 0 | AR68: =IF($K68=$AR$61,$L68,0) -> 0 | AS68: =IF($K68=$AR$61,$N68,0) -> 0 | AT68: =IF($K68=$AT$61,$L68,0) -> 0 | AU68: =IF($K68=$AT$61,$N68,0) -> 0 | AV68: =IF($K68=$AV$61,$L68,0) -> 0 | AW68: =IF($K68=$AV$61,$N68,0) -> 0 | AX68: =IF($K68=$AX$61,$L68,0) -> 0 | AY68: =IF($K68=$AX$61,$N68,0) -> 0 | AZ68: =IF($K68=$AZ$61,$L68,0) -> 0 | BA68: =IF($K68=$AZ$61,$N68,0) -> 0 | BB68: =IF($K68=$BB$61,$L68,0) -> 0 | BC68: =IF($K68=$BB$61,$N68,0) -> 0 | BD68: =IF($O68=$BD$61,$P68,0) -> 0 | BE68: =IF($O68=$BD$61,$R68,0) -> 0 | BF68: =IF($O68=$BF$61,$P68,0) -> 0 | BG68: =IF($O68=$BF$61,$R68,0) -> 0 | BH68: =IF($O68=$BH$61,$P68,0) -> 0 | BI68: =IF($O68=$BH$61,$R68,0) -> 0 | BJ68: =IF($O68=$BJ$61,$P68,0) -> 0 | BK68: =IF($O68=$BJ$61,$R68,0) -> 0 | BL68: =IF($O68=$BL$61,$P68,0) -> 0 | BM68: =IF($O68=$BL$61,$R68,0) -> 0 | BN68: =IF($O68=$BN$61,$P68,0) -> 0 | BO68: =IF($O68=$BN$61,$R68,0) -> 0 | BP68: =IF($O68=$BP$61,$P68,0) -> 0 | BQ68: =IF($O68=$BP$61,$R68,0) -> 0 | BR68: =IF($O68=$BR$61,$P68,0) -> 0 | BS68: =IF($O68=$BR$61,$R68,0) -> 0 | BT68: =IF($O68=$BT$61,$P68,0) -> 0 | BU68: =IF($O68=$BT$61,$R68,0) -> 0 | BV68: =IF($O68=$BV$61,$P68,0) -> 0 | BW68: =IF($O68=$BV$61,$R68,0) -> 0 | BX68: =IF($O68=$BX$61,$P68,0) -> 0 | BY68: =IF($O68=$BX$61,$R68,0) -> 0 | BZ68: =IF($O68=$BZ$61,$P68,0) -> 0 | CA68: =IF($O68=$BZ$61,$R68,0) -> 0 | CB68: =IF($O68=$CB$61,$P68,0) -> 0 | CC68: =IF($O68=$CB$61,$R68,0) -> 0 | CD68: =IF($O68=$CD$61,$P68,0) -> 0 | CE68: =IF($O68=$CD$61,$R68,0) -> 0 | CF68: =IF($O68=$CF$61,$P68,0) -> 0 | CG68: =IF($O68=$CF$61,$R68,0) -> 0 | CH68: =IF($O68=$CH$61,$P68,0) -> 0 | CI68: =IF($O68=$CH$61,$R68,0) -> 0 | CJ68: =IF($O68=$CJ$61,$P68,0) -> 0 | CK68: =IF($O68=$CJ$61,$R68,0) -> 0 | CL68: =IF($O68=$CL$61,$P68,0) -> 0 | CM68: =IF($O68=$CL$61,$R68,0) -> 0 | CN68: =IF($O68=$CN$61,$P68,0) -> 0 | CO68: =IF($O68=$CN$61,$R68,0) -> 0 | CP68: =IF($O68=$CP$61,$P68,0) -> 0 | CQ68: =IF($O68=$CP$61,$R68,0) -> 0 | CR68: =IF($O68=$CR$61,$P68,0) -> 0 | CS68: =IF($O68=$CR$61,$R68,0) -> 0 | CT68: =IF($O68=$CT$61,$P68,0) -> 0 | CU68: =IF($O68=$CT$61,$R68,0) -> 0 | CV68: =IF($O68=$CV$61,$P68,0) -> 0 | CW68: =IF($O68=$CV$61,$R68,0) -> 0 | CX68: =IF($O68=$CX$61,$P68,0) -> 0 | CY68: =IF($O68=$CX$61,$R68,0) -> 0
H69: =S69*1.45 -> 0 | N69: =L69*M69 -> 0 | R69: =Q69*P69 -> 0 | S69: =R69+N69 -> 0 | T69: =IF(H69<>0,1-(S69/H69),0) -> 0 | V69: =IF($K69=$V$61,$L69,0) -> 0 | W69: =IF($K69=$V$61,$N69,0) -> 0 | X69: =IF($K69=$X$61,$L69,0) -> 0 | Y69: =IF($K69=$X$61,$N69,0) -> 0 | Z69: =IF($K69=$Z$61,$L69,0) -> 0 | AA69: =IF($K69=$Z$61,$N69,0) -> 0 | AB69: =IF($K69=$AB$61,$L69,0) -> 0 | AC69: =IF($K69=$AB$61,$N69,0) -> 0 | AD69: =IF($K69=$AD$61,$L69,0) -> 0 | AE69: =IF($K69=$AD$61,$N69,0) -> 0 | AF69: =IF($K69=$AF$61,$L69,0) -> 0 | AG69: =IF($K69=$AF$61,$N69,0) -> 0 | AH69: =IF($K69=$AH$61,$L69,0) -> 0 | AI69: =IF($K69=$AH$61,$N69,0) -> 0 | AJ69: =IF($K69=$AJ$61,$L69,0) -> 0 | AK69: =IF($K69=$AJ$61,$N69,0) -> 0 | AL69: =IF($K69=$AL$61,$L69,0) -> 0 | AM69: =IF($K69=$AL$61,$N69,0) -> 0 | AN69: =IF($K69=$AN$61,$L69,0) -> 0 | AO69: =IF($K69=$AN$61,$N69,0) -> 0 | AP69: =IF($K69=$AP$61,$L69,0) -> 0 | AQ69: =IF($K69=$AP$61,$N69,0) -> 0 | AR69: =IF($K69=$AR$61,$L69,0) -> 0 | AS69: =IF($K69=$AR$61,$N69,0) -> 0 | AT69: =IF($K69=$AT$61,$L69,0) -> 0 | AU69: =IF($K69=$AT$61,$N69,0) -> 0 | AV69: =IF($K69=$AV$61,$L69,0) -> 0 | AW69: =IF($K69=$AV$61,$N69,0) -> 0 | AX69: =IF($K69=$AX$61,$L69,0) -> 0 | AY69: =IF($K69=$AX$61,$N69,0) -> 0 | AZ69: =IF($K69=$AZ$61,$L69,0) -> 0 | BA69: =IF($K69=$AZ$61,$N69,0) -> 0 | BB69: =IF($K69=$BB$61,$L69,0) -> 0 | BC69: =IF($K69=$BB$61,$N69,0) -> 0 | BD69: =IF($O69=$BD$61,$P69,0) -> 0 | BE69: =IF($O69=$BD$61,$R69,0) -> 0 | BF69: =IF($O69=$BF$61,$P69,0) -> 0 | BG69: =IF($O69=$BF$61,$R69,0) -> 0 | BH69: =IF($O69=$BH$61,$P69,0) -> 0 | BI69: =IF($O69=$BH$61,$R69,0) -> 0 | BJ69: =IF($O69=$BJ$61,$P69,0) -> 0 | BK69: =IF($O69=$BJ$61,$R69,0) -> 0 | BL69: =IF($O69=$BL$61,$P69,0) -> 0 | BM69: =IF($O69=$BL$61,$R69,0) -> 0 | BN69: =IF($O69=$BN$61,$P69,0) -> 0 | BO69: =IF($O69=$BN$61,$R69,0) -> 0 | BP69: =IF($O69=$BP$61,$P69,0) -> 0 | BQ69: =IF($O69=$BP$61,$R69,0) -> 0 | BR69: =IF($O69=$BR$61,$P69,0) -> 0 | BS69: =IF($O69=$BR$61,$R69,0) -> 0 | BT69: =IF($O69=$BT$61,$P69,0) -> 0 | BU69: =IF($O69=$BT$61,$R69,0) -> 0 | BV69: =IF($O69=$BV$61,$P69,0) -> 0 | BW69: =IF($O69=$BV$61,$R69,0) -> 0 | BX69: =IF($O69=$BX$61,$P69,0) -> 0 | BY69: =IF($O69=$BX$61,$R69,0) -> 0 | BZ69: =IF($O69=$BZ$61,$P69,0) -> 0 | CA69: =IF($O69=$BZ$61,$R69,0) -> 0 | CB69: =IF($O69=$CB$61,$P69,0) -> 0 | CC69: =IF($O69=$CB$61,$R69,0) -> 0 | CD69: =IF($O69=$CD$61,$P69,0) -> 0 | CE69: =IF($O69=$CD$61,$R69,0) -> 0 | CF69: =IF($O69=$CF$61,$P69,0) -> 0 | CG69: =IF($O69=$CF$61,$R69,0) -> 0 | CH69: =IF($O69=$CH$61,$P69,0) -> 0 | CI69: =IF($O69=$CH$61,$R69,0) -> 0 | CJ69: =IF($O69=$CJ$61,$P69,0) -> 0 | CK69: =IF($O69=$CJ$61,$R69,0) -> 0 | CL69: =IF($O69=$CL$61,$P69,0) -> 0 | CM69: =IF($O69=$CL$61,$R69,0) -> 0 | CN69: =IF($O69=$CN$61,$P69,0) -> 0 | CO69: =IF($O69=$CN$61,$R69,0) -> 0 | CP69: =IF($O69=$CP$61,$P69,0) -> 0 | CQ69: =IF($O69=$CP$61,$R69,0) -> 0 | CR69: =IF($O69=$CR$61,$P69,0) -> 0 | CS69: =IF($O69=$CR$61,$R69,0) -> 0 | CT69: =IF($O69=$CT$61,$P69,0) -> 0 | CU69: =IF($O69=$CT$61,$R69,0) -> 0 | CV69: =IF($O69=$CV$61,$P69,0) -> 0 | CW69: =IF($O69=$CV$61,$R69,0) -> 0 | CX69: =IF($O69=$CX$61,$P69,0) -> 0 | CY69: =IF($O69=$CX$61,$R69,0) -> 0
H70: =S70*1.45 -> 0 | N70: =L70*M70 -> 0 | R70: =Q70*P70 -> 0 | S70: =R70+N70 -> 0 | T70: =IF(H70<>0,1-(S70/H70),0) -> 0 | V70: =IF($K70=$V$61,$L70,0) -> 0 | W70: =IF($K70=$V$61,$N70,0) -> 0 | X70: =IF($K70=$X$61,$L70,0) -> 0 | Y70: =IF($K70=$X$61,$N70,0) -> 0 | Z70: =IF($K70=$Z$61,$L70,0) -> 0 | AA70: =IF($K70=$Z$61,$N70,0) -> 0 | AB70: =IF($K70=$AB$61,$L70,0) -> 0 | AC70: =IF($K70=$AB$61,$N70,0) -> 0 | AD70: =IF($K70=$AD$61,$L70,0) -> 0 | AE70: =IF($K70=$AD$61,$N70,0) -> 0 | AF70: =IF($K70=$AF$61,$L70,0) -> 0 | AG70: =IF($K70=$AF$61,$N70,0) -> 0 | AH70: =IF($K70=$AH$61,$L70,0) -> 0 | AI70: =IF($K70=$AH$61,$N70,0) -> 0 | AJ70: =IF($K70=$AJ$61,$L70,0) -> 0 | AK70: =IF($K70=$AJ$61,$N70,0) -> 0 | AL70: =IF($K70=$AL$61,$L70,0) -> 0 | AM70: =IF($K70=$AL$61,$N70,0) -> 0 | AN70: =IF($K70=$AN$61,$L70,0) -> 0 | AO70: =IF($K70=$AN$61,$N70,0) -> 0 | AP70: =IF($K70=$AP$61,$L70,0) -> 0 | AQ70: =IF($K70=$AP$61,$N70,0) -> 0 | AR70: =IF($K70=$AR$61,$L70,0) -> 0 | AS70: =IF($K70=$AR$61,$N70,0) -> 0 | AT70: =IF($K70=$AT$61,$L70,0) -> 0 | AU70: =IF($K70=$AT$61,$N70,0) -> 0 | AV70: =IF($K70=$AV$61,$L70,0) -> 0 | AW70: =IF($K70=$AV$61,$N70,0) -> 0 | AX70: =IF($K70=$AX$61,$L70,0) -> 0 | AY70: =IF($K70=$AX$61,$N70,0) -> 0 | AZ70: =IF($K70=$AZ$61,$L70,0) -> 0 | BA70: =IF($K70=$AZ$61,$N70,0) -> 0 | BB70: =IF($K70=$BB$61,$L70,0) -> 0 | BC70: =IF($K70=$BB$61,$N70,0) -> 0 | BD70: =IF($O70=$BD$61,$P70,0) -> 0 | BE70: =IF($O70=$BD$61,$R70,0) -> 0 | BF70: =IF($O70=$BF$61,$P70,0) -> 0 | BG70: =IF($O70=$BF$61,$R70,0) -> 0 | BH70: =IF($O70=$BH$61,$P70,0) -> 0 | BI70: =IF($O70=$BH$61,$R70,0) -> 0 | BJ70: =IF($O70=$BJ$61,$P70,0) -> 0 | BK70: =IF($O70=$BJ$61,$R70,0) -> 0 | BL70: =IF($O70=$BL$61,$P70,0) -> 0 | BM70: =IF($O70=$BL$61,$R70,0) -> 0 | BN70: =IF($O70=$BN$61,$P70,0) -> 0 | BO70: =IF($O70=$BN$61,$R70,0) -> 0 | BP70: =IF($O70=$BP$61,$P70,0) -> 0 | BQ70: =IF($O70=$BP$61,$R70,0) -> 0 | BR70: =IF($O70=$BR$61,$P70,0) -> 0 | BS70: =IF($O70=$BR$61,$R70,0) -> 0 | BT70: =IF($O70=$BT$61,$P70,0) -> 0 | BU70: =IF($O70=$BT$61,$R70,0) -> 0 | BV70: =IF($O70=$BV$61,$P70,0) -> 0 | BW70: =IF($O70=$BV$61,$R70,0) -> 0 | BX70: =IF($O70=$BX$61,$P70,0) -> 0 | BY70: =IF($O70=$BX$61,$R70,0) -> 0 | BZ70: =IF($O70=$BZ$61,$P70,0) -> 0 | CA70: =IF($O70=$BZ$61,$R70,0) -> 0 | CB70: =IF($O70=$CB$61,$P70,0) -> 0 | CC70: =IF($O70=$CB$61,$R70,0) -> 0 | CD70: =IF($O70=$CD$61,$P70,0) -> 0 | CE70: =IF($O70=$CD$61,$R70,0) -> 0 | CF70: =IF($O70=$CF$61,$P70,0) -> 0 | CG70: =IF($O70=$CF$61,$R70,0) -> 0 | CH70: =IF($O70=$CH$61,$P70,0) -> 0 | CI70: =IF($O70=$CH$61,$R70,0) -> 0 | CJ70: =IF($O70=$CJ$61,$P70,0) -> 0 | CK70: =IF($O70=$CJ$61,$R70,0) -> 0 | CL70: =IF($O70=$CL$61,$P70,0) -> 0 | CM70: =IF($O70=$CL$61,$R70,0) -> 0 | CN70: =IF($O70=$CN$61,$P70,0) -> 0 | CO70: =IF($O70=$CN$61,$R70,0) -> 0 | CP70: =IF($O70=$CP$61,$P70,0) -> 0 | CQ70: =IF($O70=$CP$61,$R70,0) -> 0 | CR70: =IF($O70=$CR$61,$P70,0) -> 0 | CS70: =IF($O70=$CR$61,$R70,0) -> 0 | CT70: =IF($O70=$CT$61,$P70,0) -> 0 | CU70: =IF($O70=$CT$61,$R70,0) -> 0 | CV70: =IF($O70=$CV$61,$P70,0) -> 0 | CW70: =IF($O70=$CV$61,$R70,0) -> 0 | CX70: =IF($O70=$CX$61,$P70,0) -> 0 | CY70: =IF($O70=$CX$61,$R70,0) -> 0
H71: =S71*1.45 -> 0 | N71: =L71*M71 -> 0 | R71: =Q71*P71 -> 0 | S71: =R71+N71 -> 0 | T71: =IF(H71<>0,1-(S71/H71),0) -> 0 | V71: =IF($K71=$V$61,$L71,0) -> 0 | W71: =IF($K71=$V$61,$N71,0) -> 0 | X71: =IF($K71=$X$61,$L71,0) -> 0 | Y71: =IF($K71=$X$61,$N71,0) -> 0 | Z71: =IF($K71=$Z$61,$L71,0) -> 0 | AA71: =IF($K71=$Z$61,$N71,0) -> 0 | AB71: =IF($K71=$AB$61,$L71,0) -> 0 | AC71: =IF($K71=$AB$61,$N71,0) -> 0 | AD71: =IF($K71=$AD$61,$L71,0) -> 0 | AE71: =IF($K71=$AD$61,$N71,0) -> 0 | AF71: =IF($K71=$AF$61,$L71,0) -> 0 | AG71: =IF($K71=$AF$61,$N71,0) -> 0 | AH71: =IF($K71=$AH$61,$L71,0) -> 0 | AI71: =IF($K71=$AH$61,$N71,0) -> 0 | AJ71: =IF($K71=$AJ$61,$L71,0) -> 0 | AK71: =IF($K71=$AJ$61,$N71,0) -> 0 | AL71: =IF($K71=$AL$61,$L71,0) -> 0 | AM71: =IF($K71=$AL$61,$N71,0) -> 0 | AN71: =IF($K71=$AN$61,$L71,0) -> 0 | AO71: =IF($K71=$AN$61,$N71,0) -> 0 | AP71: =IF($K71=$AP$61,$L71,0) -> 0 | AQ71: =IF($K71=$AP$61,$N71,0) -> 0 | AR71: =IF($K71=$AR$61,$L71,0) -> 0 | AS71: =IF($K71=$AR$61,$N71,0) -> 0 | AT71: =IF($K71=$AT$61,$L71,0) -> 0 | AU71: =IF($K71=$AT$61,$N71,0) -> 0 | AV71: =IF($K71=$AV$61,$L71,0) -> 0 | AW71: =IF($K71=$AV$61,$N71,0) -> 0 | AX71: =IF($K71=$AX$61,$L71,0) -> 0 | AY71: =IF($K71=$AX$61,$N71,0) -> 0 | AZ71: =IF($K71=$AZ$61,$L71,0) -> 0 | BA71: =IF($K71=$AZ$61,$N71,0) -> 0 | BB71: =IF($K71=$BB$61,$L71,0) -> 0 | BC71: =IF($K71=$BB$61,$N71,0) -> 0 | BD71: =IF($O71=$BD$61,$P71,0) -> 0 | BE71: =IF($O71=$BD$61,$R71,0) -> 0 | BF71: =IF($O71=$BF$61,$P71,0) -> 0 | BG71: =IF($O71=$BF$61,$R71,0) -> 0 | BH71: =IF($O71=$BH$61,$P71,0) -> 0 | BI71: =IF($O71=$BH$61,$R71,0) -> 0 | BJ71: =IF($O71=$BJ$61,$P71,0) -> 0 | BK71: =IF($O71=$BJ$61,$R71,0) -> 0 | BL71: =IF($O71=$BL$61,$P71,0) -> 0 | BM71: =IF($O71=$BL$61,$R71,0) -> 0 | BN71: =IF($O71=$BN$61,$P71,0) -> 0 | BO71: =IF($O71=$BN$61,$R71,0) -> 0 | BP71: =IF($O71=$BP$61,$P71,0) -> 0 | BQ71: =IF($O71=$BP$61,$R71,0) -> 0 | BR71: =IF($O71=$BR$61,$P71,0) -> 0 | BS71: =IF($O71=$BR$61,$R71,0) -> 0 | BT71: =IF($O71=$BT$61,$P71,0) -> 0 | BU71: =IF($O71=$BT$61,$R71,0) -> 0 | BV71: =IF($O71=$BV$61,$P71,0) -> 0 | BW71: =IF($O71=$BV$61,$R71,0) -> 0 | BX71: =IF($O71=$BX$61,$P71,0) -> 0 | BY71: =IF($O71=$BX$61,$R71,0) -> 0 | BZ71: =IF($O71=$BZ$61,$P71,0) -> 0 | CA71: =IF($O71=$BZ$61,$R71,0) -> 0 | CB71: =IF($O71=$CB$61,$P71,0) -> 0 | CC71: =IF($O71=$CB$61,$R71,0) -> 0 | CD71: =IF($O71=$CD$61,$P71,0) -> 0 | CE71: =IF($O71=$CD$61,$R71,0) -> 0 | CF71: =IF($O71=$CF$61,$P71,0) -> 0 | CG71: =IF($O71=$CF$61,$R71,0) -> 0 | CH71: =IF($O71=$CH$61,$P71,0) -> 0 | CI71: =IF($O71=$CH$61,$R71,0) -> 0 | CJ71: =IF($O71=$CJ$61,$P71,0) -> 0 | CK71: =IF($O71=$CJ$61,$R71,0) -> 0 | CL71: =IF($O71=$CL$61,$P71,0) -> 0 | CM71: =IF($O71=$CL$61,$R71,0) -> 0 | CN71: =IF($O71=$CN$61,$P71,0) -> 0 | CO71: =IF($O71=$CN$61,$R71,0) -> 0 | CP71: =IF($O71=$CP$61,$P71,0) -> 0 | CQ71: =IF($O71=$CP$61,$R71,0) -> 0 | CR71: =IF($O71=$CR$61,$P71,0) -> 0 | CS71: =IF($O71=$CR$61,$R71,0) -> 0 | CT71: =IF($O71=$CT$61,$P71,0) -> 0 | CU71: =IF($O71=$CT$61,$R71,0) -> 0 | CV71: =IF($O71=$CV$61,$P71,0) -> 0 | CW71: =IF($O71=$CV$61,$R71,0) -> 0 | CX71: =IF($O71=$CX$61,$P71,0) -> 0 | CY71: =IF($O71=$CX$61,$R71,0) -> 0
H72: =S72*1.45 -> 0 | N72: =L72*M72 -> 0 | R72: =Q72*P72 -> 0 | S72: =R72+N72 -> 0 | T72: =IF(H72<>0,1-(S72/H72),0) -> 0 | V72: =IF($K72=$V$61,$L72,0) -> 0 | W72: =IF($K72=$V$61,$N72,0) -> 0 | X72: =IF($K72=$X$61,$L72,0) -> 0 | Y72: =IF($K72=$X$61,$N72,0) -> 0 | Z72: =IF($K72=$Z$61,$L72,0) -> 0 | AA72: =IF($K72=$Z$61,$N72,0) -> 0 | AB72: =IF($K72=$AB$61,$L72,0) -> 0 | AC72: =IF($K72=$AB$61,$N72,0) -> 0 | AD72: =IF($K72=$AD$61,$L72,0) -> 0 | AE72: =IF($K72=$AD$61,$N72,0) -> 0 | AF72: =IF($K72=$AF$61,$L72,0) -> 0 | AG72: =IF($K72=$AF$61,$N72,0) -> 0 | AH72: =IF($K72=$AH$61,$L72,0) -> 0 | AI72: =IF($K72=$AH$61,$N72,0) -> 0 | AJ72: =IF($K72=$AJ$61,$L72,0) -> 0 | AK72: =IF($K72=$AJ$61,$N72,0) -> 0 | AL72: =IF($K72=$AL$61,$L72,0) -> 0 | AM72: =IF($K72=$AL$61,$N72,0) -> 0 | AN72: =IF($K72=$AN$61,$L72,0) -> 0 | AO72: =IF($K72=$AN$61,$N72,0) -> 0 | AP72: =IF($K72=$AP$61,$L72,0) -> 0 | AQ72: =IF($K72=$AP$61,$N72,0) -> 0 | AR72: =IF($K72=$AR$61,$L72,0) -> 0 | AS72: =IF($K72=$AR$61,$N72,0) -> 0 | AT72: =IF($K72=$AT$61,$L72,0) -> 0 | AU72: =IF($K72=$AT$61,$N72,0) -> 0 | AV72: =IF($K72=$AV$61,$L72,0) -> 0 | AW72: =IF($K72=$AV$61,$N72,0) -> 0 | AX72: =IF($K72=$AX$61,$L72,0) -> 0 | AY72: =IF($K72=$AX$61,$N72,0) -> 0 | AZ72: =IF($K72=$AZ$61,$L72,0) -> 0 | BA72: =IF($K72=$AZ$61,$N72,0) -> 0 | BB72: =IF($K72=$BB$61,$L72,0) -> 0 | BC72: =IF($K72=$BB$61,$N72,0) -> 0 | BD72: =IF($O72=$BD$61,$P72,0) -> 0 | BE72: =IF($O72=$BD$61,$R72,0) -> 0 | BF72: =IF($O72=$BF$61,$P72,0) -> 0 | BG72: =IF($O72=$BF$61,$R72,0) -> 0 | BH72: =IF($O72=$BH$61,$P72,0) -> 0 | BI72: =IF($O72=$BH$61,$R72,0) -> 0 | BJ72: =IF($O72=$BJ$61,$P72,0) -> 0 | BK72: =IF($O72=$BJ$61,$R72,0) -> 0 | BL72: =IF($O72=$BL$61,$P72,0) -> 0 | BM72: =IF($O72=$BL$61,$R72,0) -> 0 | BN72: =IF($O72=$BN$61,$P72,0) -> 0 | BO72: =IF($O72=$BN$61,$R72,0) -> 0 | BP72: =IF($O72=$BP$61,$P72,0) -> 0 | BQ72: =IF($O72=$BP$61,$R72,0) -> 0 | BR72: =IF($O72=$BR$61,$P72,0) -> 0 | BS72: =IF($O72=$BR$61,$R72,0) -> 0 | BT72: =IF($O72=$BT$61,$P72,0) -> 0 | BU72: =IF($O72=$BT$61,$R72,0) -> 0 | BV72: =IF($O72=$BV$61,$P72,0) -> 0 | BW72: =IF($O72=$BV$61,$R72,0) -> 0 | BX72: =IF($O72=$BX$61,$P72,0) -> 0 | BY72: =IF($O72=$BX$61,$R72,0) -> 0 | BZ72: =IF($O72=$BZ$61,$P72,0) -> 0 | CA72: =IF($O72=$BZ$61,$R72,0) -> 0 | CB72: =IF($O72=$CB$61,$P72,0) -> 0 | CC72: =IF($O72=$CB$61,$R72,0) -> 0 | CD72: =IF($O72=$CD$61,$P72,0) -> 0 | CE72: =IF($O72=$CD$61,$R72,0) -> 0 | CF72: =IF($O72=$CF$61,$P72,0) -> 0 | CG72: =IF($O72=$CF$61,$R72,0) -> 0 | CH72: =IF($O72=$CH$61,$P72,0) -> 0 | CI72: =IF($O72=$CH$61,$R72,0) -> 0 | CJ72: =IF($O72=$CJ$61,$P72,0) -> 0 | CK72: =IF($O72=$CJ$61,$R72,0) -> 0 | CL72: =IF($O72=$CL$61,$P72,0) -> 0 | CM72: =IF($O72=$CL$61,$R72,0) -> 0 | CN72: =IF($O72=$CN$61,$P72,0) -> 0 | CO72: =IF($O72=$CN$61,$R72,0) -> 0 | CP72: =IF($O72=$CP$61,$P72,0) -> 0 | CQ72: =IF($O72=$CP$61,$R72,0) -> 0 | CR72: =IF($O72=$CR$61,$P72,0) -> 0 | CS72: =IF($O72=$CR$61,$R72,0) -> 0 | CT72: =IF($O72=$CT$61,$P72,0) -> 0 | CU72: =IF($O72=$CT$61,$R72,0) -> 0 | CV72: =IF($O72=$CV$61,$P72,0) -> 0 | CW72: =IF($O72=$CV$61,$R72,0) -> 0 | CX72: =IF($O72=$CX$61,$P72,0) -> 0 | CY72: =IF($O72=$CX$61,$R72,0) -> 0
H73: =S73*1.45 -> 0 | N73: =L73*M73 -> 0 | R73: =Q73*P73 -> 0 | S73: =R73+N73 -> 0 | T73: =IF(H73<>0,1-(S73/H73),0) -> 0 | V73: =IF($K73=$V$61,$L73,0) -> 0 | W73: =IF($K73=$V$61,$N73,0) -> 0 | X73: =IF($K73=$X$61,$L73,0) -> 0 | Y73: =IF($K73=$X$61,$N73,0) -> 0 | Z73: =IF($K73=$Z$61,$L73,0) -> 0 | AA73: =IF($K73=$Z$61,$N73,0) -> 0 | AB73: =IF($K73=$AB$61,$L73,0) -> 0 | AC73: =IF($K73=$AB$61,$N73,0) -> 0 | AD73: =IF($K73=$AD$61,$L73,0) -> 0 | AE73: =IF($K73=$AD$61,$N73,0) -> 0 | AF73: =IF($K73=$AF$61,$L73,0) -> 0 | AG73: =IF($K73=$AF$61,$N73,0) -> 0 | AH73: =IF($K73=$AH$61,$L73,0) -> 0 | AI73: =IF($K73=$AH$61,$N73,0) -> 0 | AJ73: =IF($K73=$AJ$61,$L73,0) -> 0 | AK73: =IF($K73=$AJ$61,$N73,0) -> 0 | AL73: =IF($K73=$AL$61,$L73,0) -> 0 | AM73: =IF($K73=$AL$61,$N73,0) -> 0 | AN73: =IF($K73=$AN$61,$L73,0) -> 0 | AO73: =IF($K73=$AN$61,$N73,0) -> 0 | AP73: =IF($K73=$AP$61,$L73,0) -> 0 | AQ73: =IF($K73=$AP$61,$N73,0) -> 0 | AR73: =IF($K73=$AR$61,$L73,0) -> 0 | AS73: =IF($K73=$AR$61,$N73,0) -> 0 | AT73: =IF($K73=$AT$61,$L73,0) -> 0 | AU73: =IF($K73=$AT$61,$N73,0) -> 0 | AV73: =IF($K73=$AV$61,$L73,0) -> 0 | AW73: =IF($K73=$AV$61,$N73,0) -> 0 | AX73: =IF($K73=$AX$61,$L73,0) -> 0 | AY73: =IF($K73=$AX$61,$N73,0) -> 0 | AZ73: =IF($K73=$AZ$61,$L73,0) -> 0 | BA73: =IF($K73=$AZ$61,$N73,0) -> 0 | BB73: =IF($K73=$BB$61,$L73,0) -> 0 | BC73: =IF($K73=$BB$61,$N73,0) -> 0 | BD73: =IF($O73=$BD$61,$P73,0) -> 0 | BE73: =IF($O73=$BD$61,$R73,0) -> 0 | BF73: =IF($O73=$BF$61,$P73,0) -> 0 | BG73: =IF($O73=$BF$61,$R73,0) -> 0 | BH73: =IF($O73=$BH$61,$P73,0) -> 0 | BI73: =IF($O73=$BH$61,$R73,0) -> 0 | BJ73: =IF($O73=$BJ$61,$P73,0) -> 0 | BK73: =IF($O73=$BJ$61,$R73,0) -> 0 | BL73: =IF($O73=$BL$61,$P73,0) -> 0 | BM73: =IF($O73=$BL$61,$R73,0) -> 0 | BN73: =IF($O73=$BN$61,$P73,0) -> 0 | BO73: =IF($O73=$BN$61,$R73,0) -> 0 | BP73: =IF($O73=$BP$61,$P73,0) -> 0 | BQ73: =IF($O73=$BP$61,$R73,0) -> 0 | BR73: =IF($O73=$BR$61,$P73,0) -> 0 | BS73: =IF($O73=$BR$61,$R73,0) -> 0 | BT73: =IF($O73=$BT$61,$P73,0) -> 0 | BU73: =IF($O73=$BT$61,$R73,0) -> 0 | BV73: =IF($O73=$BV$61,$P73,0) -> 0 | BW73: =IF($O73=$BV$61,$R73,0) -> 0 | BX73: =IF($O73=$BX$61,$P73,0) -> 0 | BY73: =IF($O73=$BX$61,$R73,0) -> 0 | BZ73: =IF($O73=$BZ$61,$P73,0) -> 0 | CA73: =IF($O73=$BZ$61,$R73,0) -> 0 | CB73: =IF($O73=$CB$61,$P73,0) -> 0 | CC73: =IF($O73=$CB$61,$R73,0) -> 0 | CD73: =IF($O73=$CD$61,$P73,0) -> 0 | CE73: =IF($O73=$CD$61,$R73,0) -> 0 | CF73: =IF($O73=$CF$61,$P73,0) -> 0 | CG73: =IF($O73=$CF$61,$R73,0) -> 0 | CH73: =IF($O73=$CH$61,$P73,0) -> 0 | CI73: =IF($O73=$CH$61,$R73,0) -> 0 | CJ73: =IF($O73=$CJ$61,$P73,0) -> 0 | CK73: =IF($O73=$CJ$61,$R73,0) -> 0 | CL73: =IF($O73=$CL$61,$P73,0) -> 0 | CM73: =IF($O73=$CL$61,$R73,0) -> 0 | CN73: =IF($O73=$CN$61,$P73,0) -> 0 | CO73: =IF($O73=$CN$61,$R73,0) -> 0 | CP73: =IF($O73=$CP$61,$P73,0) -> 0 | CQ73: =IF($O73=$CP$61,$R73,0) -> 0 | CR73: =IF($O73=$CR$61,$P73,0) -> 0 | CS73: =IF($O73=$CR$61,$R73,0) -> 0 | CT73: =IF($O73=$CT$61,$P73,0) -> 0 | CU73: =IF($O73=$CT$61,$R73,0) -> 0 | CV73: =IF($O73=$CV$61,$P73,0) -> 0 | CW73: =IF($O73=$CV$61,$R73,0) -> 0 | CX73: =IF($O73=$CX$61,$P73,0) -> 0 | CY73: =IF($O73=$CX$61,$R73,0) -> 0
H74: =S74*1.45 -> 0 | N74: =L74*M74 -> 0 | R74: =Q74*P74 -> 0 | S74: =R74+N74 -> 0 | T74: =IF(H74<>0,1-(S74/H74),0) -> 0 | V74: =IF($K74=$V$61,$L74,0) -> 0 | W74: =IF($K74=$V$61,$N74,0) -> 0 | X74: =IF($K74=$X$61,$L74,0) -> 0 | Y74: =IF($K74=$X$61,$N74,0) -> 0 | Z74: =IF($K74=$Z$61,$L74,0) -> 0 | AA74: =IF($K74=$Z$61,$N74,0) -> 0 | AB74: =IF($K74=$AB$61,$L74,0) -> 0 | AC74: =IF($K74=$AB$61,$N74,0) -> 0 | AD74: =IF($K74=$AD$61,$L74,0) -> 0 | AE74: =IF($K74=$AD$61,$N74,0) -> 0 | AF74: =IF($K74=$AF$61,$L74,0) -> 0 | AG74: =IF($K74=$AF$61,$N74,0) -> 0 | AH74: =IF($K74=$AH$61,$L74,0) -> 0 | AI74: =IF($K74=$AH$61,$N74,0) -> 0 | AJ74: =IF($K74=$AJ$61,$L74,0) -> 0 | AK74: =IF($K74=$AJ$61,$N74,0) -> 0 | AL74: =IF($K74=$AL$61,$L74,0) -> 0 | AM74: =IF($K74=$AL$61,$N74,0) -> 0 | AN74: =IF($K74=$AN$61,$L74,0) -> 0 | AO74: =IF($K74=$AN$61,$N74,0) -> 0 | AP74: =IF($K74=$AP$61,$L74,0) -> 0 | AQ74: =IF($K74=$AP$61,$N74,0) -> 0 | AR74: =IF($K74=$AR$61,$L74,0) -> 0 | AS74: =IF($K74=$AR$61,$N74,0) -> 0 | AT74: =IF($K74=$AT$61,$L74,0) -> 0 | AU74: =IF($K74=$AT$61,$N74,0) -> 0 | AV74: =IF($K74=$AV$61,$L74,0) -> 0 | AW74: =IF($K74=$AV$61,$N74,0) -> 0 | AX74: =IF($K74=$AX$61,$L74,0) -> 0 | AY74: =IF($K74=$AX$61,$N74,0) -> 0 | AZ74: =IF($K74=$AZ$61,$L74,0) -> 0 | BA74: =IF($K74=$AZ$61,$N74,0) -> 0 | BB74: =IF($K74=$BB$61,$L74,0) -> 0 | BC74: =IF($K74=$BB$61,$N74,0) -> 0 | BD74: =IF($O74=$BD$61,$P74,0) -> 0 | BE74: =IF($O74=$BD$61,$R74,0) -> 0 | BF74: =IF($O74=$BF$61,$P74,0) -> 0 | BG74: =IF($O74=$BF$61,$R74,0) -> 0 | BH74: =IF($O74=$BH$61,$P74,0) -> 0 | BI74: =IF($O74=$BH$61,$R74,0) -> 0 | BJ74: =IF($O74=$BJ$61,$P74,0) -> 0 | BK74: =IF($O74=$BJ$61,$R74,0) -> 0 | BL74: =IF($O74=$BL$61,$P74,0) -> 0 | BM74: =IF($O74=$BL$61,$R74,0) -> 0 | BN74: =IF($O74=$BN$61,$P74,0) -> 0 | BO74: =IF($O74=$BN$61,$R74,0) -> 0 | BP74: =IF($O74=$BP$61,$P74,0) -> 0 | BQ74: =IF($O74=$BP$61,$R74,0) -> 0 | BR74: =IF($O74=$BR$61,$P74,0) -> 0 | BS74: =IF($O74=$BR$61,$R74,0) -> 0 | BT74: =IF($O74=$BT$61,$P74,0) -> 0 | BU74: =IF($O74=$BT$61,$R74,0) -> 0 | BV74: =IF($O74=$BV$61,$P74,0) -> 0 | BW74: =IF($O74=$BV$61,$R74,0) -> 0 | BX74: =IF($O74=$BX$61,$P74,0) -> 0 | BY74: =IF($O74=$BX$61,$R74,0) -> 0 | BZ74: =IF($O74=$BZ$61,$P74,0) -> 0 | CA74: =IF($O74=$BZ$61,$R74,0) -> 0 | CB74: =IF($O74=$CB$61,$P74,0) -> 0 | CC74: =IF($O74=$CB$61,$R74,0) -> 0 | CD74: =IF($O74=$CD$61,$P74,0) -> 0 | CE74: =IF($O74=$CD$61,$R74,0) -> 0 | CF74: =IF($O74=$CF$61,$P74,0) -> 0 | CG74: =IF($O74=$CF$61,$R74,0) -> 0 | CH74: =IF($O74=$CH$61,$P74,0) -> 0 | CI74: =IF($O74=$CH$61,$R74,0) -> 0 | CJ74: =IF($O74=$CJ$61,$P74,0) -> 0 | CK74: =IF($O74=$CJ$61,$R74,0) -> 0 | CL74: =IF($O74=$CL$61,$P74,0) -> 0 | CM74: =IF($O74=$CL$61,$R74,0) -> 0 | CN74: =IF($O74=$CN$61,$P74,0) -> 0 | CO74: =IF($O74=$CN$61,$R74,0) -> 0 | CP74: =IF($O74=$CP$61,$P74,0) -> 0 | CQ74: =IF($O74=$CP$61,$R74,0) -> 0 | CR74: =IF($O74=$CR$61,$P74,0) -> 0 | CS74: =IF($O74=$CR$61,$R74,0) -> 0 | CT74: =IF($O74=$CT$61,$P74,0) -> 0 | CU74: =IF($O74=$CT$61,$R74,0) -> 0 | CV74: =IF($O74=$CV$61,$P74,0) -> 0 | CW74: =IF($O74=$CV$61,$R74,0) -> 0 | CX74: =IF($O74=$CX$61,$P74,0) -> 0 | CY74: =IF($O74=$CX$61,$R74,0) -> 0
... H81: =S81*1.45 -> 0 | N81: =L81*M81 -> 0 | R81: =Q81*P81 -> 0 | S81: =R81+N81 -> 0 | T81: =IF(H81<>0,1-(S81/H81),0) -> 0 | V81: =IF($K81=$V$61,$L81,0) -> 0 | W81: =IF($K81=$V$61,$N81,0) -> 0 | X81: =IF($K81=$X$61,$L81,0) -> 0 | Y81: =IF($K81=$X$61,$N81,0) -> 0 | Z81: =IF($K81=$Z$61,$L81,0) -> 0 | AA81: =IF($K81=$Z$61,$N81,0) -> 0 | AB81: =IF($K81=$AB$61,$L81,0) -> 0 | AC81: =IF($K81=$AB$61,$N81,0) -> 0 | AD81: =IF($K81=$AD$61,$L81,0) -> 0 | AE81: =IF($K81=$AD$61,$N81,0) -> 0 | AF81: =IF($K81=$AF$61,$L81,0) -> 0 | AG81: =IF($K81=$AF$61,$N81,0) -> 0 | AH81: =IF($K81=$AH$61,$L81,0) -> 0 | AI81: =IF($K81=$AH$61,$N81,0) -> 0 | AJ81: =IF($K81=$AJ$61,$L81,0) -> 0 | AK81: =IF($K81=$AJ$61,$N81,0) -> 0 | AL81: =IF($K81=$AL$61,$L81,0) -> 0 | AM81: =IF($K81=$AL$61,$N81,0) -> 0 | AN81: =IF($K81=$AN$61,$L81,0) -> 0 | AO81: =IF($K81=$AN$61,$N81,0) -> 0 | AP81: =IF($K81=$AP$61,$L81,0) -> 0 | AQ81: =IF($K81=$AP$61,$N81,0) -> 0 | AR81: =IF($K81=$AR$61,$L81,0) -> 0 | AS81: =IF($K81=$AR$61,$N81,0) -> 0 | AT81: =IF($K81=$AT$61,$L81,0) -> 0 | AU81: =IF($K81=$AT$61,$N81,0) -> 0 | AV81: =IF($K81=$AV$61,$L81,0) -> 0 | AW81: =IF($K81=$AV$61,$N81,0) -> 0 | AX81: =IF($K81=$AX$61,$L81,0) -> 0 | AY81: =IF($K81=$AX$61,$N81,0) -> 0 | AZ81: =IF($K81=$AZ$61,$L81,0) -> 0 | BA81: =IF($K81=$AZ$61,$N81,0) -> 0 | BB81: =IF($K81=$BB$61,$L81,0) -> 0 | BC81: =IF($K81=$BB$61,$N81,0) -> 0 | BD81: =IF($O81=$BD$61,$P81,0) -> 0 | BE81: =IF($O81=$BD$61,$R81,0) -> 0 | BF81: =IF($O81=$BF$61,$P81,0) -> 0 | BG81: =IF($O81=$BF$61,$R81,0) -> 0 | BH81: =IF($O81=$BH$61,$P81,0) -> 0 | BI81: =IF($O81=$BH$61,$R81,0) -> 0 | BJ81: =IF($O81=$BJ$61,$P81,0) -> 0 | BK81: =IF($O81=$BJ$61,$R81,0) -> 0 | BL81: =IF($O81=$BL$61,$P81,0) -> 0 | BM81: =IF($O81=$BL$61,$R81,0) -> 0 | BN81: =IF($O81=$BN$61,$P81,0) -> 0 | BO81: =IF($O81=$BN$61,$R81,0) -> 0 | BP81: =IF($O81=$BP$61,$P81,0) -> 0 | BQ81: =IF($O81=$BP$61,$R81,0) -> 0 | BR81: =IF($O81=$BR$61,$P81,0) -> 0 | BS81: =IF($O81=$BR$61,$R81,0) -> 0 | BT81: =IF($O81=$BT$61,$P81,0) -> 0 | BU81: =IF($O81=$BT$61,$R81,0) -> 0 | BV81: =IF($O81=$BV$61,$P81,0) -> 0 | BW81: =IF($O81=$BV$61,$R81,0) -> 0 | BX81: =IF($O81=$BX$61,$P81,0) -> 0 | BY81: =IF($O81=$BX$61,$R81,0) -> 0 | BZ81: =IF($O81=$BZ$61,$P81,0) -> 0 | CA81: =IF($O81=$BZ$61,$R81,0) -> 0 | CB81: =IF($O81=$CB$61,$P81,0) -> 0 | CC81: =IF($O81=$CB$61,$R81,0) -> 0 | CD81: =IF($O81=$CD$61,$P81,0) -> 0 | CE81: =IF($O81=$CD$61,$R81,0) -> 0 | CF81: =IF($O81=$CF$61,$P81,0) -> 0 | CG81: =IF($O81=$CF$61,$R81,0) -> 0 | CH81: =IF($O81=$CH$61,$P81,0) -> 0 | CI81: =IF($O81=$CH$61,$R81,0) -> 0 | CJ81: =IF($O81=$CJ$61,$P81,0) -> 0 | CK81: =IF($O81=$CJ$61,$R81,0) -> 0 | CL81: =IF($O81=$CL$61,$P81,0) -> 0 | CM81: =IF($O81=$CL$61,$R81,0) -> 0 | CN81: =IF($O81=$CN$61,$P81,0) -> 0 | CO81: =IF($O81=$CN$61,$R81,0) -> 0 | CP81: =IF($O81=$CP$61,$P81,0) -> 0 | CQ81: =IF($O81=$CP$61,$R81,0) -> 0 | CR81: =IF($O81=$CR$61,$P81,0) -> 0 | CS81: =IF($O81=$CR$61,$R81,0) -> 0 | CT81: =IF($O81=$CT$61,$P81,0) -> 0 | CU81: =IF($O81=$CT$61,$R81,0) -> 0 | CV81: =IF($O81=$CV$61,$P81,0) -> 0 | CW81: =IF($O81=$CV$61,$R81,0) -> 0 | CX81: =IF($O81=$CX$61,$P81,0) -> 0 | CY81: =IF($O81=$CX$61,$R81,0) -> 0
C82: 小 計 | H82: =SUM(H63:H81) -> 0 | K82: 計 | N82: =L82*M82 -> 0 | R82: ﾍﾟｰｼﾞ計 | S82: =SUM(S62:S81) -> 0 | T82: =IF(H82<>0,1-(S82/H82),0) -> 0 | V82: =IF($K82=$V$61,$L82,0) -> 0 | W82: =IF($K82=$V$61,$N82,0) -> 0 | X82: =IF($K82=$X$61,$L82,0) -> 0 | Y82: =IF($K82=$X$61,$N82,0) -> 0 | Z82: =IF($K82=$Z$61,$L82,0) -> 0 | AA82: =IF($K82=$Z$61,$N82,0) -> 0 | AB82: =IF($K82=$AB$61,$L82,0) -> 0 | AC82: =IF($K82=$AB$61,$N82,0) -> 0 | AD82: =IF($K82=$AD$61,$L82,0) -> 0 | AE82: =IF($K82=$AD$61,$N82,0) -> 0 | AF82: =IF($K82=$AF$61,$L82,0) -> 0 | AG82: =IF($K82=$AF$61,$N82,0) -> 0 | AH82: =IF($K82=$AH$61,$L82,0) -> 0 | AI82: =IF($K82=$AH$61,$N82,0) -> 0 | AJ82: =IF($K82=$AJ$61,$L82,0) -> 0 | AK82: =IF($K82=$AJ$61,$N82,0) -> 0 | AL82: =IF($K82=$AL$61,$L82,0) -> 0 | AM82: =IF($K82=$AL$61,$N82,0) -> 0 | AN82: =IF($K82=$AN$61,$L82,0) -> 0 | AO82: =IF($K82=$AN$61,$N82,0) -> 0 | AP82: =IF($K82=$AP$61,$L82,0) -> 0 | AQ82: =IF($K82=$AP$61,$N82,0) -> 0 | AR82: =IF($K82=$AR$61,$L82,0) -> 0 | AS82: =IF($K82=$AR$61,$N82,0) -> 0 | AT82: =IF($K82=$AT$61,$L82,0) -> 0 | AU82: =IF($K82=$AT$61,$N82,0) -> 0 | AV82: =IF($K82=$AV$61,$L82,0) -> 0 | AW82: =IF($K82=$AV$61,$N82,0) -> 0 | AX82: =IF($K82=$AX$61,$L82,0) -> 0 | AY82: =IF($K82=$AX$61,$N82,0) -> 0 | AZ82: =IF($K82=$AZ$61,$L82,0) -> 0 | BA82: =IF($K82=$AZ$61,$N82,0) -> 0 | BB82: =IF($K82=$BB$61,$L82,0) -> 0 | BC82: =IF($K82=$BB$61,$N82,0) -> 0 | BD82: =IF($O82=$BD$61,$P82,0) -> 0 | BE82: =IF($O82=$BD$61,$R82,0) -> 0 | BF82: =IF($O82=$BF$61,$P82,0) -> 0 | BG82: =IF($O82=$BF$61,$R82,0) -> 0 | BH82: =IF($O82=$BH$61,$P82,0) -> 0 | BI82: =IF($O82=$BH$61,$R82,0) -> 0 | BJ82: =IF($O82=$BJ$61,$P82,0) -> 0 | BK82: =IF($O82=$BJ$61,$R82,0) -> 0 | BL82: =IF($O82=$BL$61,$P82,0) -> 0 | BM82: =IF($O82=$BL$61,$R82,0) -> 0 | BN82: =IF($O82=$BN$61,$P82,0) -> 0 | BO82: =IF($O82=$BN$61,$R82,0) -> 0 | BP82: =IF($O82=$BP$61,$P82,0) -> 0 | BQ82: =IF($O82=$BP$61,$R82,0) -> 0 | BR82: =IF($O82=$BR$61,$P82,0) -> 0 | BS82: =IF($O82=$BR$61,$R82,0) -> 0 | BT82: =IF($O82=$BT$61,$P82,0) -> 0 | BU82: =IF($O82=$BT$61,$R82,0) -> 0 | BV82: =IF($O82=$BV$61,$P82,0) -> 0 | BW82: =IF($O82=$BV$61,$R82,0) -> 0 | BX82: =IF($O82=$BX$61,$P82,0) -> 0 | BY82: =IF($O82=$BX$61,$R82,0) -> 0 | BZ82: =IF($O82=$BZ$61,$P82,0) -> 0 | CA82: =IF($O82=$BZ$61,$R82,0) -> 0 | CB82: =IF($O82=$CB$61,$P82,0) -> 0 | CC82: =IF($O82=$CB$61,$R82,0) -> 0 | CD82: =IF($O82=$CD$61,$P82,0) -> 0 | CE82: =IF($O82=$CD$61,$R82,0) -> 0 | CF82: =IF($O82=$CF$61,$P82,0) -> 0 | CG82: =IF($O82=$CF$61,$R82,0) -> 0 | CH82: =IF($O82=$CH$61,$P82,0) -> 0 | CI82: =IF($O82=$CH$61,$R82,0) -> 0 | CJ82: =IF($O82=$CJ$61,$P82,0) -> 0 | CK82: =IF($O82=$CJ$61,$R82,0) -> 0 | CL82: =IF($O82=$CL$61,$P82,0) -> 0 | CM82: =IF($O82=$CL$61,$R82,0) -> 0 | CN82: =IF($O82=$CN$61,$P82,0) -> 0 | CO82: =IF($O82=$CN$61,$R82,0) -> 0 | CP82: =IF($O82=$CP$61,$P82,0) -> 0 | CQ82: =IF($O82=$CP$61,$R82,0) -> 0 | CR82: =IF($O82=$CR$61,$P82,0) -> 0 | CS82: =IF($O82=$CR$61,$R82,0) -> 0 | CT82: =IF($O82=$CT$61,$P82,0) -> 0 | CU82: =IF($O82=$CT$61,$R82,0) -> 0 | CV82: =IF($O82=$CV$61,$P82,0) -> 0 | CW82: =IF($O82=$CV$61,$R82,0) -> 0 | CX82: =IF($O82=$CX$61,$P82,0) -> 0 | CY82: =IF($O82=$CX$61,$R82,0) -> 0
N83: =L83*M83 -> 0 | R83: =P83*Q83 -> 0 | S83: =N83+R83 -> 0 | T83: =IF(H83<>0,1-(S83/H83),0) -> 0 | V83: =IF($K83=$V$61,$L83,0) -> 0 | W83: =IF($K83=$V$61,$N83,0) -> 0 | X83: =IF($K83=$X$61,$L83,0) -> 0 | Y83: =IF($K83=$X$61,$N83,0) -> 0 | Z83: =IF($K83=$Z$61,$L83,0) -> 0 | AA83: =IF($K83=$Z$61,$N83,0) -> 0 | AB83: =IF($K83=$AB$61,$L83,0) -> 0 | AC83: =IF($K83=$AB$61,$N83,0) -> 0 | AD83: =IF($K83=$AD$61,$L83,0) -> 0 | AE83: =IF($K83=$AD$61,$N83,0) -> 0 | AF83: =IF($K83=$AF$61,$L83,0) -> 0 | AG83: =IF($K83=$AF$61,$N83,0) -> 0 | AH83: =IF($K83=$AH$61,$L83,0) -> 0 | AI83: =IF($K83=$AH$61,$N83,0) -> 0 | AJ83: =IF($K83=$AJ$61,$L83,0) -> 0 | AK83: =IF($K83=$AJ$61,$N83,0) -> 0 | AL83: =IF($K83=$AL$61,$L83,0) -> 0 | AM83: =IF($K83=$AL$61,$N83,0) -> 0 | AN83: =IF($K83=$AN$61,$L83,0) -> 0 | AO83: =IF($K83=$AN$61,$N83,0) -> 0 | AP83: =IF($K83=$AP$61,$L83,0) -> 0 | AQ83: =IF($K83=$AP$61,$N83,0) -> 0 | AR83: =IF($K83=$AR$61,$L83,0) -> 0 | AS83: =IF($K83=$AR$61,$N83,0) -> 0 | AT83: =IF($K83=$AT$61,$L83,0) -> 0 | AU83: =IF($K83=$AT$61,$N83,0) -> 0 | AV83: =IF($K83=$AV$61,$L83,0) -> 0 | AW83: =IF($K83=$AV$61,$N83,0) -> 0 | AX83: =IF($K83=$AX$61,$L83,0) -> 0 | AY83: =IF($K83=$AX$61,$N83,0) -> 0 | AZ83: =IF($K83=$AZ$61,$L83,0) -> 0 | BA83: =IF($K83=$AZ$61,$N83,0) -> 0 | BB83: =IF($K83=$BB$61,$L83,0) -> 0 | BC83: =IF($K83=$BB$61,$N83,0) -> 0 | BD83: =IF($O83=$BD$61,$P83,0) -> 0 | BE83: =IF($O83=$BD$61,$R83,0) -> 0 | BF83: =IF($O83=$BF$61,$P83,0) -> 0 | BG83: =IF($O83=$BF$61,$R83,0) -> 0 | BH83: =IF($O83=$BH$61,$P83,0) -> 0 | BI83: =IF($O83=$BH$61,$R83,0) -> 0 | BJ83: =IF($O83=$BJ$61,$P83,0) -> 0 | BK83: =IF($O83=$BJ$61,$R83,0) -> 0 | BL83: =IF($O83=$BL$61,$P83,0) -> 0 | BM83: =IF($O83=$BL$61,$R83,0) -> 0 | BN83: =IF($O83=$BN$61,$P83,0) -> 0 | BO83: =IF($O83=$BN$61,$R83,0) -> 0 | BP83: =IF($O83=$BP$61,$P83,0) -> 0 | BQ83: =IF($O83=$BP$61,$R83,0) -> 0 | BR83: =IF($O83=$BR$61,$P83,0) -> 0 | BS83: =IF($O83=$BR$61,$R83,0) -> 0 | BT83: =IF($O83=$BT$61,$P83,0) -> 0 | BU83: =IF($O83=$BT$61,$R83,0) -> 0 | BV83: =IF($O83=$BV$61,$P83,0) -> 0 | BW83: =IF($O83=$BV$61,$R83,0) -> 0 | BX83: =IF($O83=$BX$61,$P83,0) -> 0 | BY83: =IF($O83=$BX$61,$R83,0) -> 0 | BZ83: =IF($O83=$BZ$61,$P83,0) -> 0 | CA83: =IF($O83=$BZ$61,$R83,0) -> 0 | CB83: =IF($O83=$CB$61,$P83,0) -> 0 | CC83: =IF($O83=$CB$61,$R83,0) -> 0 | CD83: =IF($O83=$CD$61,$P83,0) -> 0 | CE83: =IF($O83=$CD$61,$R83,0) -> 0 | CF83: =IF($O83=$CF$61,$P83,0) -> 0 | CG83: =IF($O83=$CF$61,$R83,0) -> 0 | CH83: =IF($O83=$CH$61,$P83,0) -> 0 | CI83: =IF($O83=$CH$61,$R83,0) -> 0 | CJ83: =IF($O83=$CJ$61,$P83,0) -> 0 | CK83: =IF($O83=$CJ$61,$R83,0) -> 0 | CL83: =IF($O83=$CL$61,$P83,0) -> 0 | CM83: =IF($O83=$CL$61,$R83,0) -> 0 | CN83: =IF($O83=$CN$61,$P83,0) -> 0 | CO83: =IF($O83=$CN$61,$R83,0) -> 0 | CP83: =IF($O83=$CP$61,$P83,0) -> 0 | CQ83: =IF($O83=$CP$61,$R83,0) -> 0 | CR83: =IF($O83=$CR$61,$P83,0) -> 0 | CS83: =IF($O83=$CR$61,$R83,0) -> 0 | CT83: =IF($O83=$CT$61,$P83,0) -> 0 | CU83: =IF($O83=$CT$61,$R83,0) -> 0 | CV83: =IF($O83=$CV$61,$P83,0) -> 0 | CW83: =IF($O83=$CV$61,$R83,0) -> 0 | CX83: =IF($O83=$CX$61,$P83,0) -> 0 | CY83: =IF($O83=$CX$61,$R83,0) -> 0
I84: ラグズ建築 | N84: =L84*M84 -> 0 | R84: =P84*Q84 -> 0 | S84: =N84+R84 -> 0 | V84: =IF($K84=$V$61,$L84,0) -> 0 | W84: =IF($K84=$V$61,$N84,0) -> 0 | X84: =IF($K84=$X$61,$L84,0) -> 0 | Y84: =IF($K84=$X$61,$N84,0) -> 0 | Z84: =IF($K84=$Z$61,$L84,0) -> 0 | AA84: =IF($K84=$Z$61,$N84,0) -> 0 | AB84: =IF($K84=$AB$61,$L84,0) -> 0 | AC84: =IF($K84=$AB$61,$N84,0) -> 0 | AD84: =IF($K84=$AD$61,$L84,0) -> 0 | AE84: =IF($K84=$AD$61,$N84,0) -> 0 | AF84: =IF($K84=$AF$61,$L84,0) -> 0 | AG84: =IF($K84=$AF$61,$N84,0) -> 0 | AH84: =IF($K84=$AH$61,$L84,0) -> 0 | AI84: =IF($K84=$AH$61,$N84,0) -> 0 | AJ84: =IF($K84=$AJ$61,$L84,0) -> 0 | AK84: =IF($K84=$AJ$61,$N84,0) -> 0 | AL84: =IF($K84=$AL$61,$L84,0) -> 0 | AM84: =IF($K84=$AL$61,$N84,0) -> 0 | AN84: =IF($K84=$AN$61,$L84,0) -> 0 | AO84: =IF($K84=$AN$61,$N84,0) -> 0 | AP84: =IF($K84=$AP$61,$L84,0) -> 0 | AQ84: =IF($K84=$AP$61,$N84,0) -> 0 | AR84: =IF($K84=$AR$61,$L84,0) -> 0 | AS84: =IF($K84=$AR$61,$N84,0) -> 0 | AT84: =IF($K84=$AT$61,$L84,0) -> 0 | AU84: =IF($K84=$AT$61,$N84,0) -> 0 | AV84: =IF($K84=$AV$61,$L84,0) -> 0 | AW84: =IF($K84=$AV$61,$N84,0) -> 0 | AX84: =IF($K84=$AX$61,$L84,0) -> 0 | AY84: =IF($K84=$AX$61,$N84,0) -> 0 | AZ84: =IF($K84=$AZ$61,$L84,0) -> 0 | BA84: =IF($K84=$AZ$61,$N84,0) -> 0 | BB84: =IF($K84=$BB$61,$L84,0) -> 0 | BC84: =IF($K84=$BB$61,$N84,0) -> 0 | BD84: =IF($O84=$BD$61,$P84,0) -> 0 | BE84: =IF($O84=$BD$61,$R84,0) -> 0 | BF84: =IF($O84=$BF$61,$P84,0) -> 0 | BG84: =IF($O84=$BF$61,$R84,0) -> 0 | BH84: =IF($O84=$BH$61,$P84,0) -> 0 | BI84: =IF($O84=$BH$61,$R84,0) -> 0 | BJ84: =IF($O84=$BJ$61,$P84,0) -> 0 | BK84: =IF($O84=$BJ$61,$R84,0) -> 0 | BL84: =IF($O84=$BL$61,$P84,0) -> 0 | BM84: =IF($O84=$BL$61,$R84,0) -> 0 | BN84: =IF($O84=$BN$61,$P84,0) -> 0 | BO84: =IF($O84=$BN$61,$R84,0) -> 0 | BP84: =IF($O84=$BP$61,$P84,0) -> 0 | BQ84: =IF($O84=$BP$61,$R84,0) -> 0 | BR84: =IF($O84=$BR$61,$P84,0) -> 0 | BS84: =IF($O84=$BR$61,$R84,0) -> 0 | BT84: =IF($O84=$BT$61,$P84,0) -> 0 | BU84: =IF($O84=$BT$61,$R84,0) -> 0 | BV84: =IF($O84=$BV$61,$P84,0) -> 0 | BW84: =IF($O84=$BV$61,$R84,0) -> 0 | BX84: =IF($O84=$BX$61,$P84,0) -> 0 | BY84: =IF($O84=$BX$61,$R84,0) -> 0 | BZ84: =IF($O84=$BZ$61,$P84,0) -> 0 | CA84: =IF($O84=$BZ$61,$R84,0) -> 0 | CB84: =IF($O84=$CB$61,$P84,0) -> 0 | CC84: =IF($O84=$CB$61,$R84,0) -> 0 | CD84: =IF($O84=$CD$61,$P84,0) -> 0 | CE84: =IF($O84=$CD$61,$R84,0) -> 0 | CF84: =IF($O84=$CF$61,$P84,0) -> 0 | CG84: =IF($O84=$CF$61,$R84,0) -> 0 | CH84: =IF($O84=$CH$61,$P84,0) -> 0 | CI84: =IF($O84=$CH$61,$R84,0) -> 0 | CJ84: =IF($O84=$CJ$61,$P84,0) -> 0 | CK84: =IF($O84=$CJ$61,$R84,0) -> 0 | CL84: =IF($O84=$CL$61,$P84,0) -> 0 | CM84: =IF($O84=$CL$61,$R84,0) -> 0 | CN84: =IF($O84=$CN$61,$P84,0) -> 0 | CO84: =IF($O84=$CN$61,$R84,0) -> 0 | CP84: =IF($O84=$CP$61,$P84,0) -> 0 | CQ84: =IF($O84=$CP$61,$R84,0) -> 0 | CR84: =IF($O84=$CR$61,$P84,0) -> 0 | CS84: =IF($O84=$CR$61,$R84,0) -> 0 | CT84: =IF($O84=$CT$61,$P84,0) -> 0 | CU84: =IF($O84=$CT$61,$R84,0) -> 0 | CV84: =IF($O84=$CV$61,$P84,0) -> 0 | CW84: =IF($O84=$CV$61,$R84,0) -> 0 | CX84: =IF($O84=$CX$61,$P84,0) -> 0 | CY84: =IF($O84=$CX$61,$R84,0) -> 0
E85: 内 訳 明 細 書 | J85: 3 | K85: 日付 | N85: =L85*M85 -> 0 | R85: =P85*Q85 -> 0 | S85: =N85+R85 -> 0 | V85: =IF($K85=$V$61,$L85,0) -> 0 | W85: =IF($K85=$V$61,$N85,0) -> 0 | X85: =IF($K85=$X$61,$L85,0) -> 0 | Y85: =IF($K85=$X$61,$N85,0) -> 0 | Z85: =IF($K85=$Z$61,$L85,0) -> 0 | AA85: =IF($K85=$Z$61,$N85,0) -> 0 | AB85: =IF($K85=$AB$61,$L85,0) -> 0 | AC85: =IF($K85=$AB$61,$N85,0) -> 0 | AD85: =IF($K85=$AD$61,$L85,0) -> 0 | AE85: =IF($K85=$AD$61,$N85,0) -> 0 | AF85: =IF($K85=$AF$61,$L85,0) -> 0 | AG85: =IF($K85=$AF$61,$N85,0) -> 0 | AH85: =IF($K85=$AH$61,$L85,0) -> 0 | AI85: =IF($K85=$AH$61,$N85,0) -> 0 | AJ85: =IF($K85=$AJ$61,$L85,0) -> 0 | AK85: =IF($K85=$AJ$61,$N85,0) -> 0 | AL85: =IF($K85=$AL$61,$L85,0) -> 0 | AM85: =IF($K85=$AL$61,$N85,0) -> 0 | AN85: =IF($K85=$AN$61,$L85,0) -> 0 | AO85: =IF($K85=$AN$61,$N85,0) -> 0 | AP85: =IF($K85=$AP$61,$L85,0) -> 0 | AQ85: =IF($K85=$AP$61,$N85,0) -> 0 | AR85: =IF($K85=$AR$61,$L85,0) -> 0 | AS85: =IF($K85=$AR$61,$N85,0) -> 0 | AT85: =IF($K85=$AT$61,$L85,0) -> 0 | AU85: =IF($K85=$AT$61,$N85,0) -> 0 | AV85: =IF($K85=$AV$61,$L85,0) -> 0 | AW85: =IF($K85=$AV$61,$N85,0) -> 0 | AX85: =IF($K85=$AX$61,$L85,0) -> 0 | AY85: =IF($K85=$AX$61,$N85,0) -> 0 | AZ85: =IF($K85=$AZ$61,$L85,0) -> 0 | BA85: =IF($K85=$AZ$61,$N85,0) -> 0 | BB85: =IF($K85=$BB$61,$L85,0) -> 0 | BC85: =IF($K85=$BB$61,$N85,0) -> 0 | BD85: =IF($O85=$BD$61,$P85,0) -> 0 | BE85: =IF($O85=$BD$61,$R85,0) -> 0 | BF85: =IF($O85=$BF$61,$P85,0) -> 0 | BG85: =IF($O85=$BF$61,$R85,0) -> 0 | BH85: =IF($O85=$BH$61,$P85,0) -> 0 | BI85: =IF($O85=$BH$61,$R85,0) -> 0 | BJ85: =IF($O85=$BJ$61,$P85,0) -> 0 | BK85: =IF($O85=$BJ$61,$R85,0) -> 0 | BL85: =IF($O85=$BL$61,$P85,0) -> 0 | BM85: =IF($O85=$BL$61,$R85,0) -> 0 | BN85: =IF($O85=$BN$61,$P85,0) -> 0 | BO85: =IF($O85=$BN$61,$R85,0) -> 0 | BP85: =IF($O85=$BP$61,$P85,0) -> 0 | BQ85: =IF($O85=$BP$61,$R85,0) -> 0 | BR85: =IF($O85=$BR$61,$P85,0) -> 0 | BS85: =IF($O85=$BR$61,$R85,0) -> 0 | BT85: =IF($O85=$BT$61,$P85,0) -> 0 | BU85: =IF($O85=$BT$61,$R85,0) -> 0 | BV85: =IF($O85=$BV$61,$P85,0) -> 0 | BW85: =IF($O85=$BV$61,$R85,0) -> 0 | BX85: =IF($O85=$BX$61,$P85,0) -> 0 | BY85: =IF($O85=$BX$61,$R85,0) -> 0 | BZ85: =IF($O85=$BZ$61,$P85,0) -> 0 | CA85: =IF($O85=$BZ$61,$R85,0) -> 0 | CB85: =IF($O85=$CB$61,$P85,0) -> 0 | CC85: =IF($O85=$CB$61,$R85,0) -> 0 | CD85: =IF($O85=$CD$61,$P85,0) -> 0 | CE85: =IF($O85=$CD$61,$R85,0) -> 0 | CF85: =IF($O85=$CF$61,$P85,0) -> 0 | CG85: =IF($O85=$CF$61,$R85,0) -> 0 | CH85: =IF($O85=$CH$61,$P85,0) -> 0 | CI85: =IF($O85=$CH$61,$R85,0) -> 0 | CJ85: =IF($O85=$CJ$61,$P85,0) -> 0 | CK85: =IF($O85=$CJ$61,$R85,0) -> 0 | CL85: =IF($O85=$CL$61,$P85,0) -> 0 | CM85: =IF($O85=$CL$61,$R85,0) -> 0 | CN85: =IF($O85=$CN$61,$P85,0) -> 0 | CO85: =IF($O85=$CN$61,$R85,0) -> 0 | CP85: =IF($O85=$CP$61,$P85,0) -> 0 | CQ85: =IF($O85=$CP$61,$R85,0) -> 0 | CR85: =IF($O85=$CR$61,$P85,0) -> 0 | CS85: =IF($O85=$CR$61,$R85,0) -> 0 | CT85: =IF($O85=$CT$61,$P85,0) -> 0 | CU85: =IF($O85=$CT$61,$R85,0) -> 0 | CV85: =IF($O85=$CV$61,$P85,0) -> 0 | CW85: =IF($O85=$CV$61,$R85,0) -> 0 | CX85: =IF($O85=$CX$61,$P85,0) -> 0 | CY85: =IF($O85=$CX$61,$R85,0) -> 0
N86: =L86*M86 -> 0 | R86: =P86*Q86 -> 0 | S86: =N86+R86 -> 0 | V86: =IF($K86=$V$61,$L86,0) -> 0 | W86: =IF($K86=$V$61,$N86,0) -> 0 | X86: =IF($K86=$X$61,$L86,0) -> 0 | Y86: =IF($K86=$X$61,$N86,0) -> 0 | Z86: =IF($K86=$Z$61,$L86,0) -> 0 | AA86: =IF($K86=$Z$61,$N86,0) -> 0 | AB86: =IF($K86=$AB$61,$L86,0) -> 0 | AC86: =IF($K86=$AB$61,$N86,0) -> 0 | AD86: =IF($K86=$AD$61,$L86,0) -> 0 | AE86: =IF($K86=$AD$61,$N86,0) -> 0 | AF86: =IF($K86=$AF$61,$L86,0) -> 0 | AG86: =IF($K86=$AF$61,$N86,0) -> 0 | AH86: =IF($K86=$AH$61,$L86,0) -> 0 | AI86: =IF($K86=$AH$61,$N86,0) -> 0 | AJ86: =IF($K86=$AJ$61,$L86,0) -> 0 | AK86: =IF($K86=$AJ$61,$N86,0) -> 0 | AL86: =IF($K86=$AL$61,$L86,0) -> 0 | AM86: =IF($K86=$AL$61,$N86,0) -> 0 | AN86: =IF($K86=$AN$61,$L86,0) -> 0 | AO86: =IF($K86=$AN$61,$N86,0) -> 0 | AP86: =IF($K86=$AP$61,$L86,0) -> 0 | AQ86: =IF($K86=$AP$61,$N86,0) -> 0 | AR86: =IF($K86=$AR$61,$L86,0) -> 0 | AS86: =IF($K86=$AR$61,$N86,0) -> 0 | AT86: =IF($K86=$AT$61,$L86,0) -> 0 | AU86: =IF($K86=$AT$61,$N86,0) -> 0 | AV86: =IF($K86=$AV$61,$L86,0) -> 0 | AW86: =IF($K86=$AV$61,$N86,0) -> 0 | AX86: =IF($K86=$AX$61,$L86,0) -> 0 | AY86: =IF($K86=$AX$61,$N86,0) -> 0 | AZ86: =IF($K86=$AZ$61,$L86,0) -> 0 | BA86: =IF($K86=$AZ$61,$N86,0) -> 0 | BB86: =IF($K86=$BB$61,$L86,0) -> 0 | BC86: =IF($K86=$BB$61,$N86,0) -> 0 | BD86: =IF($O86=$BD$61,$P86,0) -> 0 | BE86: =IF($O86=$BD$61,$R86,0) -> 0 | BF86: =IF($O86=$BF$61,$P86,0) -> 0 | BG86: =IF($O86=$BF$61,$R86,0) -> 0 | BH86: =IF($O86=$BH$61,$P86,0) -> 0 | BI86: =IF($O86=$BH$61,$R86,0) -> 0 | BJ86: =IF($O86=$BJ$61,$P86,0) -> 0 | BK86: =IF($O86=$BJ$61,$R86,0) -> 0 | BL86: =IF($O86=$BL$61,$P86,0) -> 0 | BM86: =IF($O86=$BL$61,$R86,0) -> 0 | BN86: =IF($O86=$BN$61,$P86,0) -> 0 | BO86: =IF($O86=$BN$61,$R86,0) -> 0 | BP86: =IF($O86=$BP$61,$P86,0) -> 0 | BQ86: =IF($O86=$BP$61,$R86,0) -> 0 | BR86: =IF($O86=$BR$61,$P86,0) -> 0 | BS86: =IF($O86=$BR$61,$R86,0) -> 0 | BT86: =IF($O86=$BT$61,$P86,0) -> 0 | BU86: =IF($O86=$BT$61,$R86,0) -> 0 | BV86: =IF($O86=$BV$61,$P86,0) -> 0 | BW86: =IF($O86=$BV$61,$R86,0) -> 0 | BX86: =IF($O86=$BX$61,$P86,0) -> 0 | BY86: =IF($O86=$BX$61,$R86,0) -> 0 | BZ86: =IF($O86=$BZ$61,$P86,0) -> 0 | CA86: =IF($O86=$BZ$61,$R86,0) -> 0 | CB86: =IF($O86=$CB$61,$P86,0) -> 0 | CC86: =IF($O86=$CB$61,$R86,0) -> 0 | CD86: =IF($O86=$CD$61,$P86,0) -> 0 | CE86: =IF($O86=$CD$61,$R86,0) -> 0 | CF86: =IF($O86=$CF$61,$P86,0) -> 0 | CG86: =IF($O86=$CF$61,$R86,0) -> 0 | CH86: =IF($O86=$CH$61,$P86,0) -> 0 | CI86: =IF($O86=$CH$61,$R86,0) -> 0 | CJ86: =IF($O86=$CJ$61,$P86,0) -> 0 | CK86: =IF($O86=$CJ$61,$R86,0) -> 0 | CL86: =IF($O86=$CL$61,$P86,0) -> 0 | CM86: =IF($O86=$CL$61,$R86,0) -> 0 | CN86: =IF($O86=$CN$61,$P86,0) -> 0 | CO86: =IF($O86=$CN$61,$R86,0) -> 0 | CP86: =IF($O86=$CP$61,$P86,0) -> 0 | CQ86: =IF($O86=$CP$61,$R86,0) -> 0 | CR86: =IF($O86=$CR$61,$P86,0) -> 0 | CS86: =IF($O86=$CR$61,$R86,0) -> 0 | CT86: =IF($O86=$CT$61,$P86,0) -> 0 | CU86: =IF($O86=$CT$61,$R86,0) -> 0 | CV86: =IF($O86=$CV$61,$P86,0) -> 0 | CW86: =IF($O86=$CV$61,$R86,0) -> 0 | CX86: =IF($O86=$CX$61,$P86,0) -> 0 | CY86: =IF($O86=$CX$61,$R86,0) -> 0
A87: 名 称 | E87: 数量 | F87: 呼称 | G87: 単 価 | H87: 金 額 | I87: 定価 | J87: 備 考 | K87: 職人 | L87: 人工 | M87: 人当 | N87: 費用① | O87: 材料 | P87: 数量 | Q87: 単価 | R87: 費用② | S87: 原価 | T87: 粗利率 | V87: =IF($K87=$V$61,$L87,0) -> 0 | W87: =IF($K87=$V$61,$N87,0) -> 0 | X87: =IF($K87=$X$61,$L87,0) -> 0 | Y87: =IF($K87=$X$61,$N87,0) -> 0 | Z87: =IF($K87=$Z$61,$L87,0) -> 0 | AA87: =IF($K87=$Z$61,$N87,0) -> 0 | AB87: =IF($K87=$AB$61,$L87,0) -> 0 | AC87: =IF($K87=$AB$61,$N87,0) -> 0 | AD87: =IF($K87=$AD$61,$L87,0) -> 0 | AE87: =IF($K87=$AD$61,$N87,0) -> 0 | AF87: =IF($K87=$AF$61,$L87,0) -> 0 | AG87: =IF($K87=$AF$61,$N87,0) -> 0 | AH87: =IF($K87=$AH$61,$L87,0) -> 0 | AI87: =IF($K87=$AH$61,$N87,0) -> 0 | AJ87: =IF($K87=$AJ$61,$L87,0) -> 0 | AK87: =IF($K87=$AJ$61,$N87,0) -> 0 | AL87: =IF($K87=$AL$61,$L87,0) -> 0 | AM87: =IF($K87=$AL$61,$N87,0) -> 0 | AN87: =IF($K87=$AN$61,$L87,0) -> 0 | AO87: =IF($K87=$AN$61,$N87,0) -> 0 | AP87: =IF($K87=$AP$61,$L87,0) -> 0 | AQ87: =IF($K87=$AP$61,$N87,0) -> 0 | AR87: =IF($K87=$AR$61,$L87,0) -> 0 | AS87: =IF($K87=$AR$61,$N87,0) -> 0 | AT87: =IF($K87=$AT$61,$L87,0) -> 0 | AU87: =IF($K87=$AT$61,$N87,0) -> 0 | AV87: =IF($K87=$AV$61,$L87,0) -> 0 | AW87: =IF($K87=$AV$61,$N87,0) -> 0 | AX87: =IF($K87=$AX$61,$L87,0) -> 0 | AY87: =IF($K87=$AX$61,$N87,0) -> 0 | AZ87: =IF($K87=$AZ$61,$L87,0) -> 0 | BA87: =IF($K87=$AZ$61,$N87,0) -> 0 | BB87: =IF($K87=$BB$61,$L87,0) -> 0 | BC87: =IF($K87=$BB$61,$N87,0) -> 0 | BD87: =IF($O87=$BD$61,$P87,0) -> 0 | BE87: =IF($O87=$BD$61,$R87,0) -> 0 | BF87: =IF($O87=$BF$61,$P87,0) -> 0 | BG87: =IF($O87=$BF$61,$R87,0) -> 0 | BH87: =IF($O87=$BH$61,$P87,0) -> 0 | BI87: =IF($O87=$BH$61,$R87,0) -> 0 | BJ87: =IF($O87=$BJ$61,$P87,0) -> 0 | BK87: =IF($O87=$BJ$61,$R87,0) -> 0 | BL87: =IF($O87=$BL$61,$P87,0) -> 0 | BM87: =IF($O87=$BL$61,$R87,0) -> 0 | BN87: =IF($O87=$BN$61,$P87,0) -> 0 | BO87: =IF($O87=$BN$61,$R87,0) -> 0 | BP87: =IF($O87=$BP$61,$P87,0) -> 0 | BQ87: =IF($O87=$BP$61,$R87,0) -> 0 | BR87: =IF($O87=$BR$61,$P87,0) -> 0 | BS87: =IF($O87=$BR$61,$R87,0) -> 0 | BT87: =IF($O87=$BT$61,$P87,0) -> 0 | BU87: =IF($O87=$BT$61,$R87,0) -> 0 | BV87: =IF($O87=$BV$61,$P87,0) -> 0 | BW87: =IF($O87=$BV$61,$R87,0) -> 0 | BX87: =IF($O87=$BX$61,$P87,0) -> 0 | BY87: =IF($O87=$BX$61,$R87,0) -> 0 | BZ87: =IF($O87=$BZ$61,$P87,0) -> 0 | CA87: =IF($O87=$BZ$61,$R87,0) -> 0 | CB87: =IF($O87=$CB$61,$P87,0) -> 0 | CC87: =IF($O87=$CB$61,$R87,0) -> 0 | CD87: =IF($O87=$CD$61,$P87,0) -> 0 | CE87: =IF($O87=$CD$61,$R87,0) -> 0 | CF87: =IF($O87=$CF$61,$P87,0) -> 0 | CG87: =IF($O87=$CF$61,$R87,0) -> 0 | CH87: =IF($O87=$CH$61,$P87,0) -> 0 | CI87: =IF($O87=$CH$61,$R87,0) -> 0 | CJ87: =IF($O87=$CJ$61,$P87,0) -> 0 | CK87: =IF($O87=$CJ$61,$R87,0) -> 0 | CL87: =IF($O87=$CL$61,$P87,0) -> 0 | CM87: =IF($O87=$CL$61,$R87,0) -> 0 | CN87: =IF($O87=$CN$61,$P87,0) -> 0 | CO87: =IF($O87=$CN$61,$R87,0) -> 0 | CP87: =IF($O87=$CP$61,$P87,0) -> 0 | CQ87: =IF($O87=$CP$61,$R87,0) -> 0 | CR87: =IF($O87=$CR$61,$P87,0) -> 0 | CS87: =IF($O87=$CR$61,$R87,0) -> 0 | CT87: =IF($O87=$CT$61,$P87,0) -> 0 | CU87: =IF($O87=$CT$61,$R87,0) -> 0 | CV87: =IF($O87=$CV$61,$P87,0) -> 0 | CW87: =IF($O87=$CV$61,$R87,0) -> 0 | CX87: =IF($O87=$CX$61,$P87,0) -> 0 | CY87: =IF($O87=$CX$61,$R87,0) -> 0
A88: 2 | B88: =B38 -> 0 | H88: =S88*1.45 -> 0 | N88: =L88*M88 -> 0 | R88: =Q88*P88 -> 0 | S88: =R88+N88 -> 0 | T88: =IF(H88<>0,1-(S88/H88),0) -> 0 | V88: =IF($K88=$V$61,$L88,0) -> 0 | W88: =IF($K88=$V$61,$N88,0) -> 0 | X88: =IF($K88=$X$61,$L88,0) -> 0 | Y88: =IF($K88=$X$61,$N88,0) -> 0 | Z88: =IF($K88=$Z$61,$L88,0) -> 0 | AA88: =IF($K88=$Z$61,$N88,0) -> 0 | AB88: =IF($K88=$AB$61,$L88,0) -> 0 | AC88: =IF($K88=$AB$61,$N88,0) -> 0 | AD88: =IF($K88=$AD$61,$L88,0) -> 0 | AE88: =IF($K88=$AD$61,$N88,0) -> 0 | AF88: =IF($K88=$AF$61,$L88,0) -> 0 | AG88: =IF($K88=$AF$61,$N88,0) -> 0 | AH88: =IF($K88=$AH$61,$L88,0) -> 0 | AI88: =IF($K88=$AH$61,$N88,0) -> 0 | AJ88: =IF($K88=$AJ$61,$L88,0) -> 0 | AK88: =IF($K88=$AJ$61,$N88,0) -> 0 | AL88: =IF($K88=$AL$61,$L88,0) -> 0 | AM88: =IF($K88=$AL$61,$N88,0) -> 0 | AN88: =IF($K88=$AN$61,$L88,0) -> 0 | AO88: =IF($K88=$AN$61,$N88,0) -> 0 | AP88: =IF($K88=$AP$61,$L88,0) -> 0 | AQ88: =IF($K88=$AP$61,$N88,0) -> 0 | AR88: =IF($K88=$AR$61,$L88,0) -> 0 | AS88: =IF($K88=$AR$61,$N88,0) -> 0 | AT88: =IF($K88=$AT$61,$L88,0) -> 0 | AU88: =IF($K88=$AT$61,$N88,0) -> 0 | AV88: =IF($K88=$AV$61,$L88,0) -> 0 | AW88: =IF($K88=$AV$61,$N88,0) -> 0 | AX88: =IF($K88=$AX$61,$L88,0) -> 0 | AY88: =IF($K88=$AX$61,$N88,0) -> 0 | AZ88: =IF($K88=$AZ$61,$L88,0) -> 0 | BA88: =IF($K88=$AZ$61,$N88,0) -> 0 | BB88: =IF($K88=$BB$61,$L88,0) -> 0 | BC88: =IF($K88=$BB$61,$N88,0) -> 0 | BD88: =IF($O88=$BD$61,$P88,0) -> 0 | BE88: =IF($O88=$BD$61,$R88,0) -> 0 | BF88: =IF($O88=$BF$61,$P88,0) -> 0 | BG88: =IF($O88=$BF$61,$R88,0) -> 0 | BH88: =IF($O88=$BH$61,$P88,0) -> 0 | BI88: =IF($O88=$BH$61,$R88,0) -> 0 | BJ88: =IF($O88=$BJ$61,$P88,0) -> 0 | BK88: =IF($O88=$BJ$61,$R88,0) -> 0 | BL88: =IF($O88=$BL$61,$P88,0) -> 0 | BM88: =IF($O88=$BL$61,$R88,0) -> 0 | BN88: =IF($O88=$BN$61,$P88,0) -> 0 | BO88: =IF($O88=$BN$61,$R88,0) -> 0 | BP88: =IF($O88=$BP$61,$P88,0) -> 0 | BQ88: =IF($O88=$BP$61,$R88,0) -> 0 | BR88: =IF($O88=$BR$61,$P88,0) -> 0 | BS88: =IF($O88=$BR$61,$R88,0) -> 0 | BT88: =IF($O88=$BT$61,$P88,0) -> 0 | BU88: =IF($O88=$BT$61,$R88,0) -> 0 | BV88: =IF($O88=$BV$61,$P88,0) -> 0 | BW88: =IF($O88=$BV$61,$R88,0) -> 0 | BX88: =IF($O88=$BX$61,$P88,0) -> 0 | BY88: =IF($O88=$BX$61,$R88,0) -> 0 | BZ88: =IF($O88=$BZ$61,$P88,0) -> 0 | CA88: =IF($O88=$BZ$61,$R88,0) -> 0 | CB88: =IF($O88=$CB$61,$P88,0) -> 0 | CC88: =IF($O88=$CB$61,$R88,0) -> 0 | CD88: =IF($O88=$CD$61,$P88,0) -> 0 | CE88: =IF($O88=$CD$61,$R88,0) -> 0 | CF88: =IF($O88=$CF$61,$P88,0) -> 0 | CG88: =IF($O88=$CF$61,$R88,0) -> 0 | CH88: =IF($O88=$CH$61,$P88,0) -> 0 | CI88: =IF($O88=$CH$61,$R88,0) -> 0 | CJ88: =IF($O88=$CJ$61,$P88,0) -> 0 | CK88: =IF($O88=$CJ$61,$R88,0) -> 0 | CL88: =IF($O88=$CL$61,$P88,0) -> 0 | CM88: =IF($O88=$CL$61,$R88,0) -> 0 | CN88: =IF($O88=$CN$61,$P88,0) -> 0 | CO88: =IF($O88=$CN$61,$R88,0) -> 0 | CP88: =IF($O88=$CP$61,$P88,0) -> 0 | CQ88: =IF($O88=$CP$61,$R88,0) -> 0 | CR88: =IF($O88=$CR$61,$P88,0) -> 0 | CS88: =IF($O88=$CR$61,$R88,0) -> 0 | CT88: =IF($O88=$CT$61,$P88,0) -> 0 | CU88: =IF($O88=$CT$61,$R88,0) -> 0 | CV88: =IF($O88=$CV$61,$P88,0) -> 0 | CW88: =IF($O88=$CV$61,$R88,0) -> 0 | CX88: =IF($O88=$CX$61,$P88,0) -> 0 | CY88: =IF($O88=$CX$61,$R88,0) -> 0
H89: =S89*1.45 -> 0 | N89: =L89*M89 -> 0 | R89: =Q89*P89 -> 0 | S89: =R89+N89 -> 0 | T89: =IF(H89<>0,1-(S89/H89),0) -> 0 | V89: =IF($K89=$V$61,$L89,0) -> 0 | W89: =IF($K89=$V$61,$N89,0) -> 0 | X89: =IF($K89=$X$61,$L89,0) -> 0 | Y89: =IF($K89=$X$61,$N89,0) -> 0 | Z89: =IF($K89=$Z$61,$L89,0) -> 0 | AA89: =IF($K89=$Z$61,$N89,0) -> 0 | AB89: =IF($K89=$AB$61,$L89,0) -> 0 | AC89: =IF($K89=$AB$61,$N89,0) -> 0 | AD89: =IF($K89=$AD$61,$L89,0) -> 0 | AE89: =IF($K89=$AD$61,$N89,0) -> 0 | AF89: =IF($K89=$AF$61,$L89,0) -> 0 | AG89: =IF($K89=$AF$61,$N89,0) -> 0 | AH89: =IF($K89=$AH$61,$L89,0) -> 0 | AI89: =IF($K89=$AH$61,$N89,0) -> 0 | AJ89: =IF($K89=$AJ$61,$L89,0) -> 0 | AK89: =IF($K89=$AJ$61,$N89,0) -> 0 | AL89: =IF($K89=$AL$61,$L89,0) -> 0 | AM89: =IF($K89=$AL$61,$N89,0) -> 0 | AN89: =IF($K89=$AN$61,$L89,0) -> 0 | AO89: =IF($K89=$AN$61,$N89,0) -> 0 | AP89: =IF($K89=$AP$61,$L89,0) -> 0 | AQ89: =IF($K89=$AP$61,$N89,0) -> 0 | AR89: =IF($K89=$AR$61,$L89,0) -> 0 | AS89: =IF($K89=$AR$61,$N89,0) -> 0 | AT89: =IF($K89=$AT$61,$L89,0) -> 0 | AU89: =IF($K89=$AT$61,$N89,0) -> 0 | AV89: =IF($K89=$AV$61,$L89,0) -> 0 | AW89: =IF($K89=$AV$61,$N89,0) -> 0 | AX89: =IF($K89=$AX$61,$L89,0) -> 0 | AY89: =IF($K89=$AX$61,$N89,0) -> 0 | AZ89: =IF($K89=$AZ$61,$L89,0) -> 0 | BA89: =IF($K89=$AZ$61,$N89,0) -> 0 | BB89: =IF($K89=$BB$61,$L89,0) -> 0 | BC89: =IF($K89=$BB$61,$N89,0) -> 0 | BD89: =IF($O89=$BD$61,$P89,0) -> 0 | BE89: =IF($O89=$BD$61,$R89,0) -> 0 | BF89: =IF($O89=$BF$61,$P89,0) -> 0 | BG89: =IF($O89=$BF$61,$R89,0) -> 0 | BH89: =IF($O89=$BH$61,$P89,0) -> 0 | BI89: =IF($O89=$BH$61,$R89,0) -> 0 | BJ89: =IF($O89=$BJ$61,$P89,0) -> 0 | BK89: =IF($O89=$BJ$61,$R89,0) -> 0 | BL89: =IF($O89=$BL$61,$P89,0) -> 0 | BM89: =IF($O89=$BL$61,$R89,0) -> 0 | BN89: =IF($O89=$BN$61,$P89,0) -> 0 | BO89: =IF($O89=$BN$61,$R89,0) -> 0 | BP89: =IF($O89=$BP$61,$P89,0) -> 0 | BQ89: =IF($O89=$BP$61,$R89,0) -> 0 | BR89: =IF($O89=$BR$61,$P89,0) -> 0 | BS89: =IF($O89=$BR$61,$R89,0) -> 0 | BT89: =IF($O89=$BT$61,$P89,0) -> 0 | BU89: =IF($O89=$BT$61,$R89,0) -> 0 | BV89: =IF($O89=$BV$61,$P89,0) -> 0 | BW89: =IF($O89=$BV$61,$R89,0) -> 0 | BX89: =IF($O89=$BX$61,$P89,0) -> 0 | BY89: =IF($O89=$BX$61,$R89,0) -> 0 | BZ89: =IF($O89=$BZ$61,$P89,0) -> 0 | CA89: =IF($O89=$BZ$61,$R89,0) -> 0 | CB89: =IF($O89=$CB$61,$P89,0) -> 0 | CC89: =IF($O89=$CB$61,$R89,0) -> 0 | CD89: =IF($O89=$CD$61,$P89,0) -> 0 | CE89: =IF($O89=$CD$61,$R89,0) -> 0 | CF89: =IF($O89=$CF$61,$P89,0) -> 0 | CG89: =IF($O89=$CF$61,$R89,0) -> 0 | CH89: =IF($O89=$CH$61,$P89,0) -> 0 | CI89: =IF($O89=$CH$61,$R89,0) -> 0 | CJ89: =IF($O89=$CJ$61,$P89,0) -> 0 | CK89: =IF($O89=$CJ$61,$R89,0) -> 0 | CL89: =IF($O89=$CL$61,$P89,0) -> 0 | CM89: =IF($O89=$CL$61,$R89,0) -> 0 | CN89: =IF($O89=$CN$61,$P89,0) -> 0 | CO89: =IF($O89=$CN$61,$R89,0) -> 0 | CP89: =IF($O89=$CP$61,$P89,0) -> 0 | CQ89: =IF($O89=$CP$61,$R89,0) -> 0 | CR89: =IF($O89=$CR$61,$P89,0) -> 0 | CS89: =IF($O89=$CR$61,$R89,0) -> 0 | CT89: =IF($O89=$CT$61,$P89,0) -> 0 | CU89: =IF($O89=$CT$61,$R89,0) -> 0 | CV89: =IF($O89=$CV$61,$P89,0) -> 0 | CW89: =IF($O89=$CV$61,$R89,0) -> 0 | CX89: =IF($O89=$CX$61,$P89,0) -> 0 | CY89: =IF($O89=$CX$61,$R89,0) -> 0
H90: =S90*1.45 -> 0 | N90: =L90*M90 -> 0 | R90: =Q90*P90 -> 0 | S90: =R90+N90 -> 0 | T90: =IF(H90<>0,1-(S90/H90),0) -> 0 | V90: =IF($K90=$V$61,$L90,0) -> 0 | W90: =IF($K90=$V$61,$N90,0) -> 0 | X90: =IF($K90=$X$61,$L90,0) -> 0 | Y90: =IF($K90=$X$61,$N90,0) -> 0 | Z90: =IF($K90=$Z$61,$L90,0) -> 0 | AA90: =IF($K90=$Z$61,$N90,0) -> 0 | AB90: =IF($K90=$AB$61,$L90,0) -> 0 | AC90: =IF($K90=$AB$61,$N90,0) -> 0 | AD90: =IF($K90=$AD$61,$L90,0) -> 0 | AE90: =IF($K90=$AD$61,$N90,0) -> 0 | AF90: =IF($K90=$AF$61,$L90,0) -> 0 | AG90: =IF($K90=$AF$61,$N90,0) -> 0 | AH90: =IF($K90=$AH$61,$L90,0) -> 0 | AI90: =IF($K90=$AH$61,$N90,0) -> 0 | AJ90: =IF($K90=$AJ$61,$L90,0) -> 0 | AK90: =IF($K90=$AJ$61,$N90,0) -> 0 | AL90: =IF($K90=$AL$61,$L90,0) -> 0 | AM90: =IF($K90=$AL$61,$N90,0) -> 0 | AN90: =IF($K90=$AN$61,$L90,0) -> 0 | AO90: =IF($K90=$AN$61,$N90,0) -> 0 | AP90: =IF($K90=$AP$61,$L90,0) -> 0 | AQ90: =IF($K90=$AP$61,$N90,0) -> 0 | AR90: =IF($K90=$AR$61,$L90,0) -> 0 | AS90: =IF($K90=$AR$61,$N90,0) -> 0 | AT90: =IF($K90=$AT$61,$L90,0) -> 0 | AU90: =IF($K90=$AT$61,$N90,0) -> 0 | AV90: =IF($K90=$AV$61,$L90,0) -> 0 | AW90: =IF($K90=$AV$61,$N90,0) -> 0 | AX90: =IF($K90=$AX$61,$L90,0) -> 0 | AY90: =IF($K90=$AX$61,$N90,0) -> 0 | AZ90: =IF($K90=$AZ$61,$L90,0) -> 0 | BA90: =IF($K90=$AZ$61,$N90,0) -> 0 | BB90: =IF($K90=$BB$61,$L90,0) -> 0 | BC90: =IF($K90=$BB$61,$N90,0) -> 0 | BD90: =IF($O90=$BD$61,$P90,0) -> 0 | BE90: =IF($O90=$BD$61,$R90,0) -> 0 | BF90: =IF($O90=$BF$61,$P90,0) -> 0 | BG90: =IF($O90=$BF$61,$R90,0) -> 0 | BH90: =IF($O90=$BH$61,$P90,0) -> 0 | BI90: =IF($O90=$BH$61,$R90,0) -> 0 | BJ90: =IF($O90=$BJ$61,$P90,0) -> 0 | BK90: =IF($O90=$BJ$61,$R90,0) -> 0 | BL90: =IF($O90=$BL$61,$P90,0) -> 0 | BM90: =IF($O90=$BL$61,$R90,0) -> 0 | BN90: =IF($O90=$BN$61,$P90,0) -> 0 | BO90: =IF($O90=$BN$61,$R90,0) -> 0 | BP90: =IF($O90=$BP$61,$P90,0) -> 0 | BQ90: =IF($O90=$BP$61,$R90,0) -> 0 | BR90: =IF($O90=$BR$61,$P90,0) -> 0 | BS90: =IF($O90=$BR$61,$R90,0) -> 0 | BT90: =IF($O90=$BT$61,$P90,0) -> 0 | BU90: =IF($O90=$BT$61,$R90,0) -> 0 | BV90: =IF($O90=$BV$61,$P90,0) -> 0 | BW90: =IF($O90=$BV$61,$R90,0) -> 0 | BX90: =IF($O90=$BX$61,$P90,0) -> 0 | BY90: =IF($O90=$BX$61,$R90,0) -> 0 | BZ90: =IF($O90=$BZ$61,$P90,0) -> 0 | CA90: =IF($O90=$BZ$61,$R90,0) -> 0 | CB90: =IF($O90=$CB$61,$P90,0) -> 0 | CC90: =IF($O90=$CB$61,$R90,0) -> 0 | CD90: =IF($O90=$CD$61,$P90,0) -> 0 | CE90: =IF($O90=$CD$61,$R90,0) -> 0 | CF90: =IF($O90=$CF$61,$P90,0) -> 0 | CG90: =IF($O90=$CF$61,$R90,0) -> 0 | CH90: =IF($O90=$CH$61,$P90,0) -> 0 | CI90: =IF($O90=$CH$61,$R90,0) -> 0 | CJ90: =IF($O90=$CJ$61,$P90,0) -> 0 | CK90: =IF($O90=$CJ$61,$R90,0) -> 0 | CL90: =IF($O90=$CL$61,$P90,0) -> 0 | CM90: =IF($O90=$CL$61,$R90,0) -> 0 | CN90: =IF($O90=$CN$61,$P90,0) -> 0 | CO90: =IF($O90=$CN$61,$R90,0) -> 0 | CP90: =IF($O90=$CP$61,$P90,0) -> 0 | CQ90: =IF($O90=$CP$61,$R90,0) -> 0 | CR90: =IF($O90=$CR$61,$P90,0) -> 0 | CS90: =IF($O90=$CR$61,$R90,0) -> 0 | CT90: =IF($O90=$CT$61,$P90,0) -> 0 | CU90: =IF($O90=$CT$61,$R90,0) -> 0 | CV90: =IF($O90=$CV$61,$P90,0) -> 0 | CW90: =IF($O90=$CV$61,$R90,0) -> 0 | CX90: =IF($O90=$CX$61,$P90,0) -> 0 | CY90: =IF($O90=$CX$61,$R90,0) -> 0
H91: =S91*1.45 -> 0 | N91: =L91*M91 -> 0 | R91: =Q91*P91 -> 0 | S91: =R91+N91 -> 0 | T91: =IF(H91<>0,1-(S91/H91),0) -> 0 | V91: =IF($K91=$V$61,$L91,0) -> 0 | W91: =IF($K91=$V$61,$N91,0) -> 0 | X91: =IF($K91=$X$61,$L91,0) -> 0 | Y91: =IF($K91=$X$61,$N91,0) -> 0 | Z91: =IF($K91=$Z$61,$L91,0) -> 0 | AA91: =IF($K91=$Z$61,$N91,0) -> 0 | AB91: =IF($K91=$AB$61,$L91,0) -> 0 | AC91: =IF($K91=$AB$61,$N91,0) -> 0 | AD91: =IF($K91=$AD$61,$L91,0) -> 0 | AE91: =IF($K91=$AD$61,$N91,0) -> 0 | AF91: =IF($K91=$AF$61,$L91,0) -> 0 | AG91: =IF($K91=$AF$61,$N91,0) -> 0 | AH91: =IF($K91=$AH$61,$L91,0) -> 0 | AI91: =IF($K91=$AH$61,$N91,0) -> 0 | AJ91: =IF($K91=$AJ$61,$L91,0) -> 0 | AK91: =IF($K91=$AJ$61,$N91,0) -> 0 | AL91: =IF($K91=$AL$61,$L91,0) -> 0 | AM91: =IF($K91=$AL$61,$N91,0) -> 0 | AN91: =IF($K91=$AN$61,$L91,0) -> 0 | AO91: =IF($K91=$AN$61,$N91,0) -> 0 | AP91: =IF($K91=$AP$61,$L91,0) -> 0 | AQ91: =IF($K91=$AP$61,$N91,0) -> 0 | AR91: =IF($K91=$AR$61,$L91,0) -> 0 | AS91: =IF($K91=$AR$61,$N91,0) -> 0 | AT91: =IF($K91=$AT$61,$L91,0) -> 0 | AU91: =IF($K91=$AT$61,$N91,0) -> 0 | AV91: =IF($K91=$AV$61,$L91,0) -> 0 | AW91: =IF($K91=$AV$61,$N91,0) -> 0 | AX91: =IF($K91=$AX$61,$L91,0) -> 0 | AY91: =IF($K91=$AX$61,$N91,0) -> 0 | AZ91: =IF($K91=$AZ$61,$L91,0) -> 0 | BA91: =IF($K91=$AZ$61,$N91,0) -> 0 | BB91: =IF($K91=$BB$61,$L91,0) -> 0 | BC91: =IF($K91=$BB$61,$N91,0) -> 0 | BD91: =IF($O91=$BD$61,$P91,0) -> 0 | BE91: =IF($O91=$BD$61,$R91,0) -> 0 | BF91: =IF($O91=$BF$61,$P91,0) -> 0 | BG91: =IF($O91=$BF$61,$R91,0) -> 0 | BH91: =IF($O91=$BH$61,$P91,0) -> 0 | BI91: =IF($O91=$BH$61,$R91,0) -> 0 | BJ91: =IF($O91=$BJ$61,$P91,0) -> 0 | BK91: =IF($O91=$BJ$61,$R91,0) -> 0 | BL91: =IF($O91=$BL$61,$P91,0) -> 0 | BM91: =IF($O91=$BL$61,$R91,0) -> 0 | BN91: =IF($O91=$BN$61,$P91,0) -> 0 | BO91: =IF($O91=$BN$61,$R91,0) -> 0 | BP91: =IF($O91=$BP$61,$P91,0) -> 0 | BQ91: =IF($O91=$BP$61,$R91,0) -> 0 | BR91: =IF($O91=$BR$61,$P91,0) -> 0 | BS91: =IF($O91=$BR$61,$R91,0) -> 0 | BT91: =IF($O91=$BT$61,$P91,0) -> 0 | BU91: =IF($O91=$BT$61,$R91,0) -> 0 | BV91: =IF($O91=$BV$61,$P91,0) -> 0 | BW91: =IF($O91=$BV$61,$R91,0) -> 0 | BX91: =IF($O91=$BX$61,$P91,0) -> 0 | BY91: =IF($O91=$BX$61,$R91,0) -> 0 | BZ91: =IF($O91=$BZ$61,$P91,0) -> 0 | CA91: =IF($O91=$BZ$61,$R91,0) -> 0 | CB91: =IF($O91=$CB$61,$P91,0) -> 0 | CC91: =IF($O91=$CB$61,$R91,0) -> 0 | CD91: =IF($O91=$CD$61,$P91,0) -> 0 | CE91: =IF($O91=$CD$61,$R91,0) -> 0 | CF91: =IF($O91=$CF$61,$P91,0) -> 0 | CG91: =IF($O91=$CF$61,$R91,0) -> 0 | CH91: =IF($O91=$CH$61,$P91,0) -> 0 | CI91: =IF($O91=$CH$61,$R91,0) -> 0 | CJ91: =IF($O91=$CJ$61,$P91,0) -> 0 | CK91: =IF($O91=$CJ$61,$R91,0) -> 0 | CL91: =IF($O91=$CL$61,$P91,0) -> 0 | CM91: =IF($O91=$CL$61,$R91,0) -> 0 | CN91: =IF($O91=$CN$61,$P91,0) -> 0 | CO91: =IF($O91=$CN$61,$R91,0) -> 0 | CP91: =IF($O91=$CP$61,$P91,0) -> 0 | CQ91: =IF($O91=$CP$61,$R91,0) -> 0 | CR91: =IF($O91=$CR$61,$P91,0) -> 0 | CS91: =IF($O91=$CR$61,$R91,0) -> 0 | CT91: =IF($O91=$CT$61,$P91,0) -> 0 | CU91: =IF($O91=$CT$61,$R91,0) -> 0 | CV91: =IF($O91=$CV$61,$P91,0) -> 0 | CW91: =IF($O91=$CV$61,$R91,0) -> 0 | CX91: =IF($O91=$CX$61,$P91,0) -> 0 | CY91: =IF($O91=$CX$61,$R91,0) -> 0
H92: =S92*1.45 -> 0 | N92: =L92*M92 -> 0 | R92: =Q92*P92 -> 0 | S92: =R92+N92 -> 0 | T92: =IF(H92<>0,1-(S92/H92),0) -> 0 | V92: =IF($K92=$V$61,$L92,0) -> 0 | W92: =IF($K92=$V$61,$N92,0) -> 0 | X92: =IF($K92=$X$61,$L92,0) -> 0 | Y92: =IF($K92=$X$61,$N92,0) -> 0 | Z92: =IF($K92=$Z$61,$L92,0) -> 0 | AA92: =IF($K92=$Z$61,$N92,0) -> 0 | AB92: =IF($K92=$AB$61,$L92,0) -> 0 | AC92: =IF($K92=$AB$61,$N92,0) -> 0 | AD92: =IF($K92=$AD$61,$L92,0) -> 0 | AE92: =IF($K92=$AD$61,$N92,0) -> 0 | AF92: =IF($K92=$AF$61,$L92,0) -> 0 | AG92: =IF($K92=$AF$61,$N92,0) -> 0 | AH92: =IF($K92=$AH$61,$L92,0) -> 0 | AI92: =IF($K92=$AH$61,$N92,0) -> 0 | AJ92: =IF($K92=$AJ$61,$L92,0) -> 0 | AK92: =IF($K92=$AJ$61,$N92,0) -> 0 | AL92: =IF($K92=$AL$61,$L92,0) -> 0 | AM92: =IF($K92=$AL$61,$N92,0) -> 0 | AN92: =IF($K92=$AN$61,$L92,0) -> 0 | AO92: =IF($K92=$AN$61,$N92,0) -> 0 | AP92: =IF($K92=$AP$61,$L92,0) -> 0 | AQ92: =IF($K92=$AP$61,$N92,0) -> 0 | AR92: =IF($K92=$AR$61,$L92,0) -> 0 | AS92: =IF($K92=$AR$61,$N92,0) -> 0 | AT92: =IF($K92=$AT$61,$L92,0) -> 0 | AU92: =IF($K92=$AT$61,$N92,0) -> 0 | AV92: =IF($K92=$AV$61,$L92,0) -> 0 | AW92: =IF($K92=$AV$61,$N92,0) -> 0 | AX92: =IF($K92=$AX$61,$L92,0) -> 0 | AY92: =IF($K92=$AX$61,$N92,0) -> 0 | AZ92: =IF($K92=$AZ$61,$L92,0) -> 0 | BA92: =IF($K92=$AZ$61,$N92,0) -> 0 | BB92: =IF($K92=$BB$61,$L92,0) -> 0 | BC92: =IF($K92=$BB$61,$N92,0) -> 0 | BD92: =IF($O92=$BD$61,$P92,0) -> 0 | BE92: =IF($O92=$BD$61,$R92,0) -> 0 | BF92: =IF($O92=$BF$61,$P92,0) -> 0 | BG92: =IF($O92=$BF$61,$R92,0) -> 0 | BH92: =IF($O92=$BH$61,$P92,0) -> 0 | BI92: =IF($O92=$BH$61,$R92,0) -> 0 | BJ92: =IF($O92=$BJ$61,$P92,0) -> 0 | BK92: =IF($O92=$BJ$61,$R92,0) -> 0 | BL92: =IF($O92=$BL$61,$P92,0) -> 0 | BM92: =IF($O92=$BL$61,$R92,0) -> 0 | BN92: =IF($O92=$BN$61,$P92,0) -> 0 | BO92: =IF($O92=$BN$61,$R92,0) -> 0 | BP92: =IF($O92=$BP$61,$P92,0) -> 0 | BQ92: =IF($O92=$BP$61,$R92,0) -> 0 | BR92: =IF($O92=$BR$61,$P92,0) -> 0 | BS92: =IF($O92=$BR$61,$R92,0) -> 0 | BT92: =IF($O92=$BT$61,$P92,0) -> 0 | BU92: =IF($O92=$BT$61,$R92,0) -> 0 | BV92: =IF($O92=$BV$61,$P92,0) -> 0 | BW92: =IF($O92=$BV$61,$R92,0) -> 0 | BX92: =IF($O92=$BX$61,$P92,0) -> 0 | BY92: =IF($O92=$BX$61,$R92,0) -> 0 | BZ92: =IF($O92=$BZ$61,$P92,0) -> 0 | CA92: =IF($O92=$BZ$61,$R92,0) -> 0 | CB92: =IF($O92=$CB$61,$P92,0) -> 0 | CC92: =IF($O92=$CB$61,$R92,0) -> 0 | CD92: =IF($O92=$CD$61,$P92,0) -> 0 | CE92: =IF($O92=$CD$61,$R92,0) -> 0 | CF92: =IF($O92=$CF$61,$P92,0) -> 0 | CG92: =IF($O92=$CF$61,$R92,0) -> 0 | CH92: =IF($O92=$CH$61,$P92,0) -> 0 | CI92: =IF($O92=$CH$61,$R92,0) -> 0 | CJ92: =IF($O92=$CJ$61,$P92,0) -> 0 | CK92: =IF($O92=$CJ$61,$R92,0) -> 0 | CL92: =IF($O92=$CL$61,$P92,0) -> 0 | CM92: =IF($O92=$CL$61,$R92,0) -> 0 | CN92: =IF($O92=$CN$61,$P92,0) -> 0 | CO92: =IF($O92=$CN$61,$R92,0) -> 0 | CP92: =IF($O92=$CP$61,$P92,0) -> 0 | CQ92: =IF($O92=$CP$61,$R92,0) -> 0 | CR92: =IF($O92=$CR$61,$P92,0) -> 0 | CS92: =IF($O92=$CR$61,$R92,0) -> 0 | CT92: =IF($O92=$CT$61,$P92,0) -> 0 | CU92: =IF($O92=$CT$61,$R92,0) -> 0 | CV92: =IF($O92=$CV$61,$P92,0) -> 0 | CW92: =IF($O92=$CV$61,$R92,0) -> 0 | CX92: =IF($O92=$CX$61,$P92,0) -> 0 | CY92: =IF($O92=$CX$61,$R92,0) -> 0
H93: =S93*1.45 -> 0 | N93: =L93*M93 -> 0 | R93: =Q93*P93 -> 0 | S93: =R93+N93 -> 0 | T93: =IF(H93<>0,1-(S93/H93),0) -> 0 | V93: =IF($K93=$V$61,$L93,0) -> 0 | W93: =IF($K93=$V$61,$N93,0) -> 0 | X93: =IF($K93=$X$61,$L93,0) -> 0 | Y93: =IF($K93=$X$61,$N93,0) -> 0 | Z93: =IF($K93=$Z$61,$L93,0) -> 0 | AA93: =IF($K93=$Z$61,$N93,0) -> 0 | AB93: =IF($K93=$AB$61,$L93,0) -> 0 | AC93: =IF($K93=$AB$61,$N93,0) -> 0 | AD93: =IF($K93=$AD$61,$L93,0) -> 0 | AE93: =IF($K93=$AD$61,$N93,0) -> 0 | AF93: =IF($K93=$AF$61,$L93,0) -> 0 | AG93: =IF($K93=$AF$61,$N93,0) -> 0 | AH93: =IF($K93=$AH$61,$L93,0) -> 0 | AI93: =IF($K93=$AH$61,$N93,0) -> 0 | AJ93: =IF($K93=$AJ$61,$L93,0) -> 0 | AK93: =IF($K93=$AJ$61,$N93,0) -> 0 | AL93: =IF($K93=$AL$61,$L93,0) -> 0 | AM93: =IF($K93=$AL$61,$N93,0) -> 0 | AN93: =IF($K93=$AN$61,$L93,0) -> 0 | AO93: =IF($K93=$AN$61,$N93,0) -> 0 | AP93: =IF($K93=$AP$61,$L93,0) -> 0 | AQ93: =IF($K93=$AP$61,$N93,0) -> 0 | AR93: =IF($K93=$AR$61,$L93,0) -> 0 | AS93: =IF($K93=$AR$61,$N93,0) -> 0 | AT93: =IF($K93=$AT$61,$L93,0) -> 0 | AU93: =IF($K93=$AT$61,$N93,0) -> 0 | AV93: =IF($K93=$AV$61,$L93,0) -> 0 | AW93: =IF($K93=$AV$61,$N93,0) -> 0 | AX93: =IF($K93=$AX$61,$L93,0) -> 0 | AY93: =IF($K93=$AX$61,$N93,0) -> 0 | AZ93: =IF($K93=$AZ$61,$L93,0) -> 0 | BA93: =IF($K93=$AZ$61,$N93,0) -> 0 | BB93: =IF($K93=$BB$61,$L93,0) -> 0 | BC93: =IF($K93=$BB$61,$N93,0) -> 0 | BD93: =IF($O93=$BD$61,$P93,0) -> 0 | BE93: =IF($O93=$BD$61,$R93,0) -> 0 | BF93: =IF($O93=$BF$61,$P93,0) -> 0 | BG93: =IF($O93=$BF$61,$R93,0) -> 0 | BH93: =IF($O93=$BH$61,$P93,0) -> 0 | BI93: =IF($O93=$BH$61,$R93,0) -> 0 | BJ93: =IF($O93=$BJ$61,$P93,0) -> 0 | BK93: =IF($O93=$BJ$61,$R93,0) -> 0 | BL93: =IF($O93=$BL$61,$P93,0) -> 0 | BM93: =IF($O93=$BL$61,$R93,0) -> 0 | BN93: =IF($O93=$BN$61,$P93,0) -> 0 | BO93: =IF($O93=$BN$61,$R93,0) -> 0 | BP93: =IF($O93=$BP$61,$P93,0) -> 0 | BQ93: =IF($O93=$BP$61,$R93,0) -> 0 | BR93: =IF($O93=$BR$61,$P93,0) -> 0 | BS93: =IF($O93=$BR$61,$R93,0) -> 0 | BT93: =IF($O93=$BT$61,$P93,0) -> 0 | BU93: =IF($O93=$BT$61,$R93,0) -> 0 | BV93: =IF($O93=$BV$61,$P93,0) -> 0 | BW93: =IF($O93=$BV$61,$R93,0) -> 0 | BX93: =IF($O93=$BX$61,$P93,0) -> 0 | BY93: =IF($O93=$BX$61,$R93,0) -> 0 | BZ93: =IF($O93=$BZ$61,$P93,0) -> 0 | CA93: =IF($O93=$BZ$61,$R93,0) -> 0 | CB93: =IF($O93=$CB$61,$P93,0) -> 0 | CC93: =IF($O93=$CB$61,$R93,0) -> 0 | CD93: =IF($O93=$CD$61,$P93,0) -> 0 | CE93: =IF($O93=$CD$61,$R93,0) -> 0 | CF93: =IF($O93=$CF$61,$P93,0) -> 0 | CG93: =IF($O93=$CF$61,$R93,0) -> 0 | CH93: =IF($O93=$CH$61,$P93,0) -> 0 | CI93: =IF($O93=$CH$61,$R93,0) -> 0 | CJ93: =IF($O93=$CJ$61,$P93,0) -> 0 | CK93: =IF($O93=$CJ$61,$R93,0) -> 0 | CL93: =IF($O93=$CL$61,$P93,0) -> 0 | CM93: =IF($O93=$CL$61,$R93,0) -> 0 | CN93: =IF($O93=$CN$61,$P93,0) -> 0 | CO93: =IF($O93=$CN$61,$R93,0) -> 0 | CP93: =IF($O93=$CP$61,$P93,0) -> 0 | CQ93: =IF($O93=$CP$61,$R93,0) -> 0 | CR93: =IF($O93=$CR$61,$P93,0) -> 0 | CS93: =IF($O93=$CR$61,$R93,0) -> 0 | CT93: =IF($O93=$CT$61,$P93,0) -> 0 | CU93: =IF($O93=$CT$61,$R93,0) -> 0 | CV93: =IF($O93=$CV$61,$P93,0) -> 0 | CW93: =IF($O93=$CV$61,$R93,0) -> 0 | CX93: =IF($O93=$CX$61,$P93,0) -> 0 | CY93: =IF($O93=$CX$61,$R93,0) -> 0
H94: =S94*1.45 -> 0 | N94: =L94*M94 -> 0 | R94: =Q94*P94 -> 0 | S94: =R94+N94 -> 0 | T94: =IF(H94<>0,1-(S94/H94),0) -> 0 | V94: =IF($K94=$V$61,$L94,0) -> 0 | W94: =IF($K94=$V$61,$N94,0) -> 0 | X94: =IF($K94=$X$61,$L94,0) -> 0 | Y94: =IF($K94=$X$61,$N94,0) -> 0 | Z94: =IF($K94=$Z$61,$L94,0) -> 0 | AA94: =IF($K94=$Z$61,$N94,0) -> 0 | AB94: =IF($K94=$AB$61,$L94,0) -> 0 | AC94: =IF($K94=$AB$61,$N94,0) -> 0 | AD94: =IF($K94=$AD$61,$L94,0) -> 0 | AE94: =IF($K94=$AD$61,$N94,0) -> 0 | AF94: =IF($K94=$AF$61,$L94,0) -> 0 | AG94: =IF($K94=$AF$61,$N94,0) -> 0 | AH94: =IF($K94=$AH$61,$L94,0) -> 0 | AI94: =IF($K94=$AH$61,$N94,0) -> 0 | AJ94: =IF($K94=$AJ$61,$L94,0) -> 0 | AK94: =IF($K94=$AJ$61,$N94,0) -> 0 | AL94: =IF($K94=$AL$61,$L94,0) -> 0 | AM94: =IF($K94=$AL$61,$N94,0) -> 0 | AN94: =IF($K94=$AN$61,$L94,0) -> 0 | AO94: =IF($K94=$AN$61,$N94,0) -> 0 | AP94: =IF($K94=$AP$61,$L94,0) -> 0 | AQ94: =IF($K94=$AP$61,$N94,0) -> 0 | AR94: =IF($K94=$AR$61,$L94,0) -> 0 | AS94: =IF($K94=$AR$61,$N94,0) -> 0 | AT94: =IF($K94=$AT$61,$L94,0) -> 0 | AU94: =IF($K94=$AT$61,$N94,0) -> 0 | AV94: =IF($K94=$AV$61,$L94,0) -> 0 | AW94: =IF($K94=$AV$61,$N94,0) -> 0 | AX94: =IF($K94=$AX$61,$L94,0) -> 0 | AY94: =IF($K94=$AX$61,$N94,0) -> 0 | AZ94: =IF($K94=$AZ$61,$L94,0) -> 0 | BA94: =IF($K94=$AZ$61,$N94,0) -> 0 | BB94: =IF($K94=$BB$61,$L94,0) -> 0 | BC94: =IF($K94=$BB$61,$N94,0) -> 0 | BD94: =IF($O94=$BD$61,$P94,0) -> 0 | BE94: =IF($O94=$BD$61,$R94,0) -> 0 | BF94: =IF($O94=$BF$61,$P94,0) -> 0 | BG94: =IF($O94=$BF$61,$R94,0) -> 0 | BH94: =IF($O94=$BH$61,$P94,0) -> 0 | BI94: =IF($O94=$BH$61,$R94,0) -> 0 | BJ94: =IF($O94=$BJ$61,$P94,0) -> 0 | BK94: =IF($O94=$BJ$61,$R94,0) -> 0 | BL94: =IF($O94=$BL$61,$P94,0) -> 0 | BM94: =IF($O94=$BL$61,$R94,0) -> 0 | BN94: =IF($O94=$BN$61,$P94,0) -> 0 | BO94: =IF($O94=$BN$61,$R94,0) -> 0 | BP94: =IF($O94=$BP$61,$P94,0) -> 0 | BQ94: =IF($O94=$BP$61,$R94,0) -> 0 | BR94: =IF($O94=$BR$61,$P94,0) -> 0 | BS94: =IF($O94=$BR$61,$R94,0) -> 0 | BT94: =IF($O94=$BT$61,$P94,0) -> 0 | BU94: =IF($O94=$BT$61,$R94,0) -> 0 | BV94: =IF($O94=$BV$61,$P94,0) -> 0 | BW94: =IF($O94=$BV$61,$R94,0) -> 0 | BX94: =IF($O94=$BX$61,$P94,0) -> 0 | BY94: =IF($O94=$BX$61,$R94,0) -> 0 | BZ94: =IF($O94=$BZ$61,$P94,0) -> 0 | CA94: =IF($O94=$BZ$61,$R94,0) -> 0 | CB94: =IF($O94=$CB$61,$P94,0) -> 0 | CC94: =IF($O94=$CB$61,$R94,0) -> 0 | CD94: =IF($O94=$CD$61,$P94,0) -> 0 | CE94: =IF($O94=$CD$61,$R94,0) -> 0 | CF94: =IF($O94=$CF$61,$P94,0) -> 0 | CG94: =IF($O94=$CF$61,$R94,0) -> 0 | CH94: =IF($O94=$CH$61,$P94,0) -> 0 | CI94: =IF($O94=$CH$61,$R94,0) -> 0 | CJ94: =IF($O94=$CJ$61,$P94,0) -> 0 | CK94: =IF($O94=$CJ$61,$R94,0) -> 0 | CL94: =IF($O94=$CL$61,$P94,0) -> 0 | CM94: =IF($O94=$CL$61,$R94,0) -> 0 | CN94: =IF($O94=$CN$61,$P94,0) -> 0 | CO94: =IF($O94=$CN$61,$R94,0) -> 0 | CP94: =IF($O94=$CP$61,$P94,0) -> 0 | CQ94: =IF($O94=$CP$61,$R94,0) -> 0 | CR94: =IF($O94=$CR$61,$P94,0) -> 0 | CS94: =IF($O94=$CR$61,$R94,0) -> 0 | CT94: =IF($O94=$CT$61,$P94,0) -> 0 | CU94: =IF($O94=$CT$61,$R94,0) -> 0 | CV94: =IF($O94=$CV$61,$P94,0) -> 0 | CW94: =IF($O94=$CV$61,$R94,0) -> 0 | CX94: =IF($O94=$CX$61,$P94,0) -> 0 | CY94: =IF($O94=$CX$61,$R94,0) -> 0
H95: =S95*1.45 -> 0 | N95: =L95*M95 -> 0 | R95: =Q95*P95 -> 0 | S95: =R95+N95 -> 0 | T95: =IF(H95<>0,1-(S95/H95),0) -> 0 | V95: =IF($K95=$V$61,$L95,0) -> 0 | W95: =IF($K95=$V$61,$N95,0) -> 0 | X95: =IF($K95=$X$61,$L95,0) -> 0 | Y95: =IF($K95=$X$61,$N95,0) -> 0 | Z95: =IF($K95=$Z$61,$L95,0) -> 0 | AA95: =IF($K95=$Z$61,$N95,0) -> 0 | AB95: =IF($K95=$AB$61,$L95,0) -> 0 | AC95: =IF($K95=$AB$61,$N95,0) -> 0 | AD95: =IF($K95=$AD$61,$L95,0) -> 0 | AE95: =IF($K95=$AD$61,$N95,0) -> 0 | AF95: =IF($K95=$AF$61,$L95,0) -> 0 | AG95: =IF($K95=$AF$61,$N95,0) -> 0 | AH95: =IF($K95=$AH$61,$L95,0) -> 0 | AI95: =IF($K95=$AH$61,$N95,0) -> 0 | AJ95: =IF($K95=$AJ$61,$L95,0) -> 0 | AK95: =IF($K95=$AJ$61,$N95,0) -> 0 | AL95: =IF($K95=$AL$61,$L95,0) -> 0 | AM95: =IF($K95=$AL$61,$N95,0) -> 0 | AN95: =IF($K95=$AN$61,$L95,0) -> 0 | AO95: =IF($K95=$AN$61,$N95,0) -> 0 | AP95: =IF($K95=$AP$61,$L95,0) -> 0 | AQ95: =IF($K95=$AP$61,$N95,0) -> 0 | AR95: =IF($K95=$AR$61,$L95,0) -> 0 | AS95: =IF($K95=$AR$61,$N95,0) -> 0 | AT95: =IF($K95=$AT$61,$L95,0) -> 0 | AU95: =IF($K95=$AT$61,$N95,0) -> 0 | AV95: =IF($K95=$AV$61,$L95,0) -> 0 | AW95: =IF($K95=$AV$61,$N95,0) -> 0 | AX95: =IF($K95=$AX$61,$L95,0) -> 0 | AY95: =IF($K95=$AX$61,$N95,0) -> 0 | AZ95: =IF($K95=$AZ$61,$L95,0) -> 0 | BA95: =IF($K95=$AZ$61,$N95,0) -> 0 | BB95: =IF($K95=$BB$61,$L95,0) -> 0 | BC95: =IF($K95=$BB$61,$N95,0) -> 0 | BD95: =IF($O95=$BD$61,$P95,0) -> 0 | BE95: =IF($O95=$BD$61,$R95,0) -> 0 | BF95: =IF($O95=$BF$61,$P95,0) -> 0 | BG95: =IF($O95=$BF$61,$R95,0) -> 0 | BH95: =IF($O95=$BH$61,$P95,0) -> 0 | BI95: =IF($O95=$BH$61,$R95,0) -> 0 | BJ95: =IF($O95=$BJ$61,$P95,0) -> 0 | BK95: =IF($O95=$BJ$61,$R95,0) -> 0 | BL95: =IF($O95=$BL$61,$P95,0) -> 0 | BM95: =IF($O95=$BL$61,$R95,0) -> 0 | BN95: =IF($O95=$BN$61,$P95,0) -> 0 | BO95: =IF($O95=$BN$61,$R95,0) -> 0 | BP95: =IF($O95=$BP$61,$P95,0) -> 0 | BQ95: =IF($O95=$BP$61,$R95,0) -> 0 | BR95: =IF($O95=$BR$61,$P95,0) -> 0 | BS95: =IF($O95=$BR$61,$R95,0) -> 0 | BT95: =IF($O95=$BT$61,$P95,0) -> 0 | BU95: =IF($O95=$BT$61,$R95,0) -> 0 | BV95: =IF($O95=$BV$61,$P95,0) -> 0 | BW95: =IF($O95=$BV$61,$R95,0) -> 0 | BX95: =IF($O95=$BX$61,$P95,0) -> 0 | BY95: =IF($O95=$BX$61,$R95,0) -> 0 | BZ95: =IF($O95=$BZ$61,$P95,0) -> 0 | CA95: =IF($O95=$BZ$61,$R95,0) -> 0 | CB95: =IF($O95=$CB$61,$P95,0) -> 0 | CC95: =IF($O95=$CB$61,$R95,0) -> 0 | CD95: =IF($O95=$CD$61,$P95,0) -> 0 | CE95: =IF($O95=$CD$61,$R95,0) -> 0 | CF95: =IF($O95=$CF$61,$P95,0) -> 0 | CG95: =IF($O95=$CF$61,$R95,0) -> 0 | CH95: =IF($O95=$CH$61,$P95,0) -> 0 | CI95: =IF($O95=$CH$61,$R95,0) -> 0 | CJ95: =IF($O95=$CJ$61,$P95,0) -> 0 | CK95: =IF($O95=$CJ$61,$R95,0) -> 0 | CL95: =IF($O95=$CL$61,$P95,0) -> 0 | CM95: =IF($O95=$CL$61,$R95,0) -> 0 | CN95: =IF($O95=$CN$61,$P95,0) -> 0 | CO95: =IF($O95=$CN$61,$R95,0) -> 0 | CP95: =IF($O95=$CP$61,$P95,0) -> 0 | CQ95: =IF($O95=$CP$61,$R95,0) -> 0 | CR95: =IF($O95=$CR$61,$P95,0) -> 0 | CS95: =IF($O95=$CR$61,$R95,0) -> 0 | CT95: =IF($O95=$CT$61,$P95,0) -> 0 | CU95: =IF($O95=$CT$61,$R95,0) -> 0 | CV95: =IF($O95=$CV$61,$P95,0) -> 0 | CW95: =IF($O95=$CV$61,$R95,0) -> 0 | CX95: =IF($O95=$CX$61,$P95,0) -> 0 | CY95: =IF($O95=$CX$61,$R95,0) -> 0
H96: =S96*1.45 -> 0 | N96: =L96*M96 -> 0 | R96: =Q96*P96 -> 0 | S96: =R96+N96 -> 0 | T96: =IF(H96<>0,1-(S96/H96),0) -> 0 | V96: =IF($K96=$V$61,$L96,0) -> 0 | W96: =IF($K96=$V$61,$N96,0) -> 0 | X96: =IF($K96=$X$61,$L96,0) -> 0 | Y96: =IF($K96=$X$61,$N96,0) -> 0 | Z96: =IF($K96=$Z$61,$L96,0) -> 0 | AA96: =IF($K96=$Z$61,$N96,0) -> 0 | AB96: =IF($K96=$AB$61,$L96,0) -> 0 | AC96: =IF($K96=$AB$61,$N96,0) -> 0 | AD96: =IF($K96=$AD$61,$L96,0) -> 0 | AE96: =IF($K96=$AD$61,$N96,0) -> 0 | AF96: =IF($K96=$AF$61,$L96,0) -> 0 | AG96: =IF($K96=$AF$61,$N96,0) -> 0 | AH96: =IF($K96=$AH$61,$L96,0) -> 0 | AI96: =IF($K96=$AH$61,$N96,0) -> 0 | AJ96: =IF($K96=$AJ$61,$L96,0) -> 0 | AK96: =IF($K96=$AJ$61,$N96,0) -> 0 | AL96: =IF($K96=$AL$61,$L96,0) -> 0 | AM96: =IF($K96=$AL$61,$N96,0) -> 0 | AN96: =IF($K96=$AN$61,$L96,0) -> 0 | AO96: =IF($K96=$AN$61,$N96,0) -> 0 | AP96: =IF($K96=$AP$61,$L96,0) -> 0 | AQ96: =IF($K96=$AP$61,$N96,0) -> 0 | AR96: =IF($K96=$AR$61,$L96,0) -> 0 | AS96: =IF($K96=$AR$61,$N96,0) -> 0 | AT96: =IF($K96=$AT$61,$L96,0) -> 0 | AU96: =IF($K96=$AT$61,$N96,0) -> 0 | AV96: =IF($K96=$AV$61,$L96,0) -> 0 | AW96: =IF($K96=$AV$61,$N96,0) -> 0 | AX96: =IF($K96=$AX$61,$L96,0) -> 0 | AY96: =IF($K96=$AX$61,$N96,0) -> 0 | AZ96: =IF($K96=$AZ$61,$L96,0) -> 0 | BA96: =IF($K96=$AZ$61,$N96,0) -> 0 | BB96: =IF($K96=$BB$61,$L96,0) -> 0 | BC96: =IF($K96=$BB$61,$N96,0) -> 0 | BD96: =IF($O96=$BD$61,$P96,0) -> 0 | BE96: =IF($O96=$BD$61,$R96,0) -> 0 | BF96: =IF($O96=$BF$61,$P96,0) -> 0 | BG96: =IF($O96=$BF$61,$R96,0) -> 0 | BH96: =IF($O96=$BH$61,$P96,0) -> 0 | BI96: =IF($O96=$BH$61,$R96,0) -> 0 | BJ96: =IF($O96=$BJ$61,$P96,0) -> 0 | BK96: =IF($O96=$BJ$61,$R96,0) -> 0 | BL96: =IF($O96=$BL$61,$P96,0) -> 0 | BM96: =IF($O96=$BL$61,$R96,0) -> 0 | BN96: =IF($O96=$BN$61,$P96,0) -> 0 | BO96: =IF($O96=$BN$61,$R96,0) -> 0 | BP96: =IF($O96=$BP$61,$P96,0) -> 0 | BQ96: =IF($O96=$BP$61,$R96,0) -> 0 | BR96: =IF($O96=$BR$61,$P96,0) -> 0 | BS96: =IF($O96=$BR$61,$R96,0) -> 0 | BT96: =IF($O96=$BT$61,$P96,0) -> 0 | BU96: =IF($O96=$BT$61,$R96,0) -> 0 | BV96: =IF($O96=$BV$61,$P96,0) -> 0 | BW96: =IF($O96=$BV$61,$R96,0) -> 0 | BX96: =IF($O96=$BX$61,$P96,0) -> 0 | BY96: =IF($O96=$BX$61,$R96,0) -> 0 | BZ96: =IF($O96=$BZ$61,$P96,0) -> 0 | CA96: =IF($O96=$BZ$61,$R96,0) -> 0 | CB96: =IF($O96=$CB$61,$P96,0) -> 0 | CC96: =IF($O96=$CB$61,$R96,0) -> 0 | CD96: =IF($O96=$CD$61,$P96,0) -> 0 | CE96: =IF($O96=$CD$61,$R96,0) -> 0 | CF96: =IF($O96=$CF$61,$P96,0) -> 0 | CG96: =IF($O96=$CF$61,$R96,0) -> 0 | CH96: =IF($O96=$CH$61,$P96,0) -> 0 | CI96: =IF($O96=$CH$61,$R96,0) -> 0 | CJ96: =IF($O96=$CJ$61,$P96,0) -> 0 | CK96: =IF($O96=$CJ$61,$R96,0) -> 0 | CL96: =IF($O96=$CL$61,$P96,0) -> 0 | CM96: =IF($O96=$CL$61,$R96,0) -> 0 | CN96: =IF($O96=$CN$61,$P96,0) -> 0 | CO96: =IF($O96=$CN$61,$R96,0) -> 0 | CP96: =IF($O96=$CP$61,$P96,0) -> 0 | CQ96: =IF($O96=$CP$61,$R96,0) -> 0 | CR96: =IF($O96=$CR$61,$P96,0) -> 0 | CS96: =IF($O96=$CR$61,$R96,0) -> 0 | CT96: =IF($O96=$CT$61,$P96,0) -> 0 | CU96: =IF($O96=$CT$61,$R96,0) -> 0 | CV96: =IF($O96=$CV$61,$P96,0) -> 0 | CW96: =IF($O96=$CV$61,$R96,0) -> 0 | CX96: =IF($O96=$CX$61,$P96,0) -> 0 | CY96: =IF($O96=$CX$61,$R96,0) -> 0
H97: =S97*1.45 -> 0 | N97: =L97*M97 -> 0 | R97: =Q97*P97 -> 0 | S97: =R97+N97 -> 0 | T97: =IF(H97<>0,1-(S97/H97),0) -> 0 | V97: =IF($K97=$V$61,$L97,0) -> 0 | W97: =IF($K97=$V$61,$N97,0) -> 0 | X97: =IF($K97=$X$61,$L97,0) -> 0 | Y97: =IF($K97=$X$61,$N97,0) -> 0 | Z97: =IF($K97=$Z$61,$L97,0) -> 0 | AA97: =IF($K97=$Z$61,$N97,0) -> 0 | AB97: =IF($K97=$AB$61,$L97,0) -> 0 | AC97: =IF($K97=$AB$61,$N97,0) -> 0 | AD97: =IF($K97=$AD$61,$L97,0) -> 0 | AE97: =IF($K97=$AD$61,$N97,0) -> 0 | AF97: =IF($K97=$AF$61,$L97,0) -> 0 | AG97: =IF($K97=$AF$61,$N97,0) -> 0 | AH97: =IF($K97=$AH$61,$L97,0) -> 0 | AI97: =IF($K97=$AH$61,$N97,0) -> 0 | AJ97: =IF($K97=$AJ$61,$L97,0) -> 0 | AK97: =IF($K97=$AJ$61,$N97,0) -> 0 | AL97: =IF($K97=$AL$61,$L97,0) -> 0 | AM97: =IF($K97=$AL$61,$N97,0) -> 0 | AN97: =IF($K97=$AN$61,$L97,0) -> 0 | AO97: =IF($K97=$AN$61,$N97,0) -> 0 | AP97: =IF($K97=$AP$61,$L97,0) -> 0 | AQ97: =IF($K97=$AP$61,$N97,0) -> 0 | AR97: =IF($K97=$AR$61,$L97,0) -> 0 | AS97: =IF($K97=$AR$61,$N97,0) -> 0 | AT97: =IF($K97=$AT$61,$L97,0) -> 0 | AU97: =IF($K97=$AT$61,$N97,0) -> 0 | AV97: =IF($K97=$AV$61,$L97,0) -> 0 | AW97: =IF($K97=$AV$61,$N97,0) -> 0 | AX97: =IF($K97=$AX$61,$L97,0) -> 0 | AY97: =IF($K97=$AX$61,$N97,0) -> 0 | AZ97: =IF($K97=$AZ$61,$L97,0) -> 0 | BA97: =IF($K97=$AZ$61,$N97,0) -> 0 | BB97: =IF($K97=$BB$61,$L97,0) -> 0 | BC97: =IF($K97=$BB$61,$N97,0) -> 0 | BD97: =IF($O97=$BD$61,$P97,0) -> 0 | BE97: =IF($O97=$BD$61,$R97,0) -> 0 | BF97: =IF($O97=$BF$61,$P97,0) -> 0 | BG97: =IF($O97=$BF$61,$R97,0) -> 0 | BH97: =IF($O97=$BH$61,$P97,0) -> 0 | BI97: =IF($O97=$BH$61,$R97,0) -> 0 | BJ97: =IF($O97=$BJ$61,$P97,0) -> 0 | BK97: =IF($O97=$BJ$61,$R97,0) -> 0 | BL97: =IF($O97=$BL$61,$P97,0) -> 0 | BM97: =IF($O97=$BL$61,$R97,0) -> 0 | BN97: =IF($O97=$BN$61,$P97,0) -> 0 | BO97: =IF($O97=$BN$61,$R97,0) -> 0 | BP97: =IF($O97=$BP$61,$P97,0) -> 0 | BQ97: =IF($O97=$BP$61,$R97,0) -> 0 | BR97: =IF($O97=$BR$61,$P97,0) -> 0 | BS97: =IF($O97=$BR$61,$R97,0) -> 0 | BT97: =IF($O97=$BT$61,$P97,0) -> 0 | BU97: =IF($O97=$BT$61,$R97,0) -> 0 | BV97: =IF($O97=$BV$61,$P97,0) -> 0 | BW97: =IF($O97=$BV$61,$R97,0) -> 0 | BX97: =IF($O97=$BX$61,$P97,0) -> 0 | BY97: =IF($O97=$BX$61,$R97,0) -> 0 | BZ97: =IF($O97=$BZ$61,$P97,0) -> 0 | CA97: =IF($O97=$BZ$61,$R97,0) -> 0 | CB97: =IF($O97=$CB$61,$P97,0) -> 0 | CC97: =IF($O97=$CB$61,$R97,0) -> 0 | CD97: =IF($O97=$CD$61,$P97,0) -> 0 | CE97: =IF($O97=$CD$61,$R97,0) -> 0 | CF97: =IF($O97=$CF$61,$P97,0) -> 0 | CG97: =IF($O97=$CF$61,$R97,0) -> 0 | CH97: =IF($O97=$CH$61,$P97,0) -> 0 | CI97: =IF($O97=$CH$61,$R97,0) -> 0 | CJ97: =IF($O97=$CJ$61,$P97,0) -> 0 | CK97: =IF($O97=$CJ$61,$R97,0) -> 0 | CL97: =IF($O97=$CL$61,$P97,0) -> 0 | CM97: =IF($O97=$CL$61,$R97,0) -> 0 | CN97: =IF($O97=$CN$61,$P97,0) -> 0 | CO97: =IF($O97=$CN$61,$R97,0) -> 0 | CP97: =IF($O97=$CP$61,$P97,0) -> 0 | CQ97: =IF($O97=$CP$61,$R97,0) -> 0 | CR97: =IF($O97=$CR$61,$P97,0) -> 0 | CS97: =IF($O97=$CR$61,$R97,0) -> 0 | CT97: =IF($O97=$CT$61,$P97,0) -> 0 | CU97: =IF($O97=$CT$61,$R97,0) -> 0 | CV97: =IF($O97=$CV$61,$P97,0) -> 0 | CW97: =IF($O97=$CV$61,$R97,0) -> 0 | CX97: =IF($O97=$CX$61,$P97,0) -> 0 | CY97: =IF($O97=$CX$61,$R97,0) -> 0
H98: =S98*1.45 -> 0 | N98: =L98*M98 -> 0 | R98: =Q98*P98 -> 0 | S98: =R98+N98 -> 0 | T98: =IF(H98<>0,1-(S98/H98),0) -> 0 | V98: =IF($K98=$V$61,$L98,0) -> 0 | W98: =IF($K98=$V$61,$N98,0) -> 0 | X98: =IF($K98=$X$61,$L98,0) -> 0 | Y98: =IF($K98=$X$61,$N98,0) -> 0 | Z98: =IF($K98=$Z$61,$L98,0) -> 0 | AA98: =IF($K98=$Z$61,$N98,0) -> 0 | AB98: =IF($K98=$AB$61,$L98,0) -> 0 | AC98: =IF($K98=$AB$61,$N98,0) -> 0 | AD98: =IF($K98=$AD$61,$L98,0) -> 0 | AE98: =IF($K98=$AD$61,$N98,0) -> 0 | AF98: =IF($K98=$AF$61,$L98,0) -> 0 | AG98: =IF($K98=$AF$61,$N98,0) -> 0 | AH98: =IF($K98=$AH$61,$L98,0) -> 0 | AI98: =IF($K98=$AH$61,$N98,0) -> 0 | AJ98: =IF($K98=$AJ$61,$L98,0) -> 0 | AK98: =IF($K98=$AJ$61,$N98,0) -> 0 | AL98: =IF($K98=$AL$61,$L98,0) -> 0 | AM98: =IF($K98=$AL$61,$N98,0) -> 0 | AN98: =IF($K98=$AN$61,$L98,0) -> 0 | AO98: =IF($K98=$AN$61,$N98,0) -> 0 | AP98: =IF($K98=$AP$61,$L98,0) -> 0 | AQ98: =IF($K98=$AP$61,$N98,0) -> 0 | AR98: =IF($K98=$AR$61,$L98,0) -> 0 | AS98: =IF($K98=$AR$61,$N98,0) -> 0 | AT98: =IF($K98=$AT$61,$L98,0) -> 0 | AU98: =IF($K98=$AT$61,$N98,0) -> 0 | AV98: =IF($K98=$AV$61,$L98,0) -> 0 | AW98: =IF($K98=$AV$61,$N98,0) -> 0 | AX98: =IF($K98=$AX$61,$L98,0) -> 0 | AY98: =IF($K98=$AX$61,$N98,0) -> 0 | AZ98: =IF($K98=$AZ$61,$L98,0) -> 0 | BA98: =IF($K98=$AZ$61,$N98,0) -> 0 | BB98: =IF($K98=$BB$61,$L98,0) -> 0 | BC98: =IF($K98=$BB$61,$N98,0) -> 0 | BD98: =IF($O98=$BD$61,$P98,0) -> 0 | BE98: =IF($O98=$BD$61,$R98,0) -> 0 | BF98: =IF($O98=$BF$61,$P98,0) -> 0 | BG98: =IF($O98=$BF$61,$R98,0) -> 0 | BH98: =IF($O98=$BH$61,$P98,0) -> 0 | BI98: =IF($O98=$BH$61,$R98,0) -> 0 | BJ98: =IF($O98=$BJ$61,$P98,0) -> 0 | BK98: =IF($O98=$BJ$61,$R98,0) -> 0 | BL98: =IF($O98=$BL$61,$P98,0) -> 0 | BM98: =IF($O98=$BL$61,$R98,0) -> 0 | BN98: =IF($O98=$BN$61,$P98,0) -> 0 | BO98: =IF($O98=$BN$61,$R98,0) -> 0 | BP98: =IF($O98=$BP$61,$P98,0) -> 0 | BQ98: =IF($O98=$BP$61,$R98,0) -> 0 | BR98: =IF($O98=$BR$61,$P98,0) -> 0 | BS98: =IF($O98=$BR$61,$R98,0) -> 0 | BT98: =IF($O98=$BT$61,$P98,0) -> 0 | BU98: =IF($O98=$BT$61,$R98,0) -> 0 | BV98: =IF($O98=$BV$61,$P98,0) -> 0 | BW98: =IF($O98=$BV$61,$R98,0) -> 0 | BX98: =IF($O98=$BX$61,$P98,0) -> 0 | BY98: =IF($O98=$BX$61,$R98,0) -> 0 | BZ98: =IF($O98=$BZ$61,$P98,0) -> 0 | CA98: =IF($O98=$BZ$61,$R98,0) -> 0 | CB98: =IF($O98=$CB$61,$P98,0) -> 0 | CC98: =IF($O98=$CB$61,$R98,0) -> 0 | CD98: =IF($O98=$CD$61,$P98,0) -> 0 | CE98: =IF($O98=$CD$61,$R98,0) -> 0 | CF98: =IF($O98=$CF$61,$P98,0) -> 0 | CG98: =IF($O98=$CF$61,$R98,0) -> 0 | CH98: =IF($O98=$CH$61,$P98,0) -> 0 | CI98: =IF($O98=$CH$61,$R98,0) -> 0 | CJ98: =IF($O98=$CJ$61,$P98,0) -> 0 | CK98: =IF($O98=$CJ$61,$R98,0) -> 0 | CL98: =IF($O98=$CL$61,$P98,0) -> 0 | CM98: =IF($O98=$CL$61,$R98,0) -> 0 | CN98: =IF($O98=$CN$61,$P98,0) -> 0 | CO98: =IF($O98=$CN$61,$R98,0) -> 0 | CP98: =IF($O98=$CP$61,$P98,0) -> 0 | CQ98: =IF($O98=$CP$61,$R98,0) -> 0 | CR98: =IF($O98=$CR$61,$P98,0) -> 0 | CS98: =IF($O98=$CR$61,$R98,0) -> 0 | CT98: =IF($O98=$CT$61,$P98,0) -> 0 | CU98: =IF($O98=$CT$61,$R98,0) -> 0 | CV98: =IF($O98=$CV$61,$P98,0) -> 0 | CW98: =IF($O98=$CV$61,$R98,0) -> 0 | CX98: =IF($O98=$CX$61,$P98,0) -> 0 | CY98: =IF($O98=$CX$61,$R98,0) -> 0
H99: =S99*1.45 -> 0 | N99: =L99*M99 -> 0 | R99: =Q99*P99 -> 0 | S99: =R99+N99 -> 0 | T99: =IF(H99<>0,1-(S99/H99),0) -> 0 | V99: =IF($K99=$V$61,$L99,0) -> 0 | W99: =IF($K99=$V$61,$N99,0) -> 0 | X99: =IF($K99=$X$61,$L99,0) -> 0 | Y99: =IF($K99=$X$61,$N99,0) -> 0 | Z99: =IF($K99=$Z$61,$L99,0) -> 0 | AA99: =IF($K99=$Z$61,$N99,0) -> 0 | AB99: =IF($K99=$AB$61,$L99,0) -> 0 | AC99: =IF($K99=$AB$61,$N99,0) -> 0 | AD99: =IF($K99=$AD$61,$L99,0) -> 0 | AE99: =IF($K99=$AD$61,$N99,0) -> 0 | AF99: =IF($K99=$AF$61,$L99,0) -> 0 | AG99: =IF($K99=$AF$61,$N99,0) -> 0 | AH99: =IF($K99=$AH$61,$L99,0) -> 0 | AI99: =IF($K99=$AH$61,$N99,0) -> 0 | AJ99: =IF($K99=$AJ$61,$L99,0) -> 0 | AK99: =IF($K99=$AJ$61,$N99,0) -> 0 | AL99: =IF($K99=$AL$61,$L99,0) -> 0 | AM99: =IF($K99=$AL$61,$N99,0) -> 0 | AN99: =IF($K99=$AN$61,$L99,0) -> 0 | AO99: =IF($K99=$AN$61,$N99,0) -> 0 | AP99: =IF($K99=$AP$61,$L99,0) -> 0 | AQ99: =IF($K99=$AP$61,$N99,0) -> 0 | AR99: =IF($K99=$AR$61,$L99,0) -> 0 | AS99: =IF($K99=$AR$61,$N99,0) -> 0 | AT99: =IF($K99=$AT$61,$L99,0) -> 0 | AU99: =IF($K99=$AT$61,$N99,0) -> 0 | AV99: =IF($K99=$AV$61,$L99,0) -> 0 | AW99: =IF($K99=$AV$61,$N99,0) -> 0 | AX99: =IF($K99=$AX$61,$L99,0) -> 0 | AY99: =IF($K99=$AX$61,$N99,0) -> 0 | AZ99: =IF($K99=$AZ$61,$L99,0) -> 0 | BA99: =IF($K99=$AZ$61,$N99,0) -> 0 | BB99: =IF($K99=$BB$61,$L99,0) -> 0 | BC99: =IF($K99=$BB$61,$N99,0) -> 0 | BD99: =IF($O99=$BD$61,$P99,0) -> 0 | BE99: =IF($O99=$BD$61,$R99,0) -> 0 | BF99: =IF($O99=$BF$61,$P99,0) -> 0 | BG99: =IF($O99=$BF$61,$R99,0) -> 0 | BH99: =IF($O99=$BH$61,$P99,0) -> 0 | BI99: =IF($O99=$BH$61,$R99,0) -> 0 | BJ99: =IF($O99=$BJ$61,$P99,0) -> 0 | BK99: =IF($O99=$BJ$61,$R99,0) -> 0 | BL99: =IF($O99=$BL$61,$P99,0) -> 0 | BM99: =IF($O99=$BL$61,$R99,0) -> 0 | BN99: =IF($O99=$BN$61,$P99,0) -> 0 | BO99: =IF($O99=$BN$61,$R99,0) -> 0 | BP99: =IF($O99=$BP$61,$P99,0) -> 0 | BQ99: =IF($O99=$BP$61,$R99,0) -> 0 | BR99: =IF($O99=$BR$61,$P99,0) -> 0 | BS99: =IF($O99=$BR$61,$R99,0) -> 0 | BT99: =IF($O99=$BT$61,$P99,0) -> 0 | BU99: =IF($O99=$BT$61,$R99,0) -> 0 | BV99: =IF($O99=$BV$61,$P99,0) -> 0 | BW99: =IF($O99=$BV$61,$R99,0) -> 0 | BX99: =IF($O99=$BX$61,$P99,0) -> 0 | BY99: =IF($O99=$BX$61,$R99,0) -> 0 | BZ99: =IF($O99=$BZ$61,$P99,0) -> 0 | CA99: =IF($O99=$BZ$61,$R99,0) -> 0 | CB99: =IF($O99=$CB$61,$P99,0) -> 0 | CC99: =IF($O99=$CB$61,$R99,0) -> 0 | CD99: =IF($O99=$CD$61,$P99,0) -> 0 | CE99: =IF($O99=$CD$61,$R99,0) -> 0 | CF99: =IF($O99=$CF$61,$P99,0) -> 0 | CG99: =IF($O99=$CF$61,$R99,0) -> 0 | CH99: =IF($O99=$CH$61,$P99,0) -> 0 | CI99: =IF($O99=$CH$61,$R99,0) -> 0 | CJ99: =IF($O99=$CJ$61,$P99,0) -> 0 | CK99: =IF($O99=$CJ$61,$R99,0) -> 0 | CL99: =IF($O99=$CL$61,$P99,0) -> 0 | CM99: =IF($O99=$CL$61,$R99,0) -> 0 | CN99: =IF($O99=$CN$61,$P99,0) -> 0 | CO99: =IF($O99=$CN$61,$R99,0) -> 0 | CP99: =IF($O99=$CP$61,$P99,0) -> 0 | CQ99: =IF($O99=$CP$61,$R99,0) -> 0 | CR99: =IF($O99=$CR$61,$P99,0) -> 0 | CS99: =IF($O99=$CR$61,$R99,0) -> 0 | CT99: =IF($O99=$CT$61,$P99,0) -> 0 | CU99: =IF($O99=$CT$61,$R99,0) -> 0 | CV99: =IF($O99=$CV$61,$P99,0) -> 0 | CW99: =IF($O99=$CV$61,$R99,0) -> 0 | CX99: =IF($O99=$CX$61,$P99,0) -> 0 | CY99: =IF($O99=$CX$61,$R99,0) -> 0
H100: =S100*1.45 -> 0 | N100: =L100*M100 -> 0 | R100: =Q100*P100 -> 0 | S100: =R100+N100 -> 0 | T100: =IF(H100<>0,1-(S100/H100),0) -> 0 | V100: =IF($K100=$V$61,$L100,0) -> 0 | W100: =IF($K100=$V$61,$N100,0) -> 0 | X100: =IF($K100=$X$61,$L100,0) -> 0 | Y100: =IF($K100=$X$61,$N100,0) -> 0 | Z100: =IF($K100=$Z$61,$L100,0) -> 0 | AA100: =IF($K100=$Z$61,$N100,0) -> 0 | AB100: =IF($K100=$AB$61,$L100,0) -> 0 | AC100: =IF($K100=$AB$61,$N100,0) -> 0 | AD100: =IF($K100=$AD$61,$L100,0) -> 0 | AE100: =IF($K100=$AD$61,$N100,0) -> 0 | AF100: =IF($K100=$AF$61,$L100,0) -> 0 | AG100: =IF($K100=$AF$61,$N100,0) -> 0 | AH100: =IF($K100=$AH$61,$L100,0) -> 0 | AI100: =IF($K100=$AH$61,$N100,0) -> 0 | AJ100: =IF($K100=$AJ$61,$L100,0) -> 0 | AK100: =IF($K100=$AJ$61,$N100,0) -> 0 | AL100: =IF($K100=$AL$61,$L100,0) -> 0 | AM100: =IF($K100=$AL$61,$N100,0) -> 0 | AN100: =IF($K100=$AN$61,$L100,0) -> 0 | AO100: =IF($K100=$AN$61,$N100,0) -> 0 | AP100: =IF($K100=$AP$61,$L100,0) -> 0 | AQ100: =IF($K100=$AP$61,$N100,0) -> 0 | AR100: =IF($K100=$AR$61,$L100,0) -> 0 | AS100: =IF($K100=$AR$61,$N100,0) -> 0 | AT100: =IF($K100=$AT$61,$L100,0) -> 0 | AU100: =IF($K100=$AT$61,$N100,0) -> 0 | AV100: =IF($K100=$AV$61,$L100,0) -> 0 | AW100: =IF($K100=$AV$61,$N100,0) -> 0 | AX100: =IF($K100=$AX$61,$L100,0) -> 0 | AY100: =IF($K100=$AX$61,$N100,0) -> 0 | AZ100: =IF($K100=$AZ$61,$L100,0) -> 0 | BA100: =IF($K100=$AZ$61,$N100,0) -> 0 | BB100: =IF($K100=$BB$61,$L100,0) -> 0 | BC100: =IF($K100=$BB$61,$N100,0) -> 0 | BD100: =IF($O100=$BD$61,$P100,0) -> 0 | BE100: =IF($O100=$BD$61,$R100,0) -> 0 | BF100: =IF($O100=$BF$61,$P100,0) -> 0 | BG100: =IF($O100=$BF$61,$R100,0) -> 0 | BH100: =IF($O100=$BH$61,$P100,0) -> 0 | BI100: =IF($O100=$BH$61,$R100,0) -> 0 | BJ100: =IF($O100=$BJ$61,$P100,0) -> 0 | BK100: =IF($O100=$BJ$61,$R100,0) -> 0 | BL100: =IF($O100=$BL$61,$P100,0) -> 0 | BM100: =IF($O100=$BL$61,$R100,0) -> 0 | BN100: =IF($O100=$BN$61,$P100,0) -> 0 | BO100: =IF($O100=$BN$61,$R100,0) -> 0 | BP100: =IF($O100=$BP$61,$P100,0) -> 0 | BQ100: =IF($O100=$BP$61,$R100,0) -> 0 | BR100: =IF($O100=$BR$61,$P100,0) -> 0 | BS100: =IF($O100=$BR$61,$R100,0) -> 0 | BT100: =IF($O100=$BT$61,$P100,0) -> 0 | BU100: =IF($O100=$BT$61,$R100,0) -> 0 | BV100: =IF($O100=$BV$61,$P100,0) -> 0 | BW100: =IF($O100=$BV$61,$R100,0) -> 0 | BX100: =IF($O100=$BX$61,$P100,0) -> 0 | BY100: =IF($O100=$BX$61,$R100,0) -> 0 | BZ100: =IF($O100=$BZ$61,$P100,0) -> 0 | CA100: =IF($O100=$BZ$61,$R100,0) -> 0 | CB100: =IF($O100=$CB$61,$P100,0) -> 0 | CC100: =IF($O100=$CB$61,$R100,0) -> 0 | CD100: =IF($O100=$CD$61,$P100,0) -> 0 | CE100: =IF($O100=$CD$61,$R100,0) -> 0 | CF100: =IF($O100=$CF$61,$P100,0) -> 0 | CG100: =IF($O100=$CF$61,$R100,0) -> 0 | CH100: =IF($O100=$CH$61,$P100,0) -> 0 | CI100: =IF($O100=$CH$61,$R100,0) -> 0 | CJ100: =IF($O100=$CJ$61,$P100,0) -> 0 | CK100: =IF($O100=$CJ$61,$R100,0) -> 0 | CL100: =IF($O100=$CL$61,$P100,0) -> 0 | CM100: =IF($O100=$CL$61,$R100,0) -> 0 | CN100: =IF($O100=$CN$61,$P100,0) -> 0 | CO100: =IF($O100=$CN$61,$R100,0) -> 0 | CP100: =IF($O100=$CP$61,$P100,0) -> 0 | CQ100: =IF($O100=$CP$61,$R100,0) -> 0 | CR100: =IF($O100=$CR$61,$P100,0) -> 0 | CS100: =IF($O100=$CR$61,$R100,0) -> 0 | CT100: =IF($O100=$CT$61,$P100,0) -> 0 | CU100: =IF($O100=$CT$61,$R100,0) -> 0 | CV100: =IF($O100=$CV$61,$P100,0) -> 0 | CW100: =IF($O100=$CV$61,$R100,0) -> 0 | CX100: =IF($O100=$CX$61,$P100,0) -> 0 | CY100: =IF($O100=$CX$61,$R100,0) -> 0
... H107: =S107*1.45 -> 0 | N107: =L107*M107 -> 0 | R107: =Q107*P107 -> 0 | S107: =R107+N107 -> 0 | T107: =IF(H107<>0,1-(S107/H107),0) -> 0 | V107: =IF($K107=$V$61,$L107,0) -> 0 | W107: =IF($K107=$V$61,$N107,0) -> 0 | X107: =IF($K107=$X$61,$L107,0) -> 0 | Y107: =IF($K107=$X$61,$N107,0) -> 0 | Z107: =IF($K107=$Z$61,$L107,0) -> 0 | AA107: =IF($K107=$Z$61,$N107,0) -> 0 | AB107: =IF($K107=$AB$61,$L107,0) -> 0 | AC107: =IF($K107=$AB$61,$N107,0) -> 0 | AD107: =IF($K107=$AD$61,$L107,0) -> 0 | AE107: =IF($K107=$AD$61,$N107,0) -> 0 | AF107: =IF($K107=$AF$61,$L107,0) -> 0 | AG107: =IF($K107=$AF$61,$N107,0) -> 0 | AH107: =IF($K107=$AH$61,$L107,0) -> 0 | AI107: =IF($K107=$AH$61,$N107,0) -> 0 | AJ107: =IF($K107=$AJ$61,$L107,0) -> 0 | AK107: =IF($K107=$AJ$61,$N107,0) -> 0 | AL107: =IF($K107=$AL$61,$L107,0) -> 0 | AM107: =IF($K107=$AL$61,$N107,0) -> 0 | AN107: =IF($K107=$AN$61,$L107,0) -> 0 | AO107: =IF($K107=$AN$61,$N107,0) -> 0 | AP107: =IF($K107=$AP$61,$L107,0) -> 0 | AQ107: =IF($K107=$AP$61,$N107,0) -> 0 | AR107: =IF($K107=$AR$61,$L107,0) -> 0 | AS107: =IF($K107=$AR$61,$N107,0) -> 0 | AT107: =IF($K107=$AT$61,$L107,0) -> 0 | AU107: =IF($K107=$AT$61,$N107,0) -> 0 | AV107: =IF($K107=$AV$61,$L107,0) -> 0 | AW107: =IF($K107=$AV$61,$N107,0) -> 0 | AX107: =IF($K107=$AX$61,$L107,0) -> 0 | AY107: =IF($K107=$AX$61,$N107,0) -> 0 | AZ107: =IF($K107=$AZ$61,$L107,0) -> 0 | BA107: =IF($K107=$AZ$61,$N107,0) -> 0 | BB107: =IF($K107=$BB$61,$L107,0) -> 0 | BC107: =IF($K107=$BB$61,$N107,0) -> 0 | BD107: =IF($O107=$BD$61,$P107,0) -> 0 | BE107: =IF($O107=$BD$61,$R107,0) -> 0 | BF107: =IF($O107=$BF$61,$P107,0) -> 0 | BG107: =IF($O107=$BF$61,$R107,0) -> 0 | BH107: =IF($O107=$BH$61,$P107,0) -> 0 | BI107: =IF($O107=$BH$61,$R107,0) -> 0 | BJ107: =IF($O107=$BJ$61,$P107,0) -> 0 | BK107: =IF($O107=$BJ$61,$R107,0) -> 0 | BL107: =IF($O107=$BL$61,$P107,0) -> 0 | BM107: =IF($O107=$BL$61,$R107,0) -> 0 | BN107: =IF($O107=$BN$61,$P107,0) -> 0 | BO107: =IF($O107=$BN$61,$R107,0) -> 0 | BP107: =IF($O107=$BP$61,$P107,0) -> 0 | BQ107: =IF($O107=$BP$61,$R107,0) -> 0 | BR107: =IF($O107=$BR$61,$P107,0) -> 0 | BS107: =IF($O107=$BR$61,$R107,0) -> 0 | BT107: =IF($O107=$BT$61,$P107,0) -> 0 | BU107: =IF($O107=$BT$61,$R107,0) -> 0 | BV107: =IF($O107=$BV$61,$P107,0) -> 0 | BW107: =IF($O107=$BV$61,$R107,0) -> 0 | BX107: =IF($O107=$BX$61,$P107,0) -> 0 | BY107: =IF($O107=$BX$61,$R107,0) -> 0 | BZ107: =IF($O107=$BZ$61,$P107,0) -> 0 | CA107: =IF($O107=$BZ$61,$R107,0) -> 0 | CB107: =IF($O107=$CB$61,$P107,0) -> 0 | CC107: =IF($O107=$CB$61,$R107,0) -> 0 | CD107: =IF($O107=$CD$61,$P107,0) -> 0 | CE107: =IF($O107=$CD$61,$R107,0) -> 0 | CF107: =IF($O107=$CF$61,$P107,0) -> 0 | CG107: =IF($O107=$CF$61,$R107,0) -> 0 | CH107: =IF($O107=$CH$61,$P107,0) -> 0 | CI107: =IF($O107=$CH$61,$R107,0) -> 0 | CJ107: =IF($O107=$CJ$61,$P107,0) -> 0 | CK107: =IF($O107=$CJ$61,$R107,0) -> 0 | CL107: =IF($O107=$CL$61,$P107,0) -> 0 | CM107: =IF($O107=$CL$61,$R107,0) -> 0 | CN107: =IF($O107=$CN$61,$P107,0) -> 0 | CO107: =IF($O107=$CN$61,$R107,0) -> 0 | CP107: =IF($O107=$CP$61,$P107,0) -> 0 | CQ107: =IF($O107=$CP$61,$R107,0) -> 0 | CR107: =IF($O107=$CR$61,$P107,0) -> 0 | CS107: =IF($O107=$CR$61,$R107,0) -> 0 | CT107: =IF($O107=$CT$61,$P107,0) -> 0 | CU107: =IF($O107=$CT$61,$R107,0) -> 0 | CV107: =IF($O107=$CV$61,$P107,0) -> 0 | CW107: =IF($O107=$CV$61,$R107,0) -> 0 | CX107: =IF($O107=$CX$61,$P107,0) -> 0 | CY107: =IF($O107=$CX$61,$R107,0) -> 0
C108: 小 計 | H108: =SUM(H89:H107) -> 0 | K108: 計 | N108: =L108*M108 -> 0 | R108: ﾍﾟｰｼﾞ計 | S108: =SUM(S88:S107) -> 0 | T108: =IF(H108<>0,1-(S108/H108),0) -> 0 | V108: =IF($K108=$V$61,$L108,0) -> 0 | W108: =IF($K108=$V$61,$N108,0) -> 0 | X108: =IF($K108=$X$61,$L108,0) -> 0 | Y108: =IF($K108=$X$61,$N108,0) -> 0 | Z108: =IF($K108=$Z$61,$L108,0) -> 0 | AA108: =IF($K108=$Z$61,$N108,0) -> 0 | AB108: =IF($K108=$AB$61,$L108,0) -> 0 | AC108: =IF($K108=$AB$61,$N108,0) -> 0 | AD108: =IF($K108=$AD$61,$L108,0) -> 0 | AE108: =IF($K108=$AD$61,$N108,0) -> 0 | AF108: =IF($K108=$AF$61,$L108,0) -> 0 | AG108: =IF($K108=$AF$61,$N108,0) -> 0 | AH108: =IF($K108=$AH$61,$L108,0) -> 0 | AI108: =IF($K108=$AH$61,$N108,0) -> 0 | AJ108: =IF($K108=$AJ$61,$L108,0) -> 0 | AK108: =IF($K108=$AJ$61,$N108,0) -> 0 | AL108: =IF($K108=$AL$61,$L108,0) -> 0 | AM108: =IF($K108=$AL$61,$N108,0) -> 0 | AN108: =IF($K108=$AN$61,$L108,0) -> 0 | AO108: =IF($K108=$AN$61,$N108,0) -> 0 | AP108: =IF($K108=$AP$61,$L108,0) -> 0 | AQ108: =IF($K108=$AP$61,$N108,0) -> 0 | AR108: =IF($K108=$AR$61,$L108,0) -> 0 | AS108: =IF($K108=$AR$61,$N108,0) -> 0 | AT108: =IF($K108=$AT$61,$L108,0) -> 0 | AU108: =IF($K108=$AT$61,$N108,0) -> 0 | AV108: =IF($K108=$AV$61,$L108,0) -> 0 | AW108: =IF($K108=$AV$61,$N108,0) -> 0 | AX108: =IF($K108=$AX$61,$L108,0) -> 0 | AY108: =IF($K108=$AX$61,$N108,0) -> 0 | AZ108: =IF($K108=$AZ$61,$L108,0) -> 0 | BA108: =IF($K108=$AZ$61,$N108,0) -> 0 | BB108: =IF($K108=$BB$61,$L108,0) -> 0 | BC108: =IF($K108=$BB$61,$N108,0) -> 0 | BD108: =IF($O108=$BD$61,$P108,0) -> 0 | BE108: =IF($O108=$BD$61,$R108,0) -> 0 | BF108: =IF($O108=$BF$61,$P108,0) -> 0 | BG108: =IF($O108=$BF$61,$R108,0) -> 0 | BH108: =IF($O108=$BH$61,$P108,0) -> 0 | BI108: =IF($O108=$BH$61,$R108,0) -> 0 | BJ108: =IF($O108=$BJ$61,$P108,0) -> 0 | BK108: =IF($O108=$BJ$61,$R108,0) -> 0 | BL108: =IF($O108=$BL$61,$P108,0) -> 0 | BM108: =IF($O108=$BL$61,$R108,0) -> 0 | BN108: =IF($O108=$BN$61,$P108,0) -> 0 | BO108: =IF($O108=$BN$61,$R108,0) -> 0 | BP108: =IF($O108=$BP$61,$P108,0) -> 0 | BQ108: =IF($O108=$BP$61,$R108,0) -> 0 | BR108: =IF($O108=$BR$61,$P108,0) -> 0 | BS108: =IF($O108=$BR$61,$R108,0) -> 0 | BT108: =IF($O108=$BT$61,$P108,0) -> 0 | BU108: =IF($O108=$BT$61,$R108,0) -> 0 | BV108: =IF($O108=$BV$61,$P108,0) -> 0 | BW108: =IF($O108=$BV$61,$R108,0) -> 0 | BX108: =IF($O108=$BX$61,$P108,0) -> 0 | BY108: =IF($O108=$BX$61,$R108,0) -> 0 | BZ108: =IF($O108=$BZ$61,$P108,0) -> 0 | CA108: =IF($O108=$BZ$61,$R108,0) -> 0 | CB108: =IF($O108=$CB$61,$P108,0) -> 0 | CC108: =IF($O108=$CB$61,$R108,0) -> 0 | CD108: =IF($O108=$CD$61,$P108,0) -> 0 | CE108: =IF($O108=$CD$61,$R108,0) -> 0 | CF108: =IF($O108=$CF$61,$P108,0) -> 0 | CG108: =IF($O108=$CF$61,$R108,0) -> 0 | CH108: =IF($O108=$CH$61,$P108,0) -> 0 | CI108: =IF($O108=$CH$61,$R108,0) -> 0 | CJ108: =IF($O108=$CJ$61,$P108,0) -> 0 | CK108: =IF($O108=$CJ$61,$R108,0) -> 0 | CL108: =IF($O108=$CL$61,$P108,0) -> 0 | CM108: =IF($O108=$CL$61,$R108,0) -> 0 | CN108: =IF($O108=$CN$61,$P108,0) -> 0 | CO108: =IF($O108=$CN$61,$R108,0) -> 0 | CP108: =IF($O108=$CP$61,$P108,0) -> 0 | CQ108: =IF($O108=$CP$61,$R108,0) -> 0 | CR108: =IF($O108=$CR$61,$P108,0) -> 0 | CS108: =IF($O108=$CR$61,$R108,0) -> 0 | CT108: =IF($O108=$CT$61,$P108,0) -> 0 | CU108: =IF($O108=$CT$61,$R108,0) -> 0 | CV108: =IF($O108=$CV$61,$P108,0) -> 0 | CW108: =IF($O108=$CV$61,$R108,0) -> 0 | CX108: =IF($O108=$CX$61,$P108,0) -> 0 | CY108: =IF($O108=$CX$61,$R108,0) -> 0
N109: =L109*M109 -> 0 | R109: =P109*Q109 -> 0 | S109: =N109+R109 -> 0 | T109: =IF(H109<>0,1-(S109/H109),0) -> 0 | V109: =IF($K109=$V$61,$L109,0) -> 0 | W109: =IF($K109=$V$61,$N109,0) -> 0 | X109: =IF($K109=$X$61,$L109,0) -> 0 | Y109: =IF($K109=$X$61,$N109,0) -> 0 | Z109: =IF($K109=$Z$61,$L109,0) -> 0 | AA109: =IF($K109=$Z$61,$N109,0) -> 0 | AB109: =IF($K109=$AB$61,$L109,0) -> 0 | AC109: =IF($K109=$AB$61,$N109,0) -> 0 | AD109: =IF($K109=$AD$61,$L109,0) -> 0 | AE109: =IF($K109=$AD$61,$N109,0) -> 0 | AF109: =IF($K109=$AF$61,$L109,0) -> 0 | AG109: =IF($K109=$AF$61,$N109,0) -> 0 | AH109: =IF($K109=$AH$61,$L109,0) -> 0 | AI109: =IF($K109=$AH$61,$N109,0) -> 0 | AJ109: =IF($K109=$AJ$61,$L109,0) -> 0 | AK109: =IF($K109=$AJ$61,$N109,0) -> 0 | AL109: =IF($K109=$AL$61,$L109,0) -> 0 | AM109: =IF($K109=$AL$61,$N109,0) -> 0 | AN109: =IF($K109=$AN$61,$L109,0) -> 0 | AO109: =IF($K109=$AN$61,$N109,0) -> 0 | AP109: =IF($K109=$AP$61,$L109,0) -> 0 | AQ109: =IF($K109=$AP$61,$N109,0) -> 0 | AR109: =IF($K109=$AR$61,$L109,0) -> 0 | AS109: =IF($K109=$AR$61,$N109,0) -> 0 | AT109: =IF($K109=$AT$61,$L109,0) -> 0 | AU109: =IF($K109=$AT$61,$N109,0) -> 0 | AV109: =IF($K109=$AV$61,$L109,0) -> 0 | AW109: =IF($K109=$AV$61,$N109,0) -> 0 | AX109: =IF($K109=$AX$61,$L109,0) -> 0 | AY109: =IF($K109=$AX$61,$N109,0) -> 0 | AZ109: =IF($K109=$AZ$61,$L109,0) -> 0 | BA109: =IF($K109=$AZ$61,$N109,0) -> 0 | BB109: =IF($K109=$BB$61,$L109,0) -> 0 | BC109: =IF($K109=$BB$61,$N109,0) -> 0 | BD109: =IF($O109=$BD$61,$P109,0) -> 0 | BE109: =IF($O109=$BD$61,$R109,0) -> 0 | BF109: =IF($O109=$BF$61,$P109,0) -> 0 | BG109: =IF($O109=$BF$61,$R109,0) -> 0 | BH109: =IF($O109=$BH$61,$P109,0) -> 0 | BI109: =IF($O109=$BH$61,$R109,0) -> 0 | BJ109: =IF($O109=$BJ$61,$P109,0) -> 0 | BK109: =IF($O109=$BJ$61,$R109,0) -> 0 | BL109: =IF($O109=$BL$61,$P109,0) -> 0 | BM109: =IF($O109=$BL$61,$R109,0) -> 0 | BN109: =IF($O109=$BN$61,$P109,0) -> 0 | BO109: =IF($O109=$BN$61,$R109,0) -> 0 | BP109: =IF($O109=$BP$61,$P109,0) -> 0 | BQ109: =IF($O109=$BP$61,$R109,0) -> 0 | BR109: =IF($O109=$BR$61,$P109,0) -> 0 | BS109: =IF($O109=$BR$61,$R109,0) -> 0 | BT109: =IF($O109=$BT$61,$P109,0) -> 0 | BU109: =IF($O109=$BT$61,$R109,0) -> 0 | BV109: =IF($O109=$BV$61,$P109,0) -> 0 | BW109: =IF($O109=$BV$61,$R109,0) -> 0 | BX109: =IF($O109=$BX$61,$P109,0) -> 0 | BY109: =IF($O109=$BX$61,$R109,0) -> 0 | BZ109: =IF($O109=$BZ$61,$P109,0) -> 0 | CA109: =IF($O109=$BZ$61,$R109,0) -> 0 | CB109: =IF($O109=$CB$61,$P109,0) -> 0 | CC109: =IF($O109=$CB$61,$R109,0) -> 0 | CD109: =IF($O109=$CD$61,$P109,0) -> 0 | CE109: =IF($O109=$CD$61,$R109,0) -> 0 | CF109: =IF($O109=$CF$61,$P109,0) -> 0 | CG109: =IF($O109=$CF$61,$R109,0) -> 0 | CH109: =IF($O109=$CH$61,$P109,0) -> 0 | CI109: =IF($O109=$CH$61,$R109,0) -> 0 | CJ109: =IF($O109=$CJ$61,$P109,0) -> 0 | CK109: =IF($O109=$CJ$61,$R109,0) -> 0 | CL109: =IF($O109=$CL$61,$P109,0) -> 0 | CM109: =IF($O109=$CL$61,$R109,0) -> 0 | CN109: =IF($O109=$CN$61,$P109,0) -> 0 | CO109: =IF($O109=$CN$61,$R109,0) -> 0 | CP109: =IF($O109=$CP$61,$P109,0) -> 0 | CQ109: =IF($O109=$CP$61,$R109,0) -> 0 | CR109: =IF($O109=$CR$61,$P109,0) -> 0 | CS109: =IF($O109=$CR$61,$R109,0) -> 0 | CT109: =IF($O109=$CT$61,$P109,0) -> 0 | CU109: =IF($O109=$CT$61,$R109,0) -> 0 | CV109: =IF($O109=$CV$61,$P109,0) -> 0 | CW109: =IF($O109=$CV$61,$R109,0) -> 0 | CX109: =IF($O109=$CX$61,$P109,0) -> 0 | CY109: =IF($O109=$CX$61,$R109,0) -> 0
I110: ラグズ建築 | N110: =L110*M110 -> 0 | R110: =P110*Q110 -> 0 | S110: =N110+R110 -> 0 | V110: =IF($K110=$V$61,$L110,0) -> 0 | W110: =IF($K110=$V$61,$N110,0) -> 0 | X110: =IF($K110=$X$61,$L110,0) -> 0 | Y110: =IF($K110=$X$61,$N110,0) -> 0 | Z110: =IF($K110=$Z$61,$L110,0) -> 0 | AA110: =IF($K110=$Z$61,$N110,0) -> 0 | AB110: =IF($K110=$AB$61,$L110,0) -> 0 | AC110: =IF($K110=$AB$61,$N110,0) -> 0 | AD110: =IF($K110=$AD$61,$L110,0) -> 0 | AE110: =IF($K110=$AD$61,$N110,0) -> 0 | AF110: =IF($K110=$AF$61,$L110,0) -> 0 | AG110: =IF($K110=$AF$61,$N110,0) -> 0 | AH110: =IF($K110=$AH$61,$L110,0) -> 0 | AI110: =IF($K110=$AH$61,$N110,0) -> 0 | AJ110: =IF($K110=$AJ$61,$L110,0) -> 0 | AK110: =IF($K110=$AJ$61,$N110,0) -> 0 | AL110: =IF($K110=$AL$61,$L110,0) -> 0 | AM110: =IF($K110=$AL$61,$N110,0) -> 0 | AN110: =IF($K110=$AN$61,$L110,0) -> 0 | AO110: =IF($K110=$AN$61,$N110,0) -> 0 | AP110: =IF($K110=$AP$61,$L110,0) -> 0 | AQ110: =IF($K110=$AP$61,$N110,0) -> 0 | AR110: =IF($K110=$AR$61,$L110,0) -> 0 | AS110: =IF($K110=$AR$61,$N110,0) -> 0 | AT110: =IF($K110=$AT$61,$L110,0) -> 0 | AU110: =IF($K110=$AT$61,$N110,0) -> 0 | AV110: =IF($K110=$AV$61,$L110,0) -> 0 | AW110: =IF($K110=$AV$61,$N110,0) -> 0 | AX110: =IF($K110=$AX$61,$L110,0) -> 0 | AY110: =IF($K110=$AX$61,$N110,0) -> 0 | AZ110: =IF($K110=$AZ$61,$L110,0) -> 0 | BA110: =IF($K110=$AZ$61,$N110,0) -> 0 | BB110: =IF($K110=$BB$61,$L110,0) -> 0 | BC110: =IF($K110=$BB$61,$N110,0) -> 0 | BD110: =IF($O110=$BD$61,$P110,0) -> 0 | BE110: =IF($O110=$BD$61,$R110,0) -> 0 | BF110: =IF($O110=$BF$61,$P110,0) -> 0 | BG110: =IF($O110=$BF$61,$R110,0) -> 0 | BH110: =IF($O110=$BH$61,$P110,0) -> 0 | BI110: =IF($O110=$BH$61,$R110,0) -> 0 | BJ110: =IF($O110=$BJ$61,$P110,0) -> 0 | BK110: =IF($O110=$BJ$61,$R110,0) -> 0 | BL110: =IF($O110=$BL$61,$P110,0) -> 0 | BM110: =IF($O110=$BL$61,$R110,0) -> 0 | BN110: =IF($O110=$BN$61,$P110,0) -> 0 | BO110: =IF($O110=$BN$61,$R110,0) -> 0 | BP110: =IF($O110=$BP$61,$P110,0) -> 0 | BQ110: =IF($O110=$BP$61,$R110,0) -> 0 | BR110: =IF($O110=$BR$61,$P110,0) -> 0 | BS110: =IF($O110=$BR$61,$R110,0) -> 0 | BT110: =IF($O110=$BT$61,$P110,0) -> 0 | BU110: =IF($O110=$BT$61,$R110,0) -> 0 | BV110: =IF($O110=$BV$61,$P110,0) -> 0 | BW110: =IF($O110=$BV$61,$R110,0) -> 0 | BX110: =IF($O110=$BX$61,$P110,0) -> 0 | BY110: =IF($O110=$BX$61,$R110,0) -> 0 | BZ110: =IF($O110=$BZ$61,$P110,0) -> 0 | CA110: =IF($O110=$BZ$61,$R110,0) -> 0 | CB110: =IF($O110=$CB$61,$P110,0) -> 0 | CC110: =IF($O110=$CB$61,$R110,0) -> 0 | CD110: =IF($O110=$CD$61,$P110,0) -> 0 | CE110: =IF($O110=$CD$61,$R110,0) -> 0 | CF110: =IF($O110=$CF$61,$P110,0) -> 0 | CG110: =IF($O110=$CF$61,$R110,0) -> 0 | CH110: =IF($O110=$CH$61,$P110,0) -> 0 | CI110: =IF($O110=$CH$61,$R110,0) -> 0 | CJ110: =IF($O110=$CJ$61,$P110,0) -> 0 | CK110: =IF($O110=$CJ$61,$R110,0) -> 0 | CL110: =IF($O110=$CL$61,$P110,0) -> 0 | CM110: =IF($O110=$CL$61,$R110,0) -> 0 | CN110: =IF($O110=$CN$61,$P110,0) -> 0 | CO110: =IF($O110=$CN$61,$R110,0) -> 0 | CP110: =IF($O110=$CP$61,$P110,0) -> 0 | CQ110: =IF($O110=$CP$61,$R110,0) -> 0 | CR110: =IF($O110=$CR$61,$P110,0) -> 0 | CS110: =IF($O110=$CR$61,$R110,0) -> 0 | CT110: =IF($O110=$CT$61,$P110,0) -> 0 | CU110: =IF($O110=$CT$61,$R110,0) -> 0 | CV110: =IF($O110=$CV$61,$P110,0) -> 0 | CW110: =IF($O110=$CV$61,$R110,0) -> 0 | CX110: =IF($O110=$CX$61,$P110,0) -> 0 | CY110: =IF($O110=$CX$61,$R110,0) -> 0
A111: =A33 -> 0 | B111: =B33 -> 0 | E111: 内 訳 明 細 書 | J111: 4 | K111: 日付 | N111: =L111*M111 -> 0 | R111: =P111*Q111 -> 0 | S111: =N111+R111 -> 0 | V111: =IF($K111=$V$61,$L111,0) -> 0 | W111: =IF($K111=$V$61,$N111,0) -> 0 | X111: =IF($K111=$X$61,$L111,0) -> 0 | Y111: =IF($K111=$X$61,$N111,0) -> 0 | Z111: =IF($K111=$Z$61,$L111,0) -> 0 | AA111: =IF($K111=$Z$61,$N111,0) -> 0 | AB111: =IF($K111=$AB$61,$L111,0) -> 0 | AC111: =IF($K111=$AB$61,$N111,0) -> 0 | AD111: =IF($K111=$AD$61,$L111,0) -> 0 | AE111: =IF($K111=$AD$61,$N111,0) -> 0 | AF111: =IF($K111=$AF$61,$L111,0) -> 0 | AG111: =IF($K111=$AF$61,$N111,0) -> 0 | AH111: =IF($K111=$AH$61,$L111,0) -> 0 | AI111: =IF($K111=$AH$61,$N111,0) -> 0 | AJ111: =IF($K111=$AJ$61,$L111,0) -> 0 | AK111: =IF($K111=$AJ$61,$N111,0) -> 0 | AL111: =IF($K111=$AL$61,$L111,0) -> 0 | AM111: =IF($K111=$AL$61,$N111,0) -> 0 | AN111: =IF($K111=$AN$61,$L111,0) -> 0 | AO111: =IF($K111=$AN$61,$N111,0) -> 0 | AP111: =IF($K111=$AP$61,$L111,0) -> 0 | AQ111: =IF($K111=$AP$61,$N111,0) -> 0 | AR111: =IF($K111=$AR$61,$L111,0) -> 0 | AS111: =IF($K111=$AR$61,$N111,0) -> 0 | AT111: =IF($K111=$AT$61,$L111,0) -> 0 | AU111: =IF($K111=$AT$61,$N111,0) -> 0 | AV111: =IF($K111=$AV$61,$L111,0) -> 0 | AW111: =IF($K111=$AV$61,$N111,0) -> 0 | AX111: =IF($K111=$AX$61,$L111,0) -> 0 | AY111: =IF($K111=$AX$61,$N111,0) -> 0 | AZ111: =IF($K111=$AZ$61,$L111,0) -> 0 | BA111: =IF($K111=$AZ$61,$N111,0) -> 0 | BB111: =IF($K111=$BB$61,$L111,0) -> 0 | BC111: =IF($K111=$BB$61,$N111,0) -> 0 | BD111: =IF($O111=$BD$61,$P111,0) -> 0 | BE111: =IF($O111=$BD$61,$R111,0) -> 0 | BF111: =IF($O111=$BF$61,$P111,0) -> 0 | BG111: =IF($O111=$BF$61,$R111,0) -> 0 | BH111: =IF($O111=$BH$61,$P111,0) -> 0 | BI111: =IF($O111=$BH$61,$R111,0) -> 0 | BJ111: =IF($O111=$BJ$61,$P111,0) -> 0 | BK111: =IF($O111=$BJ$61,$R111,0) -> 0 | BL111: =IF($O111=$BL$61,$P111,0) -> 0 | BM111: =IF($O111=$BL$61,$R111,0) -> 0 | BN111: =IF($O111=$BN$61,$P111,0) -> 0 | BO111: =IF($O111=$BN$61,$R111,0) -> 0 | BP111: =IF($O111=$BP$61,$P111,0) -> 0 | BQ111: =IF($O111=$BP$61,$R111,0) -> 0 | BR111: =IF($O111=$BR$61,$P111,0) -> 0 | BS111: =IF($O111=$BR$61,$R111,0) -> 0 | BT111: =IF($O111=$BT$61,$P111,0) -> 0 | BU111: =IF($O111=$BT$61,$R111,0) -> 0 | BV111: =IF($O111=$BV$61,$P111,0) -> 0 | BW111: =IF($O111=$BV$61,$R111,0) -> 0 | BX111: =IF($O111=$BX$61,$P111,0) -> 0 | BY111: =IF($O111=$BX$61,$R111,0) -> 0 | BZ111: =IF($O111=$BZ$61,$P111,0) -> 0 | CA111: =IF($O111=$BZ$61,$R111,0) -> 0 | CB111: =IF($O111=$CB$61,$P111,0) -> 0 | CC111: =IF($O111=$CB$61,$R111,0) -> 0 | CD111: =IF($O111=$CD$61,$P111,0) -> 0 | CE111: =IF($O111=$CD$61,$R111,0) -> 0 | CF111: =IF($O111=$CF$61,$P111,0) -> 0 | CG111: =IF($O111=$CF$61,$R111,0) -> 0 | CH111: =IF($O111=$CH$61,$P111,0) -> 0 | CI111: =IF($O111=$CH$61,$R111,0) -> 0 | CJ111: =IF($O111=$CJ$61,$P111,0) -> 0 | CK111: =IF($O111=$CJ$61,$R111,0) -> 0 | CL111: =IF($O111=$CL$61,$P111,0) -> 0 | CM111: =IF($O111=$CL$61,$R111,0) -> 0 | CN111: =IF($O111=$CN$61,$P111,0) -> 0 | CO111: =IF($O111=$CN$61,$R111,0) -> 0 | CP111: =IF($O111=$CP$61,$P111,0) -> 0 | CQ111: =IF($O111=$CP$61,$R111,0) -> 0 | CR111: =IF($O111=$CR$61,$P111,0) -> 0 | CS111: =IF($O111=$CR$61,$R111,0) -> 0 | CT111: =IF($O111=$CT$61,$P111,0) -> 0 | CU111: =IF($O111=$CT$61,$R111,0) -> 0 | CV111: =IF($O111=$CV$61,$P111,0) -> 0 | CW111: =IF($O111=$CV$61,$R111,0) -> 0 | CX111: =IF($O111=$CX$61,$P111,0) -> 0 | CY111: =IF($O111=$CX$61,$R111,0) -> 0
N112: =L112*M112 -> 0 | R112: =P112*Q112 -> 0 | S112: =N112+R112 -> 0 | V112: =IF($K112=$V$61,$L112,0) -> 0 | W112: =IF($K112=$V$61,$N112,0) -> 0 | X112: =IF($K112=$X$61,$L112,0) -> 0 | Y112: =IF($K112=$X$61,$N112,0) -> 0 | Z112: =IF($K112=$Z$61,$L112,0) -> 0 | AA112: =IF($K112=$Z$61,$N112,0) -> 0 | AB112: =IF($K112=$AB$61,$L112,0) -> 0 | AC112: =IF($K112=$AB$61,$N112,0) -> 0 | AD112: =IF($K112=$AD$61,$L112,0) -> 0 | AE112: =IF($K112=$AD$61,$N112,0) -> 0 | AF112: =IF($K112=$AF$61,$L112,0) -> 0 | AG112: =IF($K112=$AF$61,$N112,0) -> 0 | AH112: =IF($K112=$AH$61,$L112,0) -> 0 | AI112: =IF($K112=$AH$61,$N112,0) -> 0 | AJ112: =IF($K112=$AJ$61,$L112,0) -> 0 | AK112: =IF($K112=$AJ$61,$N112,0) -> 0 | AL112: =IF($K112=$AL$61,$L112,0) -> 0 | AM112: =IF($K112=$AL$61,$N112,0) -> 0 | AN112: =IF($K112=$AN$61,$L112,0) -> 0 | AO112: =IF($K112=$AN$61,$N112,0) -> 0 | AP112: =IF($K112=$AP$61,$L112,0) -> 0 | AQ112: =IF($K112=$AP$61,$N112,0) -> 0 | AR112: =IF($K112=$AR$61,$L112,0) -> 0 | AS112: =IF($K112=$AR$61,$N112,0) -> 0 | AT112: =IF($K112=$AT$61,$L112,0) -> 0 | AU112: =IF($K112=$AT$61,$N112,0) -> 0 | AV112: =IF($K112=$AV$61,$L112,0) -> 0 | AW112: =IF($K112=$AV$61,$N112,0) -> 0 | AX112: =IF($K112=$AX$61,$L112,0) -> 0 | AY112: =IF($K112=$AX$61,$N112,0) -> 0 | AZ112: =IF($K112=$AZ$61,$L112,0) -> 0 | BA112: =IF($K112=$AZ$61,$N112,0) -> 0 | BB112: =IF($K112=$BB$61,$L112,0) -> 0 | BC112: =IF($K112=$BB$61,$N112,0) -> 0 | BD112: =IF($O112=$BD$61,$P112,0) -> 0 | BE112: =IF($O112=$BD$61,$R112,0) -> 0 | BF112: =IF($O112=$BF$61,$P112,0) -> 0 | BG112: =IF($O112=$BF$61,$R112,0) -> 0 | BH112: =IF($O112=$BH$61,$P112,0) -> 0 | BI112: =IF($O112=$BH$61,$R112,0) -> 0 | BJ112: =IF($O112=$BJ$61,$P112,0) -> 0 | BK112: =IF($O112=$BJ$61,$R112,0) -> 0 | BL112: =IF($O112=$BL$61,$P112,0) -> 0 | BM112: =IF($O112=$BL$61,$R112,0) -> 0 | BN112: =IF($O112=$BN$61,$P112,0) -> 0 | BO112: =IF($O112=$BN$61,$R112,0) -> 0 | BP112: =IF($O112=$BP$61,$P112,0) -> 0 | BQ112: =IF($O112=$BP$61,$R112,0) -> 0 | BR112: =IF($O112=$BR$61,$P112,0) -> 0 | BS112: =IF($O112=$BR$61,$R112,0) -> 0 | BT112: =IF($O112=$BT$61,$P112,0) -> 0 | BU112: =IF($O112=$BT$61,$R112,0) -> 0 | BV112: =IF($O112=$BV$61,$P112,0) -> 0 | BW112: =IF($O112=$BV$61,$R112,0) -> 0 | BX112: =IF($O112=$BX$61,$P112,0) -> 0 | BY112: =IF($O112=$BX$61,$R112,0) -> 0 | BZ112: =IF($O112=$BZ$61,$P112,0) -> 0 | CA112: =IF($O112=$BZ$61,$R112,0) -> 0 | CB112: =IF($O112=$CB$61,$P112,0) -> 0 | CC112: =IF($O112=$CB$61,$R112,0) -> 0 | CD112: =IF($O112=$CD$61,$P112,0) -> 0 | CE112: =IF($O112=$CD$61,$R112,0) -> 0 | CF112: =IF($O112=$CF$61,$P112,0) -> 0 | CG112: =IF($O112=$CF$61,$R112,0) -> 0 | CH112: =IF($O112=$CH$61,$P112,0) -> 0 | CI112: =IF($O112=$CH$61,$R112,0) -> 0 | CJ112: =IF($O112=$CJ$61,$P112,0) -> 0 | CK112: =IF($O112=$CJ$61,$R112,0) -> 0 | CL112: =IF($O112=$CL$61,$P112,0) -> 0 | CM112: =IF($O112=$CL$61,$R112,0) -> 0 | CN112: =IF($O112=$CN$61,$P112,0) -> 0 | CO112: =IF($O112=$CN$61,$R112,0) -> 0 | CP112: =IF($O112=$CP$61,$P112,0) -> 0 | CQ112: =IF($O112=$CP$61,$R112,0) -> 0 | CR112: =IF($O112=$CR$61,$P112,0) -> 0 | CS112: =IF($O112=$CR$61,$R112,0) -> 0 | CT112: =IF($O112=$CT$61,$P112,0) -> 0 | CU112: =IF($O112=$CT$61,$R112,0) -> 0 | CV112: =IF($O112=$CV$61,$P112,0) -> 0 | CW112: =IF($O112=$CV$61,$R112,0) -> 0 | CX112: =IF($O112=$CX$61,$P112,0) -> 0 | CY112: =IF($O112=$CX$61,$R112,0) -> 0
A113: 名 称 | E113: 数量 | F113: 呼称 | G113: 単 価 | H113: 金 額 | I113: 定価 | J113: 備 考 | K113: 職人 | L113: 人工 | M113: 人当 | N113: 費用① | O113: 材料 | P113: 数量 | Q113: 単価 | R113: 費用② | S113: 原価 | T113: 粗利率 | V113: =IF($K113=$V$61,$L113,0) -> 0 | W113: =IF($K113=$V$61,$N113,0) -> 0 | X113: =IF($K113=$X$61,$L113,0) -> 0 | Y113: =IF($K113=$X$61,$N113,0) -> 0 | Z113: =IF($K113=$Z$61,$L113,0) -> 0 | AA113: =IF($K113=$Z$61,$N113,0) -> 0 | AB113: =IF($K113=$AB$61,$L113,0) -> 0 | AC113: =IF($K113=$AB$61,$N113,0) -> 0 | AD113: =IF($K113=$AD$61,$L113,0) -> 0 | AE113: =IF($K113=$AD$61,$N113,0) -> 0 | AF113: =IF($K113=$AF$61,$L113,0) -> 0 | AG113: =IF($K113=$AF$61,$N113,0) -> 0 | AH113: =IF($K113=$AH$61,$L113,0) -> 0 | AI113: =IF($K113=$AH$61,$N113,0) -> 0 | AJ113: =IF($K113=$AJ$61,$L113,0) -> 0 | AK113: =IF($K113=$AJ$61,$N113,0) -> 0 | AL113: =IF($K113=$AL$61,$L113,0) -> 0 | AM113: =IF($K113=$AL$61,$N113,0) -> 0 | AN113: =IF($K113=$AN$61,$L113,0) -> 0 | AO113: =IF($K113=$AN$61,$N113,0) -> 0 | AP113: =IF($K113=$AP$61,$L113,0) -> 0 | AQ113: =IF($K113=$AP$61,$N113,0) -> 0 | AR113: =IF($K113=$AR$61,$L113,0) -> 0 | AS113: =IF($K113=$AR$61,$N113,0) -> 0 | AT113: =IF($K113=$AT$61,$L113,0) -> 0 | AU113: =IF($K113=$AT$61,$N113,0) -> 0 | AV113: =IF($K113=$AV$61,$L113,0) -> 0 | AW113: =IF($K113=$AV$61,$N113,0) -> 0 | AX113: =IF($K113=$AX$61,$L113,0) -> 0 | AY113: =IF($K113=$AX$61,$N113,0) -> 0 | AZ113: =IF($K113=$AZ$61,$L113,0) -> 0 | BA113: =IF($K113=$AZ$61,$N113,0) -> 0 | BB113: =IF($K113=$BB$61,$L113,0) -> 0 | BC113: =IF($K113=$BB$61,$N113,0) -> 0 | BD113: =IF($O113=$BD$61,$P113,0) -> 0 | BE113: =IF($O113=$BD$61,$R113,0) -> 0 | BF113: =IF($O113=$BF$61,$P113,0) -> 0 | BG113: =IF($O113=$BF$61,$R113,0) -> 0 | BH113: =IF($O113=$BH$61,$P113,0) -> 0 | BI113: =IF($O113=$BH$61,$R113,0) -> 0 | BJ113: =IF($O113=$BJ$61,$P113,0) -> 0 | BK113: =IF($O113=$BJ$61,$R113,0) -> 0 | BL113: =IF($O113=$BL$61,$P113,0) -> 0 | BM113: =IF($O113=$BL$61,$R113,0) -> 0 | BN113: =IF($O113=$BN$61,$P113,0) -> 0 | BO113: =IF($O113=$BN$61,$R113,0) -> 0 | BP113: =IF($O113=$BP$61,$P113,0) -> 0 | BQ113: =IF($O113=$BP$61,$R113,0) -> 0 | BR113: =IF($O113=$BR$61,$P113,0) -> 0 | BS113: =IF($O113=$BR$61,$R113,0) -> 0 | BT113: =IF($O113=$BT$61,$P113,0) -> 0 | BU113: =IF($O113=$BT$61,$R113,0) -> 0 | BV113: =IF($O113=$BV$61,$P113,0) -> 0 | BW113: =IF($O113=$BV$61,$R113,0) -> 0 | BX113: =IF($O113=$BX$61,$P113,0) -> 0 | BY113: =IF($O113=$BX$61,$R113,0) -> 0 | BZ113: =IF($O113=$BZ$61,$P113,0) -> 0 | CA113: =IF($O113=$BZ$61,$R113,0) -> 0 | CB113: =IF($O113=$CB$61,$P113,0) -> 0 | CC113: =IF($O113=$CB$61,$R113,0) -> 0 | CD113: =IF($O113=$CD$61,$P113,0) -> 0 | CE113: =IF($O113=$CD$61,$R113,0) -> 0 | CF113: =IF($O113=$CF$61,$P113,0) -> 0 | CG113: =IF($O113=$CF$61,$R113,0) -> 0 | CH113: =IF($O113=$CH$61,$P113,0) -> 0 | CI113: =IF($O113=$CH$61,$R113,0) -> 0 | CJ113: =IF($O113=$CJ$61,$P113,0) -> 0 | CK113: =IF($O113=$CJ$61,$R113,0) -> 0 | CL113: =IF($O113=$CL$61,$P113,0) -> 0 | CM113: =IF($O113=$CL$61,$R113,0) -> 0 | CN113: =IF($O113=$CN$61,$P113,0) -> 0 | CO113: =IF($O113=$CN$61,$R113,0) -> 0 | CP113: =IF($O113=$CP$61,$P113,0) -> 0 | CQ113: =IF($O113=$CP$61,$R113,0) -> 0 | CR113: =IF($O113=$CR$61,$P113,0) -> 0 | CS113: =IF($O113=$CR$61,$R113,0) -> 0 | CT113: =IF($O113=$CT$61,$P113,0) -> 0 | CU113: =IF($O113=$CT$61,$R113,0) -> 0 | CV113: =IF($O113=$CV$61,$P113,0) -> 0 | CW113: =IF($O113=$CV$61,$R113,0) -> 0 | CX113: =IF($O113=$CX$61,$P113,0) -> 0 | CY113: =IF($O113=$CX$61,$R113,0) -> 0
A114: 3 | B114: =B39 -> 0 | N114: =L114*M114 -> 0 | R114: =Q114*P114 -> 0 | S114: =R114+N114 -> 0 | T114: =IF(H114<>0,1-(S114/H114),0) -> 0 | V114: =IF($K114=$V$61,$L114,0) -> 0 | W114: =IF($K114=$V$61,$N114,0) -> 0 | X114: =IF($K114=$X$61,$L114,0) -> 0 | Y114: =IF($K114=$X$61,$N114,0) -> 0 | Z114: =IF($K114=$Z$61,$L114,0) -> 0 | AA114: =IF($K114=$Z$61,$N114,0) -> 0 | AB114: =IF($K114=$AB$61,$L114,0) -> 0 | AC114: =IF($K114=$AB$61,$N114,0) -> 0 | AD114: =IF($K114=$AD$61,$L114,0) -> 0 | AE114: =IF($K114=$AD$61,$N114,0) -> 0 | AF114: =IF($K114=$AF$61,$L114,0) -> 0 | AG114: =IF($K114=$AF$61,$N114,0) -> 0 | AH114: =IF($K114=$AH$61,$L114,0) -> 0 | AI114: =IF($K114=$AH$61,$N114,0) -> 0 | AJ114: =IF($K114=$AJ$61,$L114,0) -> 0 | AK114: =IF($K114=$AJ$61,$N114,0) -> 0 | AL114: =IF($K114=$AL$61,$L114,0) -> 0 | AM114: =IF($K114=$AL$61,$N114,0) -> 0 | AN114: =IF($K114=$AN$61,$L114,0) -> 0 | AO114: =IF($K114=$AN$61,$N114,0) -> 0 | AP114: =IF($K114=$AP$61,$L114,0) -> 0 | AQ114: =IF($K114=$AP$61,$N114,0) -> 0 | AR114: =IF($K114=$AR$61,$L114,0) -> 0 | AS114: =IF($K114=$AR$61,$N114,0) -> 0 | AT114: =IF($K114=$AT$61,$L114,0) -> 0 | AU114: =IF($K114=$AT$61,$N114,0) -> 0 | AV114: =IF($K114=$AV$61,$L114,0) -> 0 | AW114: =IF($K114=$AV$61,$N114,0) -> 0 | AX114: =IF($K114=$AX$61,$L114,0) -> 0 | AY114: =IF($K114=$AX$61,$N114,0) -> 0 | AZ114: =IF($K114=$AZ$61,$L114,0) -> 0 | BA114: =IF($K114=$AZ$61,$N114,0) -> 0 | BB114: =IF($K114=$BB$61,$L114,0) -> 0 | BC114: =IF($K114=$BB$61,$N114,0) -> 0 | BD114: =IF($O114=$BD$61,$P114,0) -> 0 | BE114: =IF($O114=$BD$61,$R114,0) -> 0 | BF114: =IF($O114=$BF$61,$P114,0) -> 0 | BG114: =IF($O114=$BF$61,$R114,0) -> 0 | BH114: =IF($O114=$BH$61,$P114,0) -> 0 | BI114: =IF($O114=$BH$61,$R114,0) -> 0 | BJ114: =IF($O114=$BJ$61,$P114,0) -> 0 | BK114: =IF($O114=$BJ$61,$R114,0) -> 0 | BL114: =IF($O114=$BL$61,$P114,0) -> 0 | BM114: =IF($O114=$BL$61,$R114,0) -> 0 | BN114: =IF($O114=$BN$61,$P114,0) -> 0 | BO114: =IF($O114=$BN$61,$R114,0) -> 0 | BP114: =IF($O114=$BP$61,$P114,0) -> 0 | BQ114: =IF($O114=$BP$61,$R114,0) -> 0 | BR114: =IF($O114=$BR$61,$P114,0) -> 0 | BS114: =IF($O114=$BR$61,$R114,0) -> 0 | BT114: =IF($O114=$BT$61,$P114,0) -> 0 | BU114: =IF($O114=$BT$61,$R114,0) -> 0 | BV114: =IF($O114=$BV$61,$P114,0) -> 0 | BW114: =IF($O114=$BV$61,$R114,0) -> 0 | BX114: =IF($O114=$BX$61,$P114,0) -> 0 | BY114: =IF($O114=$BX$61,$R114,0) -> 0 | BZ114: =IF($O114=$BZ$61,$P114,0) -> 0 | CA114: =IF($O114=$BZ$61,$R114,0) -> 0 | CB114: =IF($O114=$CB$61,$P114,0) -> 0 | CC114: =IF($O114=$CB$61,$R114,0) -> 0 | CD114: =IF($O114=$CD$61,$P114,0) -> 0 | CE114: =IF($O114=$CD$61,$R114,0) -> 0 | CF114: =IF($O114=$CF$61,$P114,0) -> 0 | CG114: =IF($O114=$CF$61,$R114,0) -> 0 | CH114: =IF($O114=$CH$61,$P114,0) -> 0 | CI114: =IF($O114=$CH$61,$R114,0) -> 0 | CJ114: =IF($O114=$CJ$61,$P114,0) -> 0 | CK114: =IF($O114=$CJ$61,$R114,0) -> 0 | CL114: =IF($O114=$CL$61,$P114,0) -> 0 | CM114: =IF($O114=$CL$61,$R114,0) -> 0 | CN114: =IF($O114=$CN$61,$P114,0) -> 0 | CO114: =IF($O114=$CN$61,$R114,0) -> 0 | CP114: =IF($O114=$CP$61,$P114,0) -> 0 | CQ114: =IF($O114=$CP$61,$R114,0) -> 0 | CR114: =IF($O114=$CR$61,$P114,0) -> 0 | CS114: =IF($O114=$CR$61,$R114,0) -> 0 | CT114: =IF($O114=$CT$61,$P114,0) -> 0 | CU114: =IF($O114=$CT$61,$R114,0) -> 0 | CV114: =IF($O114=$CV$61,$P114,0) -> 0 | CW114: =IF($O114=$CV$61,$R114,0) -> 0 | CX114: =IF($O114=$CX$61,$P114,0) -> 0 | CY114: =IF($O114=$CX$61,$R114,0) -> 0
H115: =S115*1.45 -> 0 | N115: =L115*M115 -> 0 | R115: =Q115*P115 -> 0 | S115: =R115+N115 -> 0 | T115: =IF(H115<>0,1-(S115/H115),0) -> 0 | V115: =IF($K115=$V$61,$L115,0) -> 0 | W115: =IF($K115=$V$61,$N115,0) -> 0 | X115: =IF($K115=$X$61,$L115,0) -> 0 | Y115: =IF($K115=$X$61,$N115,0) -> 0 | Z115: =IF($K115=$Z$61,$L115,0) -> 0 | AA115: =IF($K115=$Z$61,$N115,0) -> 0 | AB115: =IF($K115=$AB$61,$L115,0) -> 0 | AC115: =IF($K115=$AB$61,$N115,0) -> 0 | AD115: =IF($K115=$AD$61,$L115,0) -> 0 | AE115: =IF($K115=$AD$61,$N115,0) -> 0 | AF115: =IF($K115=$AF$61,$L115,0) -> 0 | AG115: =IF($K115=$AF$61,$N115,0) -> 0 | AH115: =IF($K115=$AH$61,$L115,0) -> 0 | AI115: =IF($K115=$AH$61,$N115,0) -> 0 | AJ115: =IF($K115=$AJ$61,$L115,0) -> 0 | AK115: =IF($K115=$AJ$61,$N115,0) -> 0 | AL115: =IF($K115=$AL$61,$L115,0) -> 0 | AM115: =IF($K115=$AL$61,$N115,0) -> 0 | AN115: =IF($K115=$AN$61,$L115,0) -> 0 | AO115: =IF($K115=$AN$61,$N115,0) -> 0 | AP115: =IF($K115=$AP$61,$L115,0) -> 0 | AQ115: =IF($K115=$AP$61,$N115,0) -> 0 | AR115: =IF($K115=$AR$61,$L115,0) -> 0 | AS115: =IF($K115=$AR$61,$N115,0) -> 0 | AT115: =IF($K115=$AT$61,$L115,0) -> 0 | AU115: =IF($K115=$AT$61,$N115,0) -> 0 | AV115: =IF($K115=$AV$61,$L115,0) -> 0 | AW115: =IF($K115=$AV$61,$N115,0) -> 0 | AX115: =IF($K115=$AX$61,$L115,0) -> 0 | AY115: =IF($K115=$AX$61,$N115,0) -> 0 | AZ115: =IF($K115=$AZ$61,$L115,0) -> 0 | BA115: =IF($K115=$AZ$61,$N115,0) -> 0 | BB115: =IF($K115=$BB$61,$L115,0) -> 0 | BC115: =IF($K115=$BB$61,$N115,0) -> 0 | BD115: =IF($O115=$BD$61,$P115,0) -> 0 | BE115: =IF($O115=$BD$61,$R115,0) -> 0 | BF115: =IF($O115=$BF$61,$P115,0) -> 0 | BG115: =IF($O115=$BF$61,$R115,0) -> 0 | BH115: =IF($O115=$BH$61,$P115,0) -> 0 | BI115: =IF($O115=$BH$61,$R115,0) -> 0 | BJ115: =IF($O115=$BJ$61,$P115,0) -> 0 | BK115: =IF($O115=$BJ$61,$R115,0) -> 0 | BL115: =IF($O115=$BL$61,$P115,0) -> 0 | BM115: =IF($O115=$BL$61,$R115,0) -> 0 | BN115: =IF($O115=$BN$61,$P115,0) -> 0 | BO115: =IF($O115=$BN$61,$R115,0) -> 0 | BP115: =IF($O115=$BP$61,$P115,0) -> 0 | BQ115: =IF($O115=$BP$61,$R115,0) -> 0 | BR115: =IF($O115=$BR$61,$P115,0) -> 0 | BS115: =IF($O115=$BR$61,$R115,0) -> 0 | BT115: =IF($O115=$BT$61,$P115,0) -> 0 | BU115: =IF($O115=$BT$61,$R115,0) -> 0 | BV115: =IF($O115=$BV$61,$P115,0) -> 0 | BW115: =IF($O115=$BV$61,$R115,0) -> 0 | BX115: =IF($O115=$BX$61,$P115,0) -> 0 | BY115: =IF($O115=$BX$61,$R115,0) -> 0 | BZ115: =IF($O115=$BZ$61,$P115,0) -> 0 | CA115: =IF($O115=$BZ$61,$R115,0) -> 0 | CB115: =IF($O115=$CB$61,$P115,0) -> 0 | CC115: =IF($O115=$CB$61,$R115,0) -> 0 | CD115: =IF($O115=$CD$61,$P115,0) -> 0 | CE115: =IF($O115=$CD$61,$R115,0) -> 0 | CF115: =IF($O115=$CF$61,$P115,0) -> 0 | CG115: =IF($O115=$CF$61,$R115,0) -> 0 | CH115: =IF($O115=$CH$61,$P115,0) -> 0 | CI115: =IF($O115=$CH$61,$R115,0) -> 0 | CJ115: =IF($O115=$CJ$61,$P115,0) -> 0 | CK115: =IF($O115=$CJ$61,$R115,0) -> 0 | CL115: =IF($O115=$CL$61,$P115,0) -> 0 | CM115: =IF($O115=$CL$61,$R115,0) -> 0 | CN115: =IF($O115=$CN$61,$P115,0) -> 0 | CO115: =IF($O115=$CN$61,$R115,0) -> 0 | CP115: =IF($O115=$CP$61,$P115,0) -> 0 | CQ115: =IF($O115=$CP$61,$R115,0) -> 0 | CR115: =IF($O115=$CR$61,$P115,0) -> 0 | CS115: =IF($O115=$CR$61,$R115,0) -> 0 | CT115: =IF($O115=$CT$61,$P115,0) -> 0 | CU115: =IF($O115=$CT$61,$R115,0) -> 0 | CV115: =IF($O115=$CV$61,$P115,0) -> 0 | CW115: =IF($O115=$CV$61,$R115,0) -> 0 | CX115: =IF($O115=$CX$61,$P115,0) -> 0 | CY115: =IF($O115=$CX$61,$R115,0) -> 0
H116: =S116*1.45 -> 0 | N116: =L116*M116 -> 0 | R116: =Q116*P116 -> 0 | S116: =R116+N116 -> 0 | T116: =IF(H116<>0,1-(S116/H116),0) -> 0 | V116: =IF($K116=$V$61,$L116,0) -> 0 | W116: =IF($K116=$V$61,$N116,0) -> 0 | X116: =IF($K116=$X$61,$L116,0) -> 0 | Y116: =IF($K116=$X$61,$N116,0) -> 0 | Z116: =IF($K116=$Z$61,$L116,0) -> 0 | AA116: =IF($K116=$Z$61,$N116,0) -> 0 | AB116: =IF($K116=$AB$61,$L116,0) -> 0 | AC116: =IF($K116=$AB$61,$N116,0) -> 0 | AD116: =IF($K116=$AD$61,$L116,0) -> 0 | AE116: =IF($K116=$AD$61,$N116,0) -> 0 | AF116: =IF($K116=$AF$61,$L116,0) -> 0 | AG116: =IF($K116=$AF$61,$N116,0) -> 0 | AH116: =IF($K116=$AH$61,$L116,0) -> 0 | AI116: =IF($K116=$AH$61,$N116,0) -> 0 | AJ116: =IF($K116=$AJ$61,$L116,0) -> 0 | AK116: =IF($K116=$AJ$61,$N116,0) -> 0 | AL116: =IF($K116=$AL$61,$L116,0) -> 0 | AM116: =IF($K116=$AL$61,$N116,0) -> 0 | AN116: =IF($K116=$AN$61,$L116,0) -> 0 | AO116: =IF($K116=$AN$61,$N116,0) -> 0 | AP116: =IF($K116=$AP$61,$L116,0) -> 0 | AQ116: =IF($K116=$AP$61,$N116,0) -> 0 | AR116: =IF($K116=$AR$61,$L116,0) -> 0 | AS116: =IF($K116=$AR$61,$N116,0) -> 0 | AT116: =IF($K116=$AT$61,$L116,0) -> 0 | AU116: =IF($K116=$AT$61,$N116,0) -> 0 | AV116: =IF($K116=$AV$61,$L116,0) -> 0 | AW116: =IF($K116=$AV$61,$N116,0) -> 0 | AX116: =IF($K116=$AX$61,$L116,0) -> 0 | AY116: =IF($K116=$AX$61,$N116,0) -> 0 | AZ116: =IF($K116=$AZ$61,$L116,0) -> 0 | BA116: =IF($K116=$AZ$61,$N116,0) -> 0 | BB116: =IF($K116=$BB$61,$L116,0) -> 0 | BC116: =IF($K116=$BB$61,$N116,0) -> 0 | BD116: =IF($O116=$BD$61,$P116,0) -> 0 | BE116: =IF($O116=$BD$61,$R116,0) -> 0 | BF116: =IF($O116=$BF$61,$P116,0) -> 0 | BG116: =IF($O116=$BF$61,$R116,0) -> 0 | BH116: =IF($O116=$BH$61,$P116,0) -> 0 | BI116: =IF($O116=$BH$61,$R116,0) -> 0 | BJ116: =IF($O116=$BJ$61,$P116,0) -> 0 | BK116: =IF($O116=$BJ$61,$R116,0) -> 0 | BL116: =IF($O116=$BL$61,$P116,0) -> 0 | BM116: =IF($O116=$BL$61,$R116,0) -> 0 | BN116: =IF($O116=$BN$61,$P116,0) -> 0 | BO116: =IF($O116=$BN$61,$R116,0) -> 0 | BP116: =IF($O116=$BP$61,$P116,0) -> 0 | BQ116: =IF($O116=$BP$61,$R116,0) -> 0 | BR116: =IF($O116=$BR$61,$P116,0) -> 0 | BS116: =IF($O116=$BR$61,$R116,0) -> 0 | BT116: =IF($O116=$BT$61,$P116,0) -> 0 | BU116: =IF($O116=$BT$61,$R116,0) -> 0 | BV116: =IF($O116=$BV$61,$P116,0) -> 0 | BW116: =IF($O116=$BV$61,$R116,0) -> 0 | BX116: =IF($O116=$BX$61,$P116,0) -> 0 | BY116: =IF($O116=$BX$61,$R116,0) -> 0 | BZ116: =IF($O116=$BZ$61,$P116,0) -> 0 | CA116: =IF($O116=$BZ$61,$R116,0) -> 0 | CB116: =IF($O116=$CB$61,$P116,0) -> 0 | CC116: =IF($O116=$CB$61,$R116,0) -> 0 | CD116: =IF($O116=$CD$61,$P116,0) -> 0 | CE116: =IF($O116=$CD$61,$R116,0) -> 0 | CF116: =IF($O116=$CF$61,$P116,0) -> 0 | CG116: =IF($O116=$CF$61,$R116,0) -> 0 | CH116: =IF($O116=$CH$61,$P116,0) -> 0 | CI116: =IF($O116=$CH$61,$R116,0) -> 0 | CJ116: =IF($O116=$CJ$61,$P116,0) -> 0 | CK116: =IF($O116=$CJ$61,$R116,0) -> 0 | CL116: =IF($O116=$CL$61,$P116,0) -> 0 | CM116: =IF($O116=$CL$61,$R116,0) -> 0 | CN116: =IF($O116=$CN$61,$P116,0) -> 0 | CO116: =IF($O116=$CN$61,$R116,0) -> 0 | CP116: =IF($O116=$CP$61,$P116,0) -> 0 | CQ116: =IF($O116=$CP$61,$R116,0) -> 0 | CR116: =IF($O116=$CR$61,$P116,0) -> 0 | CS116: =IF($O116=$CR$61,$R116,0) -> 0 | CT116: =IF($O116=$CT$61,$P116,0) -> 0 | CU116: =IF($O116=$CT$61,$R116,0) -> 0 | CV116: =IF($O116=$CV$61,$P116,0) -> 0 | CW116: =IF($O116=$CV$61,$R116,0) -> 0 | CX116: =IF($O116=$CX$61,$P116,0) -> 0 | CY116: =IF($O116=$CX$61,$R116,0) -> 0
H117: =S117*1.45 -> 0 | N117: =L117*M117 -> 0 | R117: =Q117*P117 -> 0 | S117: =R117+N117 -> 0 | T117: =IF(H117<>0,1-(S117/H117),0) -> 0 | V117: =IF($K117=$V$61,$L117,0) -> 0 | W117: =IF($K117=$V$61,$N117,0) -> 0 | X117: =IF($K117=$X$61,$L117,0) -> 0 | Y117: =IF($K117=$X$61,$N117,0) -> 0 | Z117: =IF($K117=$Z$61,$L117,0) -> 0 | AA117: =IF($K117=$Z$61,$N117,0) -> 0 | AB117: =IF($K117=$AB$61,$L117,0) -> 0 | AC117: =IF($K117=$AB$61,$N117,0) -> 0 | AD117: =IF($K117=$AD$61,$L117,0) -> 0 | AE117: =IF($K117=$AD$61,$N117,0) -> 0 | AF117: =IF($K117=$AF$61,$L117,0) -> 0 | AG117: =IF($K117=$AF$61,$N117,0) -> 0 | AH117: =IF($K117=$AH$61,$L117,0) -> 0 | AI117: =IF($K117=$AH$61,$N117,0) -> 0 | AJ117: =IF($K117=$AJ$61,$L117,0) -> 0 | AK117: =IF($K117=$AJ$61,$N117,0) -> 0 | AL117: =IF($K117=$AL$61,$L117,0) -> 0 | AM117: =IF($K117=$AL$61,$N117,0) -> 0 | AN117: =IF($K117=$AN$61,$L117,0) -> 0 | AO117: =IF($K117=$AN$61,$N117,0) -> 0 | AP117: =IF($K117=$AP$61,$L117,0) -> 0 | AQ117: =IF($K117=$AP$61,$N117,0) -> 0 | AR117: =IF($K117=$AR$61,$L117,0) -> 0 | AS117: =IF($K117=$AR$61,$N117,0) -> 0 | AT117: =IF($K117=$AT$61,$L117,0) -> 0 | AU117: =IF($K117=$AT$61,$N117,0) -> 0 | AV117: =IF($K117=$AV$61,$L117,0) -> 0 | AW117: =IF($K117=$AV$61,$N117,0) -> 0 | AX117: =IF($K117=$AX$61,$L117,0) -> 0 | AY117: =IF($K117=$AX$61,$N117,0) -> 0 | AZ117: =IF($K117=$AZ$61,$L117,0) -> 0 | BA117: =IF($K117=$AZ$61,$N117,0) -> 0 | BB117: =IF($K117=$BB$61,$L117,0) -> 0 | BC117: =IF($K117=$BB$61,$N117,0) -> 0 | BD117: =IF($O117=$BD$61,$P117,0) -> 0 | BE117: =IF($O117=$BD$61,$R117,0) -> 0 | BF117: =IF($O117=$BF$61,$P117,0) -> 0 | BG117: =IF($O117=$BF$61,$R117,0) -> 0 | BH117: =IF($O117=$BH$61,$P117,0) -> 0 | BI117: =IF($O117=$BH$61,$R117,0) -> 0 | BJ117: =IF($O117=$BJ$61,$P117,0) -> 0 | BK117: =IF($O117=$BJ$61,$R117,0) -> 0 | BL117: =IF($O117=$BL$61,$P117,0) -> 0 | BM117: =IF($O117=$BL$61,$R117,0) -> 0 | BN117: =IF($O117=$BN$61,$P117,0) -> 0 | BO117: =IF($O117=$BN$61,$R117,0) -> 0 | BP117: =IF($O117=$BP$61,$P117,0) -> 0 | BQ117: =IF($O117=$BP$61,$R117,0) -> 0 | BR117: =IF($O117=$BR$61,$P117,0) -> 0 | BS117: =IF($O117=$BR$61,$R117,0) -> 0 | BT117: =IF($O117=$BT$61,$P117,0) -> 0 | BU117: =IF($O117=$BT$61,$R117,0) -> 0 | BV117: =IF($O117=$BV$61,$P117,0) -> 0 | BW117: =IF($O117=$BV$61,$R117,0) -> 0 | BX117: =IF($O117=$BX$61,$P117,0) -> 0 | BY117: =IF($O117=$BX$61,$R117,0) -> 0 | BZ117: =IF($O117=$BZ$61,$P117,0) -> 0 | CA117: =IF($O117=$BZ$61,$R117,0) -> 0 | CB117: =IF($O117=$CB$61,$P117,0) -> 0 | CC117: =IF($O117=$CB$61,$R117,0) -> 0 | CD117: =IF($O117=$CD$61,$P117,0) -> 0 | CE117: =IF($O117=$CD$61,$R117,0) -> 0 | CF117: =IF($O117=$CF$61,$P117,0) -> 0 | CG117: =IF($O117=$CF$61,$R117,0) -> 0 | CH117: =IF($O117=$CH$61,$P117,0) -> 0 | CI117: =IF($O117=$CH$61,$R117,0) -> 0 | CJ117: =IF($O117=$CJ$61,$P117,0) -> 0 | CK117: =IF($O117=$CJ$61,$R117,0) -> 0 | CL117: =IF($O117=$CL$61,$P117,0) -> 0 | CM117: =IF($O117=$CL$61,$R117,0) -> 0 | CN117: =IF($O117=$CN$61,$P117,0) -> 0 | CO117: =IF($O117=$CN$61,$R117,0) -> 0 | CP117: =IF($O117=$CP$61,$P117,0) -> 0 | CQ117: =IF($O117=$CP$61,$R117,0) -> 0 | CR117: =IF($O117=$CR$61,$P117,0) -> 0 | CS117: =IF($O117=$CR$61,$R117,0) -> 0 | CT117: =IF($O117=$CT$61,$P117,0) -> 0 | CU117: =IF($O117=$CT$61,$R117,0) -> 0 | CV117: =IF($O117=$CV$61,$P117,0) -> 0 | CW117: =IF($O117=$CV$61,$R117,0) -> 0 | CX117: =IF($O117=$CX$61,$P117,0) -> 0 | CY117: =IF($O117=$CX$61,$R117,0) -> 0
H118: =S118*1.45 -> 0 | N118: =L118*M118 -> 0 | R118: =Q118*P118 -> 0 | S118: =R118+N118 -> 0 | T118: =IF(H118<>0,1-(S118/H118),0) -> 0 | V118: =IF($K118=$V$61,$L118,0) -> 0 | W118: =IF($K118=$V$61,$N118,0) -> 0 | X118: =IF($K118=$X$61,$L118,0) -> 0 | Y118: =IF($K118=$X$61,$N118,0) -> 0 | Z118: =IF($K118=$Z$61,$L118,0) -> 0 | AA118: =IF($K118=$Z$61,$N118,0) -> 0 | AB118: =IF($K118=$AB$61,$L118,0) -> 0 | AC118: =IF($K118=$AB$61,$N118,0) -> 0 | AD118: =IF($K118=$AD$61,$L118,0) -> 0 | AE118: =IF($K118=$AD$61,$N118,0) -> 0 | AF118: =IF($K118=$AF$61,$L118,0) -> 0 | AG118: =IF($K118=$AF$61,$N118,0) -> 0 | AH118: =IF($K118=$AH$61,$L118,0) -> 0 | AI118: =IF($K118=$AH$61,$N118,0) -> 0 | AJ118: =IF($K118=$AJ$61,$L118,0) -> 0 | AK118: =IF($K118=$AJ$61,$N118,0) -> 0 | AL118: =IF($K118=$AL$61,$L118,0) -> 0 | AM118: =IF($K118=$AL$61,$N118,0) -> 0 | AN118: =IF($K118=$AN$61,$L118,0) -> 0 | AO118: =IF($K118=$AN$61,$N118,0) -> 0 | AP118: =IF($K118=$AP$61,$L118,0) -> 0 | AQ118: =IF($K118=$AP$61,$N118,0) -> 0 | AR118: =IF($K118=$AR$61,$L118,0) -> 0 | AS118: =IF($K118=$AR$61,$N118,0) -> 0 | AT118: =IF($K118=$AT$61,$L118,0) -> 0 | AU118: =IF($K118=$AT$61,$N118,0) -> 0 | AV118: =IF($K118=$AV$61,$L118,0) -> 0 | AW118: =IF($K118=$AV$61,$N118,0) -> 0 | AX118: =IF($K118=$AX$61,$L118,0) -> 0 | AY118: =IF($K118=$AX$61,$N118,0) -> 0 | AZ118: =IF($K118=$AZ$61,$L118,0) -> 0 | BA118: =IF($K118=$AZ$61,$N118,0) -> 0 | BB118: =IF($K118=$BB$61,$L118,0) -> 0 | BC118: =IF($K118=$BB$61,$N118,0) -> 0 | BD118: =IF($O118=$BD$61,$P118,0) -> 0 | BE118: =IF($O118=$BD$61,$R118,0) -> 0 | BF118: =IF($O118=$BF$61,$P118,0) -> 0 | BG118: =IF($O118=$BF$61,$R118,0) -> 0 | BH118: =IF($O118=$BH$61,$P118,0) -> 0 | BI118: =IF($O118=$BH$61,$R118,0) -> 0 | BJ118: =IF($O118=$BJ$61,$P118,0) -> 0 | BK118: =IF($O118=$BJ$61,$R118,0) -> 0 | BL118: =IF($O118=$BL$61,$P118,0) -> 0 | BM118: =IF($O118=$BL$61,$R118,0) -> 0 | BN118: =IF($O118=$BN$61,$P118,0) -> 0 | BO118: =IF($O118=$BN$61,$R118,0) -> 0 | BP118: =IF($O118=$BP$61,$P118,0) -> 0 | BQ118: =IF($O118=$BP$61,$R118,0) -> 0 | BR118: =IF($O118=$BR$61,$P118,0) -> 0 | BS118: =IF($O118=$BR$61,$R118,0) -> 0 | BT118: =IF($O118=$BT$61,$P118,0) -> 0 | BU118: =IF($O118=$BT$61,$R118,0) -> 0 | BV118: =IF($O118=$BV$61,$P118,0) -> 0 | BW118: =IF($O118=$BV$61,$R118,0) -> 0 | BX118: =IF($O118=$BX$61,$P118,0) -> 0 | BY118: =IF($O118=$BX$61,$R118,0) -> 0 | BZ118: =IF($O118=$BZ$61,$P118,0) -> 0 | CA118: =IF($O118=$BZ$61,$R118,0) -> 0 | CB118: =IF($O118=$CB$61,$P118,0) -> 0 | CC118: =IF($O118=$CB$61,$R118,0) -> 0 | CD118: =IF($O118=$CD$61,$P118,0) -> 0 | CE118: =IF($O118=$CD$61,$R118,0) -> 0 | CF118: =IF($O118=$CF$61,$P118,0) -> 0 | CG118: =IF($O118=$CF$61,$R118,0) -> 0 | CH118: =IF($O118=$CH$61,$P118,0) -> 0 | CI118: =IF($O118=$CH$61,$R118,0) -> 0 | CJ118: =IF($O118=$CJ$61,$P118,0) -> 0 | CK118: =IF($O118=$CJ$61,$R118,0) -> 0 | CL118: =IF($O118=$CL$61,$P118,0) -> 0 | CM118: =IF($O118=$CL$61,$R118,0) -> 0 | CN118: =IF($O118=$CN$61,$P118,0) -> 0 | CO118: =IF($O118=$CN$61,$R118,0) -> 0 | CP118: =IF($O118=$CP$61,$P118,0) -> 0 | CQ118: =IF($O118=$CP$61,$R118,0) -> 0 | CR118: =IF($O118=$CR$61,$P118,0) -> 0 | CS118: =IF($O118=$CR$61,$R118,0) -> 0 | CT118: =IF($O118=$CT$61,$P118,0) -> 0 | CU118: =IF($O118=$CT$61,$R118,0) -> 0 | CV118: =IF($O118=$CV$61,$P118,0) -> 0 | CW118: =IF($O118=$CV$61,$R118,0) -> 0 | CX118: =IF($O118=$CX$61,$P118,0) -> 0 | CY118: =IF($O118=$CX$61,$R118,0) -> 0
H119: =S119*1.45 -> 0 | N119: =L119*M119 -> 0 | R119: =Q119*P119 -> 0 | S119: =R119+N119 -> 0 | T119: =IF(H119<>0,1-(S119/H119),0) -> 0 | V119: =IF($K119=$V$61,$L119,0) -> 0 | W119: =IF($K119=$V$61,$N119,0) -> 0 | X119: =IF($K119=$X$61,$L119,0) -> 0 | Y119: =IF($K119=$X$61,$N119,0) -> 0 | Z119: =IF($K119=$Z$61,$L119,0) -> 0 | AA119: =IF($K119=$Z$61,$N119,0) -> 0 | AB119: =IF($K119=$AB$61,$L119,0) -> 0 | AC119: =IF($K119=$AB$61,$N119,0) -> 0 | AD119: =IF($K119=$AD$61,$L119,0) -> 0 | AE119: =IF($K119=$AD$61,$N119,0) -> 0 | AF119: =IF($K119=$AF$61,$L119,0) -> 0 | AG119: =IF($K119=$AF$61,$N119,0) -> 0 | AH119: =IF($K119=$AH$61,$L119,0) -> 0 | AI119: =IF($K119=$AH$61,$N119,0) -> 0 | AJ119: =IF($K119=$AJ$61,$L119,0) -> 0 | AK119: =IF($K119=$AJ$61,$N119,0) -> 0 | AL119: =IF($K119=$AL$61,$L119,0) -> 0 | AM119: =IF($K119=$AL$61,$N119,0) -> 0 | AN119: =IF($K119=$AN$61,$L119,0) -> 0 | AO119: =IF($K119=$AN$61,$N119,0) -> 0 | AP119: =IF($K119=$AP$61,$L119,0) -> 0 | AQ119: =IF($K119=$AP$61,$N119,0) -> 0 | AR119: =IF($K119=$AR$61,$L119,0) -> 0 | AS119: =IF($K119=$AR$61,$N119,0) -> 0 | AT119: =IF($K119=$AT$61,$L119,0) -> 0 | AU119: =IF($K119=$AT$61,$N119,0) -> 0 | AV119: =IF($K119=$AV$61,$L119,0) -> 0 | AW119: =IF($K119=$AV$61,$N119,0) -> 0 | AX119: =IF($K119=$AX$61,$L119,0) -> 0 | AY119: =IF($K119=$AX$61,$N119,0) -> 0 | AZ119: =IF($K119=$AZ$61,$L119,0) -> 0 | BA119: =IF($K119=$AZ$61,$N119,0) -> 0 | BB119: =IF($K119=$BB$61,$L119,0) -> 0 | BC119: =IF($K119=$BB$61,$N119,0) -> 0 | BD119: =IF($O119=$BD$61,$P119,0) -> 0 | BE119: =IF($O119=$BD$61,$R119,0) -> 0 | BF119: =IF($O119=$BF$61,$P119,0) -> 0 | BG119: =IF($O119=$BF$61,$R119,0) -> 0 | BH119: =IF($O119=$BH$61,$P119,0) -> 0 | BI119: =IF($O119=$BH$61,$R119,0) -> 0 | BJ119: =IF($O119=$BJ$61,$P119,0) -> 0 | BK119: =IF($O119=$BJ$61,$R119,0) -> 0 | BL119: =IF($O119=$BL$61,$P119,0) -> 0 | BM119: =IF($O119=$BL$61,$R119,0) -> 0 | BN119: =IF($O119=$BN$61,$P119,0) -> 0 | BO119: =IF($O119=$BN$61,$R119,0) -> 0 | BP119: =IF($O119=$BP$61,$P119,0) -> 0 | BQ119: =IF($O119=$BP$61,$R119,0) -> 0 | BR119: =IF($O119=$BR$61,$P119,0) -> 0 | BS119: =IF($O119=$BR$61,$R119,0) -> 0 | BT119: =IF($O119=$BT$61,$P119,0) -> 0 | BU119: =IF($O119=$BT$61,$R119,0) -> 0 | BV119: =IF($O119=$BV$61,$P119,0) -> 0 | BW119: =IF($O119=$BV$61,$R119,0) -> 0 | BX119: =IF($O119=$BX$61,$P119,0) -> 0 | BY119: =IF($O119=$BX$61,$R119,0) -> 0 | BZ119: =IF($O119=$BZ$61,$P119,0) -> 0 | CA119: =IF($O119=$BZ$61,$R119,0) -> 0 | CB119: =IF($O119=$CB$61,$P119,0) -> 0 | CC119: =IF($O119=$CB$61,$R119,0) -> 0 | CD119: =IF($O119=$CD$61,$P119,0) -> 0 | CE119: =IF($O119=$CD$61,$R119,0) -> 0 | CF119: =IF($O119=$CF$61,$P119,0) -> 0 | CG119: =IF($O119=$CF$61,$R119,0) -> 0 | CH119: =IF($O119=$CH$61,$P119,0) -> 0 | CI119: =IF($O119=$CH$61,$R119,0) -> 0 | CJ119: =IF($O119=$CJ$61,$P119,0) -> 0 | CK119: =IF($O119=$CJ$61,$R119,0) -> 0 | CL119: =IF($O119=$CL$61,$P119,0) -> 0 | CM119: =IF($O119=$CL$61,$R119,0) -> 0 | CN119: =IF($O119=$CN$61,$P119,0) -> 0 | CO119: =IF($O119=$CN$61,$R119,0) -> 0 | CP119: =IF($O119=$CP$61,$P119,0) -> 0 | CQ119: =IF($O119=$CP$61,$R119,0) -> 0 | CR119: =IF($O119=$CR$61,$P119,0) -> 0 | CS119: =IF($O119=$CR$61,$R119,0) -> 0 | CT119: =IF($O119=$CT$61,$P119,0) -> 0 | CU119: =IF($O119=$CT$61,$R119,0) -> 0 | CV119: =IF($O119=$CV$61,$P119,0) -> 0 | CW119: =IF($O119=$CV$61,$R119,0) -> 0 | CX119: =IF($O119=$CX$61,$P119,0) -> 0 | CY119: =IF($O119=$CX$61,$R119,0) -> 0
H120: =S120*1.45 -> 0 | N120: =L120*M120 -> 0 | R120: =Q120*P120 -> 0 | S120: =R120+N120 -> 0 | T120: =IF(H120<>0,1-(S120/H120),0) -> 0 | V120: =IF($K120=$V$61,$L120,0) -> 0 | W120: =IF($K120=$V$61,$N120,0) -> 0 | X120: =IF($K120=$X$61,$L120,0) -> 0 | Y120: =IF($K120=$X$61,$N120,0) -> 0 | Z120: =IF($K120=$Z$61,$L120,0) -> 0 | AA120: =IF($K120=$Z$61,$N120,0) -> 0 | AB120: =IF($K120=$AB$61,$L120,0) -> 0 | AC120: =IF($K120=$AB$61,$N120,0) -> 0 | AD120: =IF($K120=$AD$61,$L120,0) -> 0 | AE120: =IF($K120=$AD$61,$N120,0) -> 0 | AF120: =IF($K120=$AF$61,$L120,0) -> 0 | AG120: =IF($K120=$AF$61,$N120,0) -> 0 | AH120: =IF($K120=$AH$61,$L120,0) -> 0 | AI120: =IF($K120=$AH$61,$N120,0) -> 0 | AJ120: =IF($K120=$AJ$61,$L120,0) -> 0 | AK120: =IF($K120=$AJ$61,$N120,0) -> 0 | AL120: =IF($K120=$AL$61,$L120,0) -> 0 | AM120: =IF($K120=$AL$61,$N120,0) -> 0 | AN120: =IF($K120=$AN$61,$L120,0) -> 0 | AO120: =IF($K120=$AN$61,$N120,0) -> 0 | AP120: =IF($K120=$AP$61,$L120,0) -> 0 | AQ120: =IF($K120=$AP$61,$N120,0) -> 0 | AR120: =IF($K120=$AR$61,$L120,0) -> 0 | AS120: =IF($K120=$AR$61,$N120,0) -> 0 | AT120: =IF($K120=$AT$61,$L120,0) -> 0 | AU120: =IF($K120=$AT$61,$N120,0) -> 0 | AV120: =IF($K120=$AV$61,$L120,0) -> 0 | AW120: =IF($K120=$AV$61,$N120,0) -> 0 | AX120: =IF($K120=$AX$61,$L120,0) -> 0 | AY120: =IF($K120=$AX$61,$N120,0) -> 0 | AZ120: =IF($K120=$AZ$61,$L120,0) -> 0 | BA120: =IF($K120=$AZ$61,$N120,0) -> 0 | BB120: =IF($K120=$BB$61,$L120,0) -> 0 | BC120: =IF($K120=$BB$61,$N120,0) -> 0 | BD120: =IF($O120=$BD$61,$P120,0) -> 0 | BE120: =IF($O120=$BD$61,$R120,0) -> 0 | BF120: =IF($O120=$BF$61,$P120,0) -> 0 | BG120: =IF($O120=$BF$61,$R120,0) -> 0 | BH120: =IF($O120=$BH$61,$P120,0) -> 0 | BI120: =IF($O120=$BH$61,$R120,0) -> 0 | BJ120: =IF($O120=$BJ$61,$P120,0) -> 0 | BK120: =IF($O120=$BJ$61,$R120,0) -> 0 | BL120: =IF($O120=$BL$61,$P120,0) -> 0 | BM120: =IF($O120=$BL$61,$R120,0) -> 0 | BN120: =IF($O120=$BN$61,$P120,0) -> 0 | BO120: =IF($O120=$BN$61,$R120,0) -> 0 | BP120: =IF($O120=$BP$61,$P120,0) -> 0 | BQ120: =IF($O120=$BP$61,$R120,0) -> 0 | BR120: =IF($O120=$BR$61,$P120,0) -> 0 | BS120: =IF($O120=$BR$61,$R120,0) -> 0 | BT120: =IF($O120=$BT$61,$P120,0) -> 0 | BU120: =IF($O120=$BT$61,$R120,0) -> 0 | BV120: =IF($O120=$BV$61,$P120,0) -> 0 | BW120: =IF($O120=$BV$61,$R120,0) -> 0 | BX120: =IF($O120=$BX$61,$P120,0) -> 0 | BY120: =IF($O120=$BX$61,$R120,0) -> 0 | BZ120: =IF($O120=$BZ$61,$P120,0) -> 0 | CA120: =IF($O120=$BZ$61,$R120,0) -> 0 | CB120: =IF($O120=$CB$61,$P120,0) -> 0 | CC120: =IF($O120=$CB$61,$R120,0) -> 0 | CD120: =IF($O120=$CD$61,$P120,0) -> 0 | CE120: =IF($O120=$CD$61,$R120,0) -> 0 | CF120: =IF($O120=$CF$61,$P120,0) -> 0 | CG120: =IF($O120=$CF$61,$R120,0) -> 0 | CH120: =IF($O120=$CH$61,$P120,0) -> 0 | CI120: =IF($O120=$CH$61,$R120,0) -> 0 | CJ120: =IF($O120=$CJ$61,$P120,0) -> 0 | CK120: =IF($O120=$CJ$61,$R120,0) -> 0 | CL120: =IF($O120=$CL$61,$P120,0) -> 0 | CM120: =IF($O120=$CL$61,$R120,0) -> 0 | CN120: =IF($O120=$CN$61,$P120,0) -> 0 | CO120: =IF($O120=$CN$61,$R120,0) -> 0 | CP120: =IF($O120=$CP$61,$P120,0) -> 0 | CQ120: =IF($O120=$CP$61,$R120,0) -> 0 | CR120: =IF($O120=$CR$61,$P120,0) -> 0 | CS120: =IF($O120=$CR$61,$R120,0) -> 0 | CT120: =IF($O120=$CT$61,$P120,0) -> 0 | CU120: =IF($O120=$CT$61,$R120,0) -> 0 | CV120: =IF($O120=$CV$61,$P120,0) -> 0 | CW120: =IF($O120=$CV$61,$R120,0) -> 0 | CX120: =IF($O120=$CX$61,$P120,0) -> 0 | CY120: =IF($O120=$CX$61,$R120,0) -> 0
H121: =S121*1.45 -> 0 | N121: =L121*M121 -> 0 | R121: =Q121*P121 -> 0 | S121: =R121+N121 -> 0 | T121: =IF(H121<>0,1-(S121/H121),0) -> 0 | V121: =IF($K121=$V$61,$L121,0) -> 0 | W121: =IF($K121=$V$61,$N121,0) -> 0 | X121: =IF($K121=$X$61,$L121,0) -> 0 | Y121: =IF($K121=$X$61,$N121,0) -> 0 | Z121: =IF($K121=$Z$61,$L121,0) -> 0 | AA121: =IF($K121=$Z$61,$N121,0) -> 0 | AB121: =IF($K121=$AB$61,$L121,0) -> 0 | AC121: =IF($K121=$AB$61,$N121,0) -> 0 | AD121: =IF($K121=$AD$61,$L121,0) -> 0 | AE121: =IF($K121=$AD$61,$N121,0) -> 0 | AF121: =IF($K121=$AF$61,$L121,0) -> 0 | AG121: =IF($K121=$AF$61,$N121,0) -> 0 | AH121: =IF($K121=$AH$61,$L121,0) -> 0 | AI121: =IF($K121=$AH$61,$N121,0) -> 0 | AJ121: =IF($K121=$AJ$61,$L121,0) -> 0 | AK121: =IF($K121=$AJ$61,$N121,0) -> 0 | AL121: =IF($K121=$AL$61,$L121,0) -> 0 | AM121: =IF($K121=$AL$61,$N121,0) -> 0 | AN121: =IF($K121=$AN$61,$L121,0) -> 0 | AO121: =IF($K121=$AN$61,$N121,0) -> 0 | AP121: =IF($K121=$AP$61,$L121,0) -> 0 | AQ121: =IF($K121=$AP$61,$N121,0) -> 0 | AR121: =IF($K121=$AR$61,$L121,0) -> 0 | AS121: =IF($K121=$AR$61,$N121,0) -> 0 | AT121: =IF($K121=$AT$61,$L121,0) -> 0 | AU121: =IF($K121=$AT$61,$N121,0) -> 0 | AV121: =IF($K121=$AV$61,$L121,0) -> 0 | AW121: =IF($K121=$AV$61,$N121,0) -> 0 | AX121: =IF($K121=$AX$61,$L121,0) -> 0 | AY121: =IF($K121=$AX$61,$N121,0) -> 0 | AZ121: =IF($K121=$AZ$61,$L121,0) -> 0 | BA121: =IF($K121=$AZ$61,$N121,0) -> 0 | BB121: =IF($K121=$BB$61,$L121,0) -> 0 | BC121: =IF($K121=$BB$61,$N121,0) -> 0 | BD121: =IF($O121=$BD$61,$P121,0) -> 0 | BE121: =IF($O121=$BD$61,$R121,0) -> 0 | BF121: =IF($O121=$BF$61,$P121,0) -> 0 | BG121: =IF($O121=$BF$61,$R121,0) -> 0 | BH121: =IF($O121=$BH$61,$P121,0) -> 0 | BI121: =IF($O121=$BH$61,$R121,0) -> 0 | BJ121: =IF($O121=$BJ$61,$P121,0) -> 0 | BK121: =IF($O121=$BJ$61,$R121,0) -> 0 | BL121: =IF($O121=$BL$61,$P121,0) -> 0 | BM121: =IF($O121=$BL$61,$R121,0) -> 0 | BN121: =IF($O121=$BN$61,$P121,0) -> 0 | BO121: =IF($O121=$BN$61,$R121,0) -> 0 | BP121: =IF($O121=$BP$61,$P121,0) -> 0 | BQ121: =IF($O121=$BP$61,$R121,0) -> 0 | BR121: =IF($O121=$BR$61,$P121,0) -> 0 | BS121: =IF($O121=$BR$61,$R121,0) -> 0 | BT121: =IF($O121=$BT$61,$P121,0) -> 0 | BU121: =IF($O121=$BT$61,$R121,0) -> 0 | BV121: =IF($O121=$BV$61,$P121,0) -> 0 | BW121: =IF($O121=$BV$61,$R121,0) -> 0 | BX121: =IF($O121=$BX$61,$P121,0) -> 0 | BY121: =IF($O121=$BX$61,$R121,0) -> 0 | BZ121: =IF($O121=$BZ$61,$P121,0) -> 0 | CA121: =IF($O121=$BZ$61,$R121,0) -> 0 | CB121: =IF($O121=$CB$61,$P121,0) -> 0 | CC121: =IF($O121=$CB$61,$R121,0) -> 0 | CD121: =IF($O121=$CD$61,$P121,0) -> 0 | CE121: =IF($O121=$CD$61,$R121,0) -> 0 | CF121: =IF($O121=$CF$61,$P121,0) -> 0 | CG121: =IF($O121=$CF$61,$R121,0) -> 0 | CH121: =IF($O121=$CH$61,$P121,0) -> 0 | CI121: =IF($O121=$CH$61,$R121,0) -> 0 | CJ121: =IF($O121=$CJ$61,$P121,0) -> 0 | CK121: =IF($O121=$CJ$61,$R121,0) -> 0 | CL121: =IF($O121=$CL$61,$P121,0) -> 0 | CM121: =IF($O121=$CL$61,$R121,0) -> 0 | CN121: =IF($O121=$CN$61,$P121,0) -> 0 | CO121: =IF($O121=$CN$61,$R121,0) -> 0 | CP121: =IF($O121=$CP$61,$P121,0) -> 0 | CQ121: =IF($O121=$CP$61,$R121,0) -> 0 | CR121: =IF($O121=$CR$61,$P121,0) -> 0 | CS121: =IF($O121=$CR$61,$R121,0) -> 0 | CT121: =IF($O121=$CT$61,$P121,0) -> 0 | CU121: =IF($O121=$CT$61,$R121,0) -> 0 | CV121: =IF($O121=$CV$61,$P121,0) -> 0 | CW121: =IF($O121=$CV$61,$R121,0) -> 0 | CX121: =IF($O121=$CX$61,$P121,0) -> 0 | CY121: =IF($O121=$CX$61,$R121,0) -> 0
H122: =S122*1.45 -> 0 | N122: =L122*M122 -> 0 | R122: =Q122*P122 -> 0 | S122: =R122+N122 -> 0 | T122: =IF(H122<>0,1-(S122/H122),0) -> 0 | V122: =IF($K122=$V$61,$L122,0) -> 0 | W122: =IF($K122=$V$61,$N122,0) -> 0 | X122: =IF($K122=$X$61,$L122,0) -> 0 | Y122: =IF($K122=$X$61,$N122,0) -> 0 | Z122: =IF($K122=$Z$61,$L122,0) -> 0 | AA122: =IF($K122=$Z$61,$N122,0) -> 0 | AB122: =IF($K122=$AB$61,$L122,0) -> 0 | AC122: =IF($K122=$AB$61,$N122,0) -> 0 | AD122: =IF($K122=$AD$61,$L122,0) -> 0 | AE122: =IF($K122=$AD$61,$N122,0) -> 0 | AF122: =IF($K122=$AF$61,$L122,0) -> 0 | AG122: =IF($K122=$AF$61,$N122,0) -> 0 | AH122: =IF($K122=$AH$61,$L122,0) -> 0 | AI122: =IF($K122=$AH$61,$N122,0) -> 0 | AJ122: =IF($K122=$AJ$61,$L122,0) -> 0 | AK122: =IF($K122=$AJ$61,$N122,0) -> 0 | AL122: =IF($K122=$AL$61,$L122,0) -> 0 | AM122: =IF($K122=$AL$61,$N122,0) -> 0 | AN122: =IF($K122=$AN$61,$L122,0) -> 0 | AO122: =IF($K122=$AN$61,$N122,0) -> 0 | AP122: =IF($K122=$AP$61,$L122,0) -> 0 | AQ122: =IF($K122=$AP$61,$N122,0) -> 0 | AR122: =IF($K122=$AR$61,$L122,0) -> 0 | AS122: =IF($K122=$AR$61,$N122,0) -> 0 | AT122: =IF($K122=$AT$61,$L122,0) -> 0 | AU122: =IF($K122=$AT$61,$N122,0) -> 0 | AV122: =IF($K122=$AV$61,$L122,0) -> 0 | AW122: =IF($K122=$AV$61,$N122,0) -> 0 | AX122: =IF($K122=$AX$61,$L122,0) -> 0 | AY122: =IF($K122=$AX$61,$N122,0) -> 0 | AZ122: =IF($K122=$AZ$61,$L122,0) -> 0 | BA122: =IF($K122=$AZ$61,$N122,0) -> 0 | BB122: =IF($K122=$BB$61,$L122,0) -> 0 | BC122: =IF($K122=$BB$61,$N122,0) -> 0 | BD122: =IF($O122=$BD$61,$P122,0) -> 0 | BE122: =IF($O122=$BD$61,$R122,0) -> 0 | BF122: =IF($O122=$BF$61,$P122,0) -> 0 | BG122: =IF($O122=$BF$61,$R122,0) -> 0 | BH122: =IF($O122=$BH$61,$P122,0) -> 0 | BI122: =IF($O122=$BH$61,$R122,0) -> 0 | BJ122: =IF($O122=$BJ$61,$P122,0) -> 0 | BK122: =IF($O122=$BJ$61,$R122,0) -> 0 | BL122: =IF($O122=$BL$61,$P122,0) -> 0 | BM122: =IF($O122=$BL$61,$R122,0) -> 0 | BN122: =IF($O122=$BN$61,$P122,0) -> 0 | BO122: =IF($O122=$BN$61,$R122,0) -> 0 | BP122: =IF($O122=$BP$61,$P122,0) -> 0 | BQ122: =IF($O122=$BP$61,$R122,0) -> 0 | BR122: =IF($O122=$BR$61,$P122,0) -> 0 | BS122: =IF($O122=$BR$61,$R122,0) -> 0 | BT122: =IF($O122=$BT$61,$P122,0) -> 0 | BU122: =IF($O122=$BT$61,$R122,0) -> 0 | BV122: =IF($O122=$BV$61,$P122,0) -> 0 | BW122: =IF($O122=$BV$61,$R122,0) -> 0 | BX122: =IF($O122=$BX$61,$P122,0) -> 0 | BY122: =IF($O122=$BX$61,$R122,0) -> 0 | BZ122: =IF($O122=$BZ$61,$P122,0) -> 0 | CA122: =IF($O122=$BZ$61,$R122,0) -> 0 | CB122: =IF($O122=$CB$61,$P122,0) -> 0 | CC122: =IF($O122=$CB$61,$R122,0) -> 0 | CD122: =IF($O122=$CD$61,$P122,0) -> 0 | CE122: =IF($O122=$CD$61,$R122,0) -> 0 | CF122: =IF($O122=$CF$61,$P122,0) -> 0 | CG122: =IF($O122=$CF$61,$R122,0) -> 0 | CH122: =IF($O122=$CH$61,$P122,0) -> 0 | CI122: =IF($O122=$CH$61,$R122,0) -> 0 | CJ122: =IF($O122=$CJ$61,$P122,0) -> 0 | CK122: =IF($O122=$CJ$61,$R122,0) -> 0 | CL122: =IF($O122=$CL$61,$P122,0) -> 0 | CM122: =IF($O122=$CL$61,$R122,0) -> 0 | CN122: =IF($O122=$CN$61,$P122,0) -> 0 | CO122: =IF($O122=$CN$61,$R122,0) -> 0 | CP122: =IF($O122=$CP$61,$P122,0) -> 0 | CQ122: =IF($O122=$CP$61,$R122,0) -> 0 | CR122: =IF($O122=$CR$61,$P122,0) -> 0 | CS122: =IF($O122=$CR$61,$R122,0) -> 0 | CT122: =IF($O122=$CT$61,$P122,0) -> 0 | CU122: =IF($O122=$CT$61,$R122,0) -> 0 | CV122: =IF($O122=$CV$61,$P122,0) -> 0 | CW122: =IF($O122=$CV$61,$R122,0) -> 0 | CX122: =IF($O122=$CX$61,$P122,0) -> 0 | CY122: =IF($O122=$CX$61,$R122,0) -> 0
H123: =S123*1.45 -> 0 | N123: =L123*M123 -> 0 | R123: =Q123*P123 -> 0 | S123: =R123+N123 -> 0 | T123: =IF(H123<>0,1-(S123/H123),0) -> 0 | V123: =IF($K123=$V$61,$L123,0) -> 0 | W123: =IF($K123=$V$61,$N123,0) -> 0 | X123: =IF($K123=$X$61,$L123,0) -> 0 | Y123: =IF($K123=$X$61,$N123,0) -> 0 | Z123: =IF($K123=$Z$61,$L123,0) -> 0 | AA123: =IF($K123=$Z$61,$N123,0) -> 0 | AB123: =IF($K123=$AB$61,$L123,0) -> 0 | AC123: =IF($K123=$AB$61,$N123,0) -> 0 | AD123: =IF($K123=$AD$61,$L123,0) -> 0 | AE123: =IF($K123=$AD$61,$N123,0) -> 0 | AF123: =IF($K123=$AF$61,$L123,0) -> 0 | AG123: =IF($K123=$AF$61,$N123,0) -> 0 | AH123: =IF($K123=$AH$61,$L123,0) -> 0 | AI123: =IF($K123=$AH$61,$N123,0) -> 0 | AJ123: =IF($K123=$AJ$61,$L123,0) -> 0 | AK123: =IF($K123=$AJ$61,$N123,0) -> 0 | AL123: =IF($K123=$AL$61,$L123,0) -> 0 | AM123: =IF($K123=$AL$61,$N123,0) -> 0 | AN123: =IF($K123=$AN$61,$L123,0) -> 0 | AO123: =IF($K123=$AN$61,$N123,0) -> 0 | AP123: =IF($K123=$AP$61,$L123,0) -> 0 | AQ123: =IF($K123=$AP$61,$N123,0) -> 0 | AR123: =IF($K123=$AR$61,$L123,0) -> 0 | AS123: =IF($K123=$AR$61,$N123,0) -> 0 | AT123: =IF($K123=$AT$61,$L123,0) -> 0 | AU123: =IF($K123=$AT$61,$N123,0) -> 0 | AV123: =IF($K123=$AV$61,$L123,0) -> 0 | AW123: =IF($K123=$AV$61,$N123,0) -> 0 | AX123: =IF($K123=$AX$61,$L123,0) -> 0 | AY123: =IF($K123=$AX$61,$N123,0) -> 0 | AZ123: =IF($K123=$AZ$61,$L123,0) -> 0 | BA123: =IF($K123=$AZ$61,$N123,0) -> 0 | BB123: =IF($K123=$BB$61,$L123,0) -> 0 | BC123: =IF($K123=$BB$61,$N123,0) -> 0 | BD123: =IF($O123=$BD$61,$P123,0) -> 0 | BE123: =IF($O123=$BD$61,$R123,0) -> 0 | BF123: =IF($O123=$BF$61,$P123,0) -> 0 | BG123: =IF($O123=$BF$61,$R123,0) -> 0 | BH123: =IF($O123=$BH$61,$P123,0) -> 0 | BI123: =IF($O123=$BH$61,$R123,0) -> 0 | BJ123: =IF($O123=$BJ$61,$P123,0) -> 0 | BK123: =IF($O123=$BJ$61,$R123,0) -> 0 | BL123: =IF($O123=$BL$61,$P123,0) -> 0 | BM123: =IF($O123=$BL$61,$R123,0) -> 0 | BN123: =IF($O123=$BN$61,$P123,0) -> 0 | BO123: =IF($O123=$BN$61,$R123,0) -> 0 | BP123: =IF($O123=$BP$61,$P123,0) -> 0 | BQ123: =IF($O123=$BP$61,$R123,0) -> 0 | BR123: =IF($O123=$BR$61,$P123,0) -> 0 | BS123: =IF($O123=$BR$61,$R123,0) -> 0 | BT123: =IF($O123=$BT$61,$P123,0) -> 0 | BU123: =IF($O123=$BT$61,$R123,0) -> 0 | BV123: =IF($O123=$BV$61,$P123,0) -> 0 | BW123: =IF($O123=$BV$61,$R123,0) -> 0 | BX123: =IF($O123=$BX$61,$P123,0) -> 0 | BY123: =IF($O123=$BX$61,$R123,0) -> 0 | BZ123: =IF($O123=$BZ$61,$P123,0) -> 0 | CA123: =IF($O123=$BZ$61,$R123,0) -> 0 | CB123: =IF($O123=$CB$61,$P123,0) -> 0 | CC123: =IF($O123=$CB$61,$R123,0) -> 0 | CD123: =IF($O123=$CD$61,$P123,0) -> 0 | CE123: =IF($O123=$CD$61,$R123,0) -> 0 | CF123: =IF($O123=$CF$61,$P123,0) -> 0 | CG123: =IF($O123=$CF$61,$R123,0) -> 0 | CH123: =IF($O123=$CH$61,$P123,0) -> 0 | CI123: =IF($O123=$CH$61,$R123,0) -> 0 | CJ123: =IF($O123=$CJ$61,$P123,0) -> 0 | CK123: =IF($O123=$CJ$61,$R123,0) -> 0 | CL123: =IF($O123=$CL$61,$P123,0) -> 0 | CM123: =IF($O123=$CL$61,$R123,0) -> 0 | CN123: =IF($O123=$CN$61,$P123,0) -> 0 | CO123: =IF($O123=$CN$61,$R123,0) -> 0 | CP123: =IF($O123=$CP$61,$P123,0) -> 0 | CQ123: =IF($O123=$CP$61,$R123,0) -> 0 | CR123: =IF($O123=$CR$61,$P123,0) -> 0 | CS123: =IF($O123=$CR$61,$R123,0) -> 0 | CT123: =IF($O123=$CT$61,$P123,0) -> 0 | CU123: =IF($O123=$CT$61,$R123,0) -> 0 | CV123: =IF($O123=$CV$61,$P123,0) -> 0 | CW123: =IF($O123=$CV$61,$R123,0) -> 0 | CX123: =IF($O123=$CX$61,$P123,0) -> 0 | CY123: =IF($O123=$CX$61,$R123,0) -> 0
H124: =S124*1.45 -> 0 | N124: =L124*M124 -> 0 | R124: =Q124*P124 -> 0 | S124: =R124+N124 -> 0 | T124: =IF(H124<>0,1-(S124/H124),0) -> 0 | V124: =IF($K124=$V$61,$L124,0) -> 0 | W124: =IF($K124=$V$61,$N124,0) -> 0 | X124: =IF($K124=$X$61,$L124,0) -> 0 | Y124: =IF($K124=$X$61,$N124,0) -> 0 | Z124: =IF($K124=$Z$61,$L124,0) -> 0 | AA124: =IF($K124=$Z$61,$N124,0) -> 0 | AB124: =IF($K124=$AB$61,$L124,0) -> 0 | AC124: =IF($K124=$AB$61,$N124,0) -> 0 | AD124: =IF($K124=$AD$61,$L124,0) -> 0 | AE124: =IF($K124=$AD$61,$N124,0) -> 0 | AF124: =IF($K124=$AF$61,$L124,0) -> 0 | AG124: =IF($K124=$AF$61,$N124,0) -> 0 | AH124: =IF($K124=$AH$61,$L124,0) -> 0 | AI124: =IF($K124=$AH$61,$N124,0) -> 0 | AJ124: =IF($K124=$AJ$61,$L124,0) -> 0 | AK124: =IF($K124=$AJ$61,$N124,0) -> 0 | AL124: =IF($K124=$AL$61,$L124,0) -> 0 | AM124: =IF($K124=$AL$61,$N124,0) -> 0 | AN124: =IF($K124=$AN$61,$L124,0) -> 0 | AO124: =IF($K124=$AN$61,$N124,0) -> 0 | AP124: =IF($K124=$AP$61,$L124,0) -> 0 | AQ124: =IF($K124=$AP$61,$N124,0) -> 0 | AR124: =IF($K124=$AR$61,$L124,0) -> 0 | AS124: =IF($K124=$AR$61,$N124,0) -> 0 | AT124: =IF($K124=$AT$61,$L124,0) -> 0 | AU124: =IF($K124=$AT$61,$N124,0) -> 0 | AV124: =IF($K124=$AV$61,$L124,0) -> 0 | AW124: =IF($K124=$AV$61,$N124,0) -> 0 | AX124: =IF($K124=$AX$61,$L124,0) -> 0 | AY124: =IF($K124=$AX$61,$N124,0) -> 0 | AZ124: =IF($K124=$AZ$61,$L124,0) -> 0 | BA124: =IF($K124=$AZ$61,$N124,0) -> 0 | BB124: =IF($K124=$BB$61,$L124,0) -> 0 | BC124: =IF($K124=$BB$61,$N124,0) -> 0 | BD124: =IF($O124=$BD$61,$P124,0) -> 0 | BE124: =IF($O124=$BD$61,$R124,0) -> 0 | BF124: =IF($O124=$BF$61,$P124,0) -> 0 | BG124: =IF($O124=$BF$61,$R124,0) -> 0 | BH124: =IF($O124=$BH$61,$P124,0) -> 0 | BI124: =IF($O124=$BH$61,$R124,0) -> 0 | BJ124: =IF($O124=$BJ$61,$P124,0) -> 0 | BK124: =IF($O124=$BJ$61,$R124,0) -> 0 | BL124: =IF($O124=$BL$61,$P124,0) -> 0 | BM124: =IF($O124=$BL$61,$R124,0) -> 0 | BN124: =IF($O124=$BN$61,$P124,0) -> 0 | BO124: =IF($O124=$BN$61,$R124,0) -> 0 | BP124: =IF($O124=$BP$61,$P124,0) -> 0 | BQ124: =IF($O124=$BP$61,$R124,0) -> 0 | BR124: =IF($O124=$BR$61,$P124,0) -> 0 | BS124: =IF($O124=$BR$61,$R124,0) -> 0 | BT124: =IF($O124=$BT$61,$P124,0) -> 0 | BU124: =IF($O124=$BT$61,$R124,0) -> 0 | BV124: =IF($O124=$BV$61,$P124,0) -> 0 | BW124: =IF($O124=$BV$61,$R124,0) -> 0 | BX124: =IF($O124=$BX$61,$P124,0) -> 0 | BY124: =IF($O124=$BX$61,$R124,0) -> 0 | BZ124: =IF($O124=$BZ$61,$P124,0) -> 0 | CA124: =IF($O124=$BZ$61,$R124,0) -> 0 | CB124: =IF($O124=$CB$61,$P124,0) -> 0 | CC124: =IF($O124=$CB$61,$R124,0) -> 0 | CD124: =IF($O124=$CD$61,$P124,0) -> 0 | CE124: =IF($O124=$CD$61,$R124,0) -> 0 | CF124: =IF($O124=$CF$61,$P124,0) -> 0 | CG124: =IF($O124=$CF$61,$R124,0) -> 0 | CH124: =IF($O124=$CH$61,$P124,0) -> 0 | CI124: =IF($O124=$CH$61,$R124,0) -> 0 | CJ124: =IF($O124=$CJ$61,$P124,0) -> 0 | CK124: =IF($O124=$CJ$61,$R124,0) -> 0 | CL124: =IF($O124=$CL$61,$P124,0) -> 0 | CM124: =IF($O124=$CL$61,$R124,0) -> 0 | CN124: =IF($O124=$CN$61,$P124,0) -> 0 | CO124: =IF($O124=$CN$61,$R124,0) -> 0 | CP124: =IF($O124=$CP$61,$P124,0) -> 0 | CQ124: =IF($O124=$CP$61,$R124,0) -> 0 | CR124: =IF($O124=$CR$61,$P124,0) -> 0 | CS124: =IF($O124=$CR$61,$R124,0) -> 0 | CT124: =IF($O124=$CT$61,$P124,0) -> 0 | CU124: =IF($O124=$CT$61,$R124,0) -> 0 | CV124: =IF($O124=$CV$61,$P124,0) -> 0 | CW124: =IF($O124=$CV$61,$R124,0) -> 0 | CX124: =IF($O124=$CX$61,$P124,0) -> 0 | CY124: =IF($O124=$CX$61,$R124,0) -> 0
H125: =S125*1.45 -> 0 | N125: =L125*M125 -> 0 | R125: =Q125*P125 -> 0 | S125: =R125+N125 -> 0 | T125: =IF(H125<>0,1-(S125/H125),0) -> 0 | V125: =IF($K125=$V$61,$L125,0) -> 0 | W125: =IF($K125=$V$61,$N125,0) -> 0 | X125: =IF($K125=$X$61,$L125,0) -> 0 | Y125: =IF($K125=$X$61,$N125,0) -> 0 | Z125: =IF($K125=$Z$61,$L125,0) -> 0 | AA125: =IF($K125=$Z$61,$N125,0) -> 0 | AB125: =IF($K125=$AB$61,$L125,0) -> 0 | AC125: =IF($K125=$AB$61,$N125,0) -> 0 | AD125: =IF($K125=$AD$61,$L125,0) -> 0 | AE125: =IF($K125=$AD$61,$N125,0) -> 0 | AF125: =IF($K125=$AF$61,$L125,0) -> 0 | AG125: =IF($K125=$AF$61,$N125,0) -> 0 | AH125: =IF($K125=$AH$61,$L125,0) -> 0 | AI125: =IF($K125=$AH$61,$N125,0) -> 0 | AJ125: =IF($K125=$AJ$61,$L125,0) -> 0 | AK125: =IF($K125=$AJ$61,$N125,0) -> 0 | AL125: =IF($K125=$AL$61,$L125,0) -> 0 | AM125: =IF($K125=$AL$61,$N125,0) -> 0 | AN125: =IF($K125=$AN$61,$L125,0) -> 0 | AO125: =IF($K125=$AN$61,$N125,0) -> 0 | AP125: =IF($K125=$AP$61,$L125,0) -> 0 | AQ125: =IF($K125=$AP$61,$N125,0) -> 0 | AR125: =IF($K125=$AR$61,$L125,0) -> 0 | AS125: =IF($K125=$AR$61,$N125,0) -> 0 | AT125: =IF($K125=$AT$61,$L125,0) -> 0 | AU125: =IF($K125=$AT$61,$N125,0) -> 0 | AV125: =IF($K125=$AV$61,$L125,0) -> 0 | AW125: =IF($K125=$AV$61,$N125,0) -> 0 | AX125: =IF($K125=$AX$61,$L125,0) -> 0 | AY125: =IF($K125=$AX$61,$N125,0) -> 0 | AZ125: =IF($K125=$AZ$61,$L125,0) -> 0 | BA125: =IF($K125=$AZ$61,$N125,0) -> 0 | BB125: =IF($K125=$BB$61,$L125,0) -> 0 | BC125: =IF($K125=$BB$61,$N125,0) -> 0 | BD125: =IF($O125=$BD$61,$P125,0) -> 0 | BE125: =IF($O125=$BD$61,$R125,0) -> 0 | BF125: =IF($O125=$BF$61,$P125,0) -> 0 | BG125: =IF($O125=$BF$61,$R125,0) -> 0 | BH125: =IF($O125=$BH$61,$P125,0) -> 0 | BI125: =IF($O125=$BH$61,$R125,0) -> 0 | BJ125: =IF($O125=$BJ$61,$P125,0) -> 0 | BK125: =IF($O125=$BJ$61,$R125,0) -> 0 | BL125: =IF($O125=$BL$61,$P125,0) -> 0 | BM125: =IF($O125=$BL$61,$R125,0) -> 0 | BN125: =IF($O125=$BN$61,$P125,0) -> 0 | BO125: =IF($O125=$BN$61,$R125,0) -> 0 | BP125: =IF($O125=$BP$61,$P125,0) -> 0 | BQ125: =IF($O125=$BP$61,$R125,0) -> 0 | BR125: =IF($O125=$BR$61,$P125,0) -> 0 | BS125: =IF($O125=$BR$61,$R125,0) -> 0 | BT125: =IF($O125=$BT$61,$P125,0) -> 0 | BU125: =IF($O125=$BT$61,$R125,0) -> 0 | BV125: =IF($O125=$BV$61,$P125,0) -> 0 | BW125: =IF($O125=$BV$61,$R125,0) -> 0 | BX125: =IF($O125=$BX$61,$P125,0) -> 0 | BY125: =IF($O125=$BX$61,$R125,0) -> 0 | BZ125: =IF($O125=$BZ$61,$P125,0) -> 0 | CA125: =IF($O125=$BZ$61,$R125,0) -> 0 | CB125: =IF($O125=$CB$61,$P125,0) -> 0 | CC125: =IF($O125=$CB$61,$R125,0) -> 0 | CD125: =IF($O125=$CD$61,$P125,0) -> 0 | CE125: =IF($O125=$CD$61,$R125,0) -> 0 | CF125: =IF($O125=$CF$61,$P125,0) -> 0 | CG125: =IF($O125=$CF$61,$R125,0) -> 0 | CH125: =IF($O125=$CH$61,$P125,0) -> 0 | CI125: =IF($O125=$CH$61,$R125,0) -> 0 | CJ125: =IF($O125=$CJ$61,$P125,0) -> 0 | CK125: =IF($O125=$CJ$61,$R125,0) -> 0 | CL125: =IF($O125=$CL$61,$P125,0) -> 0 | CM125: =IF($O125=$CL$61,$R125,0) -> 0 | CN125: =IF($O125=$CN$61,$P125,0) -> 0 | CO125: =IF($O125=$CN$61,$R125,0) -> 0 | CP125: =IF($O125=$CP$61,$P125,0) -> 0 | CQ125: =IF($O125=$CP$61,$R125,0) -> 0 | CR125: =IF($O125=$CR$61,$P125,0) -> 0 | CS125: =IF($O125=$CR$61,$R125,0) -> 0 | CT125: =IF($O125=$CT$61,$P125,0) -> 0 | CU125: =IF($O125=$CT$61,$R125,0) -> 0 | CV125: =IF($O125=$CV$61,$P125,0) -> 0 | CW125: =IF($O125=$CV$61,$R125,0) -> 0 | CX125: =IF($O125=$CX$61,$P125,0) -> 0 | CY125: =IF($O125=$CX$61,$R125,0) -> 0
H126: =S126*1.45 -> 0 | N126: =L126*M126 -> 0 | R126: =Q126*P126 -> 0 | S126: =R126+N126 -> 0 | T126: =IF(H126<>0,1-(S126/H126),0) -> 0 | V126: =IF($K126=$V$61,$L126,0) -> 0 | W126: =IF($K126=$V$61,$N126,0) -> 0 | X126: =IF($K126=$X$61,$L126,0) -> 0 | Y126: =IF($K126=$X$61,$N126,0) -> 0 | Z126: =IF($K126=$Z$61,$L126,0) -> 0 | AA126: =IF($K126=$Z$61,$N126,0) -> 0 | AB126: =IF($K126=$AB$61,$L126,0) -> 0 | AC126: =IF($K126=$AB$61,$N126,0) -> 0 | AD126: =IF($K126=$AD$61,$L126,0) -> 0 | AE126: =IF($K126=$AD$61,$N126,0) -> 0 | AF126: =IF($K126=$AF$61,$L126,0) -> 0 | AG126: =IF($K126=$AF$61,$N126,0) -> 0 | AH126: =IF($K126=$AH$61,$L126,0) -> 0 | AI126: =IF($K126=$AH$61,$N126,0) -> 0 | AJ126: =IF($K126=$AJ$61,$L126,0) -> 0 | AK126: =IF($K126=$AJ$61,$N126,0) -> 0 | AL126: =IF($K126=$AL$61,$L126,0) -> 0 | AM126: =IF($K126=$AL$61,$N126,0) -> 0 | AN126: =IF($K126=$AN$61,$L126,0) -> 0 | AO126: =IF($K126=$AN$61,$N126,0) -> 0 | AP126: =IF($K126=$AP$61,$L126,0) -> 0 | AQ126: =IF($K126=$AP$61,$N126,0) -> 0 | AR126: =IF($K126=$AR$61,$L126,0) -> 0 | AS126: =IF($K126=$AR$61,$N126,0) -> 0 | AT126: =IF($K126=$AT$61,$L126,0) -> 0 | AU126: =IF($K126=$AT$61,$N126,0) -> 0 | AV126: =IF($K126=$AV$61,$L126,0) -> 0 | AW126: =IF($K126=$AV$61,$N126,0) -> 0 | AX126: =IF($K126=$AX$61,$L126,0) -> 0 | AY126: =IF($K126=$AX$61,$N126,0) -> 0 | AZ126: =IF($K126=$AZ$61,$L126,0) -> 0 | BA126: =IF($K126=$AZ$61,$N126,0) -> 0 | BB126: =IF($K126=$BB$61,$L126,0) -> 0 | BC126: =IF($K126=$BB$61,$N126,0) -> 0 | BD126: =IF($O126=$BD$61,$P126,0) -> 0 | BE126: =IF($O126=$BD$61,$R126,0) -> 0 | BF126: =IF($O126=$BF$61,$P126,0) -> 0 | BG126: =IF($O126=$BF$61,$R126,0) -> 0 | BH126: =IF($O126=$BH$61,$P126,0) -> 0 | BI126: =IF($O126=$BH$61,$R126,0) -> 0 | BJ126: =IF($O126=$BJ$61,$P126,0) -> 0 | BK126: =IF($O126=$BJ$61,$R126,0) -> 0 | BL126: =IF($O126=$BL$61,$P126,0) -> 0 | BM126: =IF($O126=$BL$61,$R126,0) -> 0 | BN126: =IF($O126=$BN$61,$P126,0) -> 0 | BO126: =IF($O126=$BN$61,$R126,0) -> 0 | BP126: =IF($O126=$BP$61,$P126,0) -> 0 | BQ126: =IF($O126=$BP$61,$R126,0) -> 0 | BR126: =IF($O126=$BR$61,$P126,0) -> 0 | BS126: =IF($O126=$BR$61,$R126,0) -> 0 | BT126: =IF($O126=$BT$61,$P126,0) -> 0 | BU126: =IF($O126=$BT$61,$R126,0) -> 0 | BV126: =IF($O126=$BV$61,$P126,0) -> 0 | BW126: =IF($O126=$BV$61,$R126,0) -> 0 | BX126: =IF($O126=$BX$61,$P126,0) -> 0 | BY126: =IF($O126=$BX$61,$R126,0) -> 0 | BZ126: =IF($O126=$BZ$61,$P126,0) -> 0 | CA126: =IF($O126=$BZ$61,$R126,0) -> 0 | CB126: =IF($O126=$CB$61,$P126,0) -> 0 | CC126: =IF($O126=$CB$61,$R126,0) -> 0 | CD126: =IF($O126=$CD$61,$P126,0) -> 0 | CE126: =IF($O126=$CD$61,$R126,0) -> 0 | CF126: =IF($O126=$CF$61,$P126,0) -> 0 | CG126: =IF($O126=$CF$61,$R126,0) -> 0 | CH126: =IF($O126=$CH$61,$P126,0) -> 0 | CI126: =IF($O126=$CH$61,$R126,0) -> 0 | CJ126: =IF($O126=$CJ$61,$P126,0) -> 0 | CK126: =IF($O126=$CJ$61,$R126,0) -> 0 | CL126: =IF($O126=$CL$61,$P126,0) -> 0 | CM126: =IF($O126=$CL$61,$R126,0) -> 0 | CN126: =IF($O126=$CN$61,$P126,0) -> 0 | CO126: =IF($O126=$CN$61,$R126,0) -> 0 | CP126: =IF($O126=$CP$61,$P126,0) -> 0 | CQ126: =IF($O126=$CP$61,$R126,0) -> 0 | CR126: =IF($O126=$CR$61,$P126,0) -> 0 | CS126: =IF($O126=$CR$61,$R126,0) -> 0 | CT126: =IF($O126=$CT$61,$P126,0) -> 0 | CU126: =IF($O126=$CT$61,$R126,0) -> 0 | CV126: =IF($O126=$CV$61,$P126,0) -> 0 | CW126: =IF($O126=$CV$61,$R126,0) -> 0 | CX126: =IF($O126=$CX$61,$P126,0) -> 0 | CY126: =IF($O126=$CX$61,$R126,0) -> 0
... H133: =S133*1.45 -> 0 | N133: =L133*M133 -> 0 | R133: =Q133*P133 -> 0 | S133: =R133+N133 -> 0 | T133: =IF(H133<>0,1-(S133/H133),0) -> 0 | V133: =IF($K133=$V$61,$L133,0) -> 0 | W133: =IF($K133=$V$61,$N133,0) -> 0 | X133: =IF($K133=$X$61,$L133,0) -> 0 | Y133: =IF($K133=$X$61,$N133,0) -> 0 | Z133: =IF($K133=$Z$61,$L133,0) -> 0 | AA133: =IF($K133=$Z$61,$N133,0) -> 0 | AB133: =IF($K133=$AB$61,$L133,0) -> 0 | AC133: =IF($K133=$AB$61,$N133,0) -> 0 | AD133: =IF($K133=$AD$61,$L133,0) -> 0 | AE133: =IF($K133=$AD$61,$N133,0) -> 0 | AF133: =IF($K133=$AF$61,$L133,0) -> 0 | AG133: =IF($K133=$AF$61,$N133,0) -> 0 | AH133: =IF($K133=$AH$61,$L133,0) -> 0 | AI133: =IF($K133=$AH$61,$N133,0) -> 0 | AJ133: =IF($K133=$AJ$61,$L133,0) -> 0 | AK133: =IF($K133=$AJ$61,$N133,0) -> 0 | AL133: =IF($K133=$AL$61,$L133,0) -> 0 | AM133: =IF($K133=$AL$61,$N133,0) -> 0 | AN133: =IF($K133=$AN$61,$L133,0) -> 0 | AO133: =IF($K133=$AN$61,$N133,0) -> 0 | AP133: =IF($K133=$AP$61,$L133,0) -> 0 | AQ133: =IF($K133=$AP$61,$N133,0) -> 0 | AR133: =IF($K133=$AR$61,$L133,0) -> 0 | AS133: =IF($K133=$AR$61,$N133,0) -> 0 | AT133: =IF($K133=$AT$61,$L133,0) -> 0 | AU133: =IF($K133=$AT$61,$N133,0) -> 0 | AV133: =IF($K133=$AV$61,$L133,0) -> 0 | AW133: =IF($K133=$AV$61,$N133,0) -> 0 | AX133: =IF($K133=$AX$61,$L133,0) -> 0 | AY133: =IF($K133=$AX$61,$N133,0) -> 0 | AZ133: =IF($K133=$AZ$61,$L133,0) -> 0 | BA133: =IF($K133=$AZ$61,$N133,0) -> 0 | BB133: =IF($K133=$BB$61,$L133,0) -> 0 | BC133: =IF($K133=$BB$61,$N133,0) -> 0 | BD133: =IF($O133=$BD$61,$P133,0) -> 0 | BE133: =IF($O133=$BD$61,$R133,0) -> 0 | BF133: =IF($O133=$BF$61,$P133,0) -> 0 | BG133: =IF($O133=$BF$61,$R133,0) -> 0 | BH133: =IF($O133=$BH$61,$P133,0) -> 0 | BI133: =IF($O133=$BH$61,$R133,0) -> 0 | BJ133: =IF($O133=$BJ$61,$P133,0) -> 0 | BK133: =IF($O133=$BJ$61,$R133,0) -> 0 | BL133: =IF($O133=$BL$61,$P133,0) -> 0 | BM133: =IF($O133=$BL$61,$R133,0) -> 0 | BN133: =IF($O133=$BN$61,$P133,0) -> 0 | BO133: =IF($O133=$BN$61,$R133,0) -> 0 | BP133: =IF($O133=$BP$61,$P133,0) -> 0 | BQ133: =IF($O133=$BP$61,$R133,0) -> 0 | BR133: =IF($O133=$BR$61,$P133,0) -> 0 | BS133: =IF($O133=$BR$61,$R133,0) -> 0 | BT133: =IF($O133=$BT$61,$P133,0) -> 0 | BU133: =IF($O133=$BT$61,$R133,0) -> 0 | BV133: =IF($O133=$BV$61,$P133,0) -> 0 | BW133: =IF($O133=$BV$61,$R133,0) -> 0 | BX133: =IF($O133=$BX$61,$P133,0) -> 0 | BY133: =IF($O133=$BX$61,$R133,0) -> 0 | BZ133: =IF($O133=$BZ$61,$P133,0) -> 0 | CA133: =IF($O133=$BZ$61,$R133,0) -> 0 | CB133: =IF($O133=$CB$61,$P133,0) -> 0 | CC133: =IF($O133=$CB$61,$R133,0) -> 0 | CD133: =IF($O133=$CD$61,$P133,0) -> 0 | CE133: =IF($O133=$CD$61,$R133,0) -> 0 | CF133: =IF($O133=$CF$61,$P133,0) -> 0 | CG133: =IF($O133=$CF$61,$R133,0) -> 0 | CH133: =IF($O133=$CH$61,$P133,0) -> 0 | CI133: =IF($O133=$CH$61,$R133,0) -> 0 | CJ133: =IF($O133=$CJ$61,$P133,0) -> 0 | CK133: =IF($O133=$CJ$61,$R133,0) -> 0 | CL133: =IF($O133=$CL$61,$P133,0) -> 0 | CM133: =IF($O133=$CL$61,$R133,0) -> 0 | CN133: =IF($O133=$CN$61,$P133,0) -> 0 | CO133: =IF($O133=$CN$61,$R133,0) -> 0 | CP133: =IF($O133=$CP$61,$P133,0) -> 0 | CQ133: =IF($O133=$CP$61,$R133,0) -> 0 | CR133: =IF($O133=$CR$61,$P133,0) -> 0 | CS133: =IF($O133=$CR$61,$R133,0) -> 0 | CT133: =IF($O133=$CT$61,$P133,0) -> 0 | CU133: =IF($O133=$CT$61,$R133,0) -> 0 | CV133: =IF($O133=$CV$61,$P133,0) -> 0 | CW133: =IF($O133=$CV$61,$R133,0) -> 0 | CX133: =IF($O133=$CX$61,$P133,0) -> 0 | CY133: =IF($O133=$CX$61,$R133,0) -> 0
C134: 小 計 | H134: =SUM(H115:H133) -> 0 | K134: 計 | N134: =L134*M134 -> 0 | R134: ﾍﾟｰｼﾞ計 | S134: =SUM(S114:S133) -> 0 | T134: =IF(H134<>0,1-(S134/H134),0) -> 0 | V134: =IF($K134=$V$61,$L134,0) -> 0 | W134: =IF($K134=$V$61,$N134,0) -> 0 | X134: =IF($K134=$X$61,$L134,0) -> 0 | Y134: =IF($K134=$X$61,$N134,0) -> 0 | Z134: =IF($K134=$Z$61,$L134,0) -> 0 | AA134: =IF($K134=$Z$61,$N134,0) -> 0 | AB134: =IF($K134=$AB$61,$L134,0) -> 0 | AC134: =IF($K134=$AB$61,$N134,0) -> 0 | AD134: =IF($K134=$AD$61,$L134,0) -> 0 | AE134: =IF($K134=$AD$61,$N134,0) -> 0 | AF134: =IF($K134=$AF$61,$L134,0) -> 0 | AG134: =IF($K134=$AF$61,$N134,0) -> 0 | AH134: =IF($K134=$AH$61,$L134,0) -> 0 | AI134: =IF($K134=$AH$61,$N134,0) -> 0 | AJ134: =IF($K134=$AJ$61,$L134,0) -> 0 | AK134: =IF($K134=$AJ$61,$N134,0) -> 0 | AL134: =IF($K134=$AL$61,$L134,0) -> 0 | AM134: =IF($K134=$AL$61,$N134,0) -> 0 | AN134: =IF($K134=$AN$61,$L134,0) -> 0 | AO134: =IF($K134=$AN$61,$N134,0) -> 0 | AP134: =IF($K134=$AP$61,$L134,0) -> 0 | AQ134: =IF($K134=$AP$61,$N134,0) -> 0 | AR134: =IF($K134=$AR$61,$L134,0) -> 0 | AS134: =IF($K134=$AR$61,$N134,0) -> 0 | AT134: =IF($K134=$AT$61,$L134,0) -> 0 | AU134: =IF($K134=$AT$61,$N134,0) -> 0 | AV134: =IF($K134=$AV$61,$L134,0) -> 0 | AW134: =IF($K134=$AV$61,$N134,0) -> 0 | AX134: =IF($K134=$AX$61,$L134,0) -> 0 | AY134: =IF($K134=$AX$61,$N134,0) -> 0 | AZ134: =IF($K134=$AZ$61,$L134,0) -> 0 | BA134: =IF($K134=$AZ$61,$N134,0) -> 0 | BB134: =IF($K134=$BB$61,$L134,0) -> 0 | BC134: =IF($K134=$BB$61,$N134,0) -> 0 | BD134: =IF($O134=$BD$61,$P134,0) -> 0 | BE134: =IF($O134=$BD$61,$R134,0) -> 0 | BF134: =IF($O134=$BF$61,$P134,0) -> 0 | BG134: =IF($O134=$BF$61,$R134,0) -> 0 | BH134: =IF($O134=$BH$61,$P134,0) -> 0 | BI134: =IF($O134=$BH$61,$R134,0) -> 0 | BJ134: =IF($O134=$BJ$61,$P134,0) -> 0 | BK134: =IF($O134=$BJ$61,$R134,0) -> 0 | BL134: =IF($O134=$BL$61,$P134,0) -> 0 | BM134: =IF($O134=$BL$61,$R134,0) -> 0 | BN134: =IF($O134=$BN$61,$P134,0) -> 0 | BO134: =IF($O134=$BN$61,$R134,0) -> 0 | BP134: =IF($O134=$BP$61,$P134,0) -> 0 | BQ134: =IF($O134=$BP$61,$R134,0) -> 0 | BR134: =IF($O134=$BR$61,$P134,0) -> 0 | BS134: =IF($O134=$BR$61,$R134,0) -> 0 | BT134: =IF($O134=$BT$61,$P134,0) -> 0 | BU134: =IF($O134=$BT$61,$R134,0) -> 0 | BV134: =IF($O134=$BV$61,$P134,0) -> 0 | BW134: =IF($O134=$BV$61,$R134,0) -> 0 | BX134: =IF($O134=$BX$61,$P134,0) -> 0 | BY134: =IF($O134=$BX$61,$R134,0) -> 0 | BZ134: =IF($O134=$BZ$61,$P134,0) -> 0 | CA134: =IF($O134=$BZ$61,$R134,0) -> 0 | CB134: =IF($O134=$CB$61,$P134,0) -> 0 | CC134: =IF($O134=$CB$61,$R134,0) -> 0 | CD134: =IF($O134=$CD$61,$P134,0) -> 0 | CE134: =IF($O134=$CD$61,$R134,0) -> 0 | CF134: =IF($O134=$CF$61,$P134,0) -> 0 | CG134: =IF($O134=$CF$61,$R134,0) -> 0 | CH134: =IF($O134=$CH$61,$P134,0) -> 0 | CI134: =IF($O134=$CH$61,$R134,0) -> 0 | CJ134: =IF($O134=$CJ$61,$P134,0) -> 0 | CK134: =IF($O134=$CJ$61,$R134,0) -> 0 | CL134: =IF($O134=$CL$61,$P134,0) -> 0 | CM134: =IF($O134=$CL$61,$R134,0) -> 0 | CN134: =IF($O134=$CN$61,$P134,0) -> 0 | CO134: =IF($O134=$CN$61,$R134,0) -> 0 | CP134: =IF($O134=$CP$61,$P134,0) -> 0 | CQ134: =IF($O134=$CP$61,$R134,0) -> 0 | CR134: =IF($O134=$CR$61,$P134,0) -> 0 | CS134: =IF($O134=$CR$61,$R134,0) -> 0 | CT134: =IF($O134=$CT$61,$P134,0) -> 0 | CU134: =IF($O134=$CT$61,$R134,0) -> 0 | CV134: =IF($O134=$CV$61,$P134,0) -> 0 | CW134: =IF($O134=$CV$61,$R134,0) -> 0 | CX134: =IF($O134=$CX$61,$P134,0) -> 0 | CY134: =IF($O134=$CX$61,$R134,0) -> 0
N135: =L135*M135 -> 0 | R135: =P135*Q135 -> 0 | S135: =N135+R135 -> 0 | T135: =IF(H135<>0,1-(S135/H135),0) -> 0 | V135: =IF($K135=$V$61,$L135,0) -> 0 | W135: =IF($K135=$V$61,$N135,0) -> 0 | X135: =IF($K135=$X$61,$L135,0) -> 0 | Y135: =IF($K135=$X$61,$N135,0) -> 0 | Z135: =IF($K135=$Z$61,$L135,0) -> 0 | AA135: =IF($K135=$Z$61,$N135,0) -> 0 | AB135: =IF($K135=$AB$61,$L135,0) -> 0 | AC135: =IF($K135=$AB$61,$N135,0) -> 0 | AD135: =IF($K135=$AD$61,$L135,0) -> 0 | AE135: =IF($K135=$AD$61,$N135,0) -> 0 | AF135: =IF($K135=$AF$61,$L135,0) -> 0 | AG135: =IF($K135=$AF$61,$N135,0) -> 0 | AH135: =IF($K135=$AH$61,$L135,0) -> 0 | AI135: =IF($K135=$AH$61,$N135,0) -> 0 | AJ135: =IF($K135=$AJ$61,$L135,0) -> 0 | AK135: =IF($K135=$AJ$61,$N135,0) -> 0 | AL135: =IF($K135=$AL$61,$L135,0) -> 0 | AM135: =IF($K135=$AL$61,$N135,0) -> 0 | AN135: =IF($K135=$AN$61,$L135,0) -> 0 | AO135: =IF($K135=$AN$61,$N135,0) -> 0 | AP135: =IF($K135=$AP$61,$L135,0) -> 0 | AQ135: =IF($K135=$AP$61,$N135,0) -> 0 | AR135: =IF($K135=$AR$61,$L135,0) -> 0 | AS135: =IF($K135=$AR$61,$N135,0) -> 0 | AT135: =IF($K135=$AT$61,$L135,0) -> 0 | AU135: =IF($K135=$AT$61,$N135,0) -> 0 | AV135: =IF($K135=$AV$61,$L135,0) -> 0 | AW135: =IF($K135=$AV$61,$N135,0) -> 0 | AX135: =IF($K135=$AX$61,$L135,0) -> 0 | AY135: =IF($K135=$AX$61,$N135,0) -> 0 | AZ135: =IF($K135=$AZ$61,$L135,0) -> 0 | BA135: =IF($K135=$AZ$61,$N135,0) -> 0 | BB135: =IF($K135=$BB$61,$L135,0) -> 0 | BC135: =IF($K135=$BB$61,$N135,0) -> 0 | BD135: =IF($O135=$BD$61,$P135,0) -> 0 | BE135: =IF($O135=$BD$61,$R135,0) -> 0 | BF135: =IF($O135=$BF$61,$P135,0) -> 0 | BG135: =IF($O135=$BF$61,$R135,0) -> 0 | BH135: =IF($O135=$BH$61,$P135,0) -> 0 | BI135: =IF($O135=$BH$61,$R135,0) -> 0 | BJ135: =IF($O135=$BJ$61,$P135,0) -> 0 | BK135: =IF($O135=$BJ$61,$R135,0) -> 0 | BL135: =IF($O135=$BL$61,$P135,0) -> 0 | BM135: =IF($O135=$BL$61,$R135,0) -> 0 | BN135: =IF($O135=$BN$61,$P135,0) -> 0 | BO135: =IF($O135=$BN$61,$R135,0) -> 0 | BP135: =IF($O135=$BP$61,$P135,0) -> 0 | BQ135: =IF($O135=$BP$61,$R135,0) -> 0 | BR135: =IF($O135=$BR$61,$P135,0) -> 0 | BS135: =IF($O135=$BR$61,$R135,0) -> 0 | BT135: =IF($O135=$BT$61,$P135,0) -> 0 | BU135: =IF($O135=$BT$61,$R135,0) -> 0 | BV135: =IF($O135=$BV$61,$P135,0) -> 0 | BW135: =IF($O135=$BV$61,$R135,0) -> 0 | BX135: =IF($O135=$BX$61,$P135,0) -> 0 | BY135: =IF($O135=$BX$61,$R135,0) -> 0 | BZ135: =IF($O135=$BZ$61,$P135,0) -> 0 | CA135: =IF($O135=$BZ$61,$R135,0) -> 0 | CB135: =IF($O135=$CB$61,$P135,0) -> 0 | CC135: =IF($O135=$CB$61,$R135,0) -> 0 | CD135: =IF($O135=$CD$61,$P135,0) -> 0 | CE135: =IF($O135=$CD$61,$R135,0) -> 0 | CF135: =IF($O135=$CF$61,$P135,0) -> 0 | CG135: =IF($O135=$CF$61,$R135,0) -> 0 | CH135: =IF($O135=$CH$61,$P135,0) -> 0 | CI135: =IF($O135=$CH$61,$R135,0) -> 0 | CJ135: =IF($O135=$CJ$61,$P135,0) -> 0 | CK135: =IF($O135=$CJ$61,$R135,0) -> 0 | CL135: =IF($O135=$CL$61,$P135,0) -> 0 | CM135: =IF($O135=$CL$61,$R135,0) -> 0 | CN135: =IF($O135=$CN$61,$P135,0) -> 0 | CO135: =IF($O135=$CN$61,$R135,0) -> 0 | CP135: =IF($O135=$CP$61,$P135,0) -> 0 | CQ135: =IF($O135=$CP$61,$R135,0) -> 0 | CR135: =IF($O135=$CR$61,$P135,0) -> 0 | CS135: =IF($O135=$CR$61,$R135,0) -> 0 | CT135: =IF($O135=$CT$61,$P135,0) -> 0 | CU135: =IF($O135=$CT$61,$R135,0) -> 0 | CV135: =IF($O135=$CV$61,$P135,0) -> 0 | CW135: =IF($O135=$CV$61,$R135,0) -> 0 | CX135: =IF($O135=$CX$61,$P135,0) -> 0 | CY135: =IF($O135=$CX$61,$R135,0) -> 0
I136: ラグズ建築 | N136: =L136*M136 -> 0 | R136: =P136*Q136 -> 0 | S136: =N136+R136 -> 0 | V136: =IF($K136=$V$61,$L136,0) -> 0 | W136: =IF($K136=$V$61,$N136,0) -> 0 | X136: =IF($K136=$X$61,$L136,0) -> 0 | Y136: =IF($K136=$X$61,$N136,0) -> 0 | Z136: =IF($K136=$Z$61,$L136,0) -> 0 | AA136: =IF($K136=$Z$61,$N136,0) -> 0 | AB136: =IF($K136=$AB$61,$L136,0) -> 0 | AC136: =IF($K136=$AB$61,$N136,0) -> 0 | AD136: =IF($K136=$AD$61,$L136,0) -> 0 | AE136: =IF($K136=$AD$61,$N136,0) -> 0 | AF136: =IF($K136=$AF$61,$L136,0) -> 0 | AG136: =IF($K136=$AF$61,$N136,0) -> 0 | AH136: =IF($K136=$AH$61,$L136,0) -> 0 | AI136: =IF($K136=$AH$61,$N136,0) -> 0 | AJ136: =IF($K136=$AJ$61,$L136,0) -> 0 | AK136: =IF($K136=$AJ$61,$N136,0) -> 0 | AL136: =IF($K136=$AL$61,$L136,0) -> 0 | AM136: =IF($K136=$AL$61,$N136,0) -> 0 | AN136: =IF($K136=$AN$61,$L136,0) -> 0 | AO136: =IF($K136=$AN$61,$N136,0) -> 0 | AP136: =IF($K136=$AP$61,$L136,0) -> 0 | AQ136: =IF($K136=$AP$61,$N136,0) -> 0 | AR136: =IF($K136=$AR$61,$L136,0) -> 0 | AS136: =IF($K136=$AR$61,$N136,0) -> 0 | AT136: =IF($K136=$AT$61,$L136,0) -> 0 | AU136: =IF($K136=$AT$61,$N136,0) -> 0 | AV136: =IF($K136=$AV$61,$L136,0) -> 0 | AW136: =IF($K136=$AV$61,$N136,0) -> 0 | AX136: =IF($K136=$AX$61,$L136,0) -> 0 | AY136: =IF($K136=$AX$61,$N136,0) -> 0 | AZ136: =IF($K136=$AZ$61,$L136,0) -> 0 | BA136: =IF($K136=$AZ$61,$N136,0) -> 0 | BB136: =IF($K136=$BB$61,$L136,0) -> 0 | BC136: =IF($K136=$BB$61,$N136,0) -> 0 | BD136: =IF($O136=$BD$61,$P136,0) -> 0 | BE136: =IF($O136=$BD$61,$R136,0) -> 0 | BF136: =IF($O136=$BF$61,$P136,0) -> 0 | BG136: =IF($O136=$BF$61,$R136,0) -> 0 | BH136: =IF($O136=$BH$61,$P136,0) -> 0 | BI136: =IF($O136=$BH$61,$R136,0) -> 0 | BJ136: =IF($O136=$BJ$61,$P136,0) -> 0 | BK136: =IF($O136=$BJ$61,$R136,0) -> 0 | BL136: =IF($O136=$BL$61,$P136,0) -> 0 | BM136: =IF($O136=$BL$61,$R136,0) -> 0 | BN136: =IF($O136=$BN$61,$P136,0) -> 0 | BO136: =IF($O136=$BN$61,$R136,0) -> 0 | BP136: =IF($O136=$BP$61,$P136,0) -> 0 | BQ136: =IF($O136=$BP$61,$R136,0) -> 0 | BR136: =IF($O136=$BR$61,$P136,0) -> 0 | BS136: =IF($O136=$BR$61,$R136,0) -> 0 | BT136: =IF($O136=$BT$61,$P136,0) -> 0 | BU136: =IF($O136=$BT$61,$R136,0) -> 0 | BV136: =IF($O136=$BV$61,$P136,0) -> 0 | BW136: =IF($O136=$BV$61,$R136,0) -> 0 | BX136: =IF($O136=$BX$61,$P136,0) -> 0 | BY136: =IF($O136=$BX$61,$R136,0) -> 0 | BZ136: =IF($O136=$BZ$61,$P136,0) -> 0 | CA136: =IF($O136=$BZ$61,$R136,0) -> 0 | CB136: =IF($O136=$CB$61,$P136,0) -> 0 | CC136: =IF($O136=$CB$61,$R136,0) -> 0 | CD136: =IF($O136=$CD$61,$P136,0) -> 0 | CE136: =IF($O136=$CD$61,$R136,0) -> 0 | CF136: =IF($O136=$CF$61,$P136,0) -> 0 | CG136: =IF($O136=$CF$61,$R136,0) -> 0 | CH136: =IF($O136=$CH$61,$P136,0) -> 0 | CI136: =IF($O136=$CH$61,$R136,0) -> 0 | CJ136: =IF($O136=$CJ$61,$P136,0) -> 0 | CK136: =IF($O136=$CJ$61,$R136,0) -> 0 | CL136: =IF($O136=$CL$61,$P136,0) -> 0 | CM136: =IF($O136=$CL$61,$R136,0) -> 0 | CN136: =IF($O136=$CN$61,$P136,0) -> 0 | CO136: =IF($O136=$CN$61,$R136,0) -> 0 | CP136: =IF($O136=$CP$61,$P136,0) -> 0 | CQ136: =IF($O136=$CP$61,$R136,0) -> 0 | CR136: =IF($O136=$CR$61,$P136,0) -> 0 | CS136: =IF($O136=$CR$61,$R136,0) -> 0 | CT136: =IF($O136=$CT$61,$P136,0) -> 0 | CU136: =IF($O136=$CT$61,$R136,0) -> 0 | CV136: =IF($O136=$CV$61,$P136,0) -> 0 | CW136: =IF($O136=$CV$61,$R136,0) -> 0 | CX136: =IF($O136=$CX$61,$P136,0) -> 0 | CY136: =IF($O136=$CX$61,$R136,0) -> 0
A137: =A33 -> 0 | B137: =B33 -> 0 | E137: 内 訳 明 細 書 | J137: 5 | K137: 日付 | N137: =L137*M137 -> 0 | R137: =P137*Q137 -> 0 | S137: =N137+R137 -> 0 | V137: =IF($K137=$V$61,$L137,0) -> 0 | W137: =IF($K137=$V$61,$N137,0) -> 0 | X137: =IF($K137=$X$61,$L137,0) -> 0 | Y137: =IF($K137=$X$61,$N137,0) -> 0 | Z137: =IF($K137=$Z$61,$L137,0) -> 0 | AA137: =IF($K137=$Z$61,$N137,0) -> 0 | AB137: =IF($K137=$AB$61,$L137,0) -> 0 | AC137: =IF($K137=$AB$61,$N137,0) -> 0 | AD137: =IF($K137=$AD$61,$L137,0) -> 0 | AE137: =IF($K137=$AD$61,$N137,0) -> 0 | AF137: =IF($K137=$AF$61,$L137,0) -> 0 | AG137: =IF($K137=$AF$61,$N137,0) -> 0 | AH137: =IF($K137=$AH$61,$L137,0) -> 0 | AI137: =IF($K137=$AH$61,$N137,0) -> 0 | AJ137: =IF($K137=$AJ$61,$L137,0) -> 0 | AK137: =IF($K137=$AJ$61,$N137,0) -> 0 | AL137: =IF($K137=$AL$61,$L137,0) -> 0 | AM137: =IF($K137=$AL$61,$N137,0) -> 0 | AN137: =IF($K137=$AN$61,$L137,0) -> 0 | AO137: =IF($K137=$AN$61,$N137,0) -> 0 | AP137: =IF($K137=$AP$61,$L137,0) -> 0 | AQ137: =IF($K137=$AP$61,$N137,0) -> 0 | AR137: =IF($K137=$AR$61,$L137,0) -> 0 | AS137: =IF($K137=$AR$61,$N137,0) -> 0 | AT137: =IF($K137=$AT$61,$L137,0) -> 0 | AU137: =IF($K137=$AT$61,$N137,0) -> 0 | AV137: =IF($K137=$AV$61,$L137,0) -> 0 | AW137: =IF($K137=$AV$61,$N137,0) -> 0 | AX137: =IF($K137=$AX$61,$L137,0) -> 0 | AY137: =IF($K137=$AX$61,$N137,0) -> 0 | AZ137: =IF($K137=$AZ$61,$L137,0) -> 0 | BA137: =IF($K137=$AZ$61,$N137,0) -> 0 | BB137: =IF($K137=$BB$61,$L137,0) -> 0 | BC137: =IF($K137=$BB$61,$N137,0) -> 0 | BD137: =IF($O137=$BD$61,$P137,0) -> 0 | BE137: =IF($O137=$BD$61,$R137,0) -> 0 | BF137: =IF($O137=$BF$61,$P137,0) -> 0 | BG137: =IF($O137=$BF$61,$R137,0) -> 0 | BH137: =IF($O137=$BH$61,$P137,0) -> 0 | BI137: =IF($O137=$BH$61,$R137,0) -> 0 | BJ137: =IF($O137=$BJ$61,$P137,0) -> 0 | BK137: =IF($O137=$BJ$61,$R137,0) -> 0 | BL137: =IF($O137=$BL$61,$P137,0) -> 0 | BM137: =IF($O137=$BL$61,$R137,0) -> 0 | BN137: =IF($O137=$BN$61,$P137,0) -> 0 | BO137: =IF($O137=$BN$61,$R137,0) -> 0 | BP137: =IF($O137=$BP$61,$P137,0) -> 0 | BQ137: =IF($O137=$BP$61,$R137,0) -> 0 | BR137: =IF($O137=$BR$61,$P137,0) -> 0 | BS137: =IF($O137=$BR$61,$R137,0) -> 0 | BT137: =IF($O137=$BT$61,$P137,0) -> 0 | BU137: =IF($O137=$BT$61,$R137,0) -> 0 | BV137: =IF($O137=$BV$61,$P137,0) -> 0 | BW137: =IF($O137=$BV$61,$R137,0) -> 0 | BX137: =IF($O137=$BX$61,$P137,0) -> 0 | BY137: =IF($O137=$BX$61,$R137,0) -> 0 | BZ137: =IF($O137=$BZ$61,$P137,0) -> 0 | CA137: =IF($O137=$BZ$61,$R137,0) -> 0 | CB137: =IF($O137=$CB$61,$P137,0) -> 0 | CC137: =IF($O137=$CB$61,$R137,0) -> 0 | CD137: =IF($O137=$CD$61,$P137,0) -> 0 | CE137: =IF($O137=$CD$61,$R137,0) -> 0 | CF137: =IF($O137=$CF$61,$P137,0) -> 0 | CG137: =IF($O137=$CF$61,$R137,0) -> 0 | CH137: =IF($O137=$CH$61,$P137,0) -> 0 | CI137: =IF($O137=$CH$61,$R137,0) -> 0 | CJ137: =IF($O137=$CJ$61,$P137,0) -> 0 | CK137: =IF($O137=$CJ$61,$R137,0) -> 0 | CL137: =IF($O137=$CL$61,$P137,0) -> 0 | CM137: =IF($O137=$CL$61,$R137,0) -> 0 | CN137: =IF($O137=$CN$61,$P137,0) -> 0 | CO137: =IF($O137=$CN$61,$R137,0) -> 0 | CP137: =IF($O137=$CP$61,$P137,0) -> 0 | CQ137: =IF($O137=$CP$61,$R137,0) -> 0 | CR137: =IF($O137=$CR$61,$P137,0) -> 0 | CS137: =IF($O137=$CR$61,$R137,0) -> 0 | CT137: =IF($O137=$CT$61,$P137,0) -> 0 | CU137: =IF($O137=$CT$61,$R137,0) -> 0 | CV137: =IF($O137=$CV$61,$P137,0) -> 0 | CW137: =IF($O137=$CV$61,$R137,0) -> 0 | CX137: =IF($O137=$CX$61,$P137,0) -> 0 | CY137: =IF($O137=$CX$61,$R137,0) -> 0
N138: =L138*M138 -> 0 | R138: =P138*Q138 -> 0 | S138: =N138+R138 -> 0 | V138: =IF($K138=$V$61,$L138,0) -> 0 | W138: =IF($K138=$V$61,$N138,0) -> 0 | X138: =IF($K138=$X$61,$L138,0) -> 0 | Y138: =IF($K138=$X$61,$N138,0) -> 0 | Z138: =IF($K138=$Z$61,$L138,0) -> 0 | AA138: =IF($K138=$Z$61,$N138,0) -> 0 | AB138: =IF($K138=$AB$61,$L138,0) -> 0 | AC138: =IF($K138=$AB$61,$N138,0) -> 0 | AD138: =IF($K138=$AD$61,$L138,0) -> 0 | AE138: =IF($K138=$AD$61,$N138,0) -> 0 | AF138: =IF($K138=$AF$61,$L138,0) -> 0 | AG138: =IF($K138=$AF$61,$N138,0) -> 0 | AH138: =IF($K138=$AH$61,$L138,0) -> 0 | AI138: =IF($K138=$AH$61,$N138,0) -> 0 | AJ138: =IF($K138=$AJ$61,$L138,0) -> 0 | AK138: =IF($K138=$AJ$61,$N138,0) -> 0 | AL138: =IF($K138=$AL$61,$L138,0) -> 0 | AM138: =IF($K138=$AL$61,$N138,0) -> 0 | AN138: =IF($K138=$AN$61,$L138,0) -> 0 | AO138: =IF($K138=$AN$61,$N138,0) -> 0 | AP138: =IF($K138=$AP$61,$L138,0) -> 0 | AQ138: =IF($K138=$AP$61,$N138,0) -> 0 | AR138: =IF($K138=$AR$61,$L138,0) -> 0 | AS138: =IF($K138=$AR$61,$N138,0) -> 0 | AT138: =IF($K138=$AT$61,$L138,0) -> 0 | AU138: =IF($K138=$AT$61,$N138,0) -> 0 | AV138: =IF($K138=$AV$61,$L138,0) -> 0 | AW138: =IF($K138=$AV$61,$N138,0) -> 0 | AX138: =IF($K138=$AX$61,$L138,0) -> 0 | AY138: =IF($K138=$AX$61,$N138,0) -> 0 | AZ138: =IF($K138=$AZ$61,$L138,0) -> 0 | BA138: =IF($K138=$AZ$61,$N138,0) -> 0 | BB138: =IF($K138=$BB$61,$L138,0) -> 0 | BC138: =IF($K138=$BB$61,$N138,0) -> 0 | BD138: =IF($O138=$BD$61,$P138,0) -> 0 | BE138: =IF($O138=$BD$61,$R138,0) -> 0 | BF138: =IF($O138=$BF$61,$P138,0) -> 0 | BG138: =IF($O138=$BF$61,$R138,0) -> 0 | BH138: =IF($O138=$BH$61,$P138,0) -> 0 | BI138: =IF($O138=$BH$61,$R138,0) -> 0 | BJ138: =IF($O138=$BJ$61,$P138,0) -> 0 | BK138: =IF($O138=$BJ$61,$R138,0) -> 0 | BL138: =IF($O138=$BL$61,$P138,0) -> 0 | BM138: =IF($O138=$BL$61,$R138,0) -> 0 | BN138: =IF($O138=$BN$61,$P138,0) -> 0 | BO138: =IF($O138=$BN$61,$R138,0) -> 0 | BP138: =IF($O138=$BP$61,$P138,0) -> 0 | BQ138: =IF($O138=$BP$61,$R138,0) -> 0 | BR138: =IF($O138=$BR$61,$P138,0) -> 0 | BS138: =IF($O138=$BR$61,$R138,0) -> 0 | BT138: =IF($O138=$BT$61,$P138,0) -> 0 | BU138: =IF($O138=$BT$61,$R138,0) -> 0 | BV138: =IF($O138=$BV$61,$P138,0) -> 0 | BW138: =IF($O138=$BV$61,$R138,0) -> 0 | BX138: =IF($O138=$BX$61,$P138,0) -> 0 | BY138: =IF($O138=$BX$61,$R138,0) -> 0 | BZ138: =IF($O138=$BZ$61,$P138,0) -> 0 | CA138: =IF($O138=$BZ$61,$R138,0) -> 0 | CB138: =IF($O138=$CB$61,$P138,0) -> 0 | CC138: =IF($O138=$CB$61,$R138,0) -> 0 | CD138: =IF($O138=$CD$61,$P138,0) -> 0 | CE138: =IF($O138=$CD$61,$R138,0) -> 0 | CF138: =IF($O138=$CF$61,$P138,0) -> 0 | CG138: =IF($O138=$CF$61,$R138,0) -> 0 | CH138: =IF($O138=$CH$61,$P138,0) -> 0 | CI138: =IF($O138=$CH$61,$R138,0) -> 0 | CJ138: =IF($O138=$CJ$61,$P138,0) -> 0 | CK138: =IF($O138=$CJ$61,$R138,0) -> 0 | CL138: =IF($O138=$CL$61,$P138,0) -> 0 | CM138: =IF($O138=$CL$61,$R138,0) -> 0 | CN138: =IF($O138=$CN$61,$P138,0) -> 0 | CO138: =IF($O138=$CN$61,$R138,0) -> 0 | CP138: =IF($O138=$CP$61,$P138,0) -> 0 | CQ138: =IF($O138=$CP$61,$R138,0) -> 0 | CR138: =IF($O138=$CR$61,$P138,0) -> 0 | CS138: =IF($O138=$CR$61,$R138,0) -> 0 | CT138: =IF($O138=$CT$61,$P138,0) -> 0 | CU138: =IF($O138=$CT$61,$R138,0) -> 0 | CV138: =IF($O138=$CV$61,$P138,0) -> 0 | CW138: =IF($O138=$CV$61,$R138,0) -> 0 | CX138: =IF($O138=$CX$61,$P138,0) -> 0 | CY138: =IF($O138=$CX$61,$R138,0) -> 0
